Workbook
Name Anyela: Hoja1!$F$42:$F$48
Name Anyela_ACUEDUCTO: Hoja1!$I$19:$I$20
Name Anyela_ACUEDUCTO_DESCENTRALIZADO: Hoja1!$I$26:$I$30
Name Anyela_BOMBEROS_DESCENTRALIZADO: Hoja1!$I$45
Name Anyela_Educacion: Hoja1!$I$4:$I$13
Name Anyela_Educación: Hoja1!$I$4:$I$13
Name Anyela_PROPIOS: Hoja1!$I$33:$I$40
Name Anyela_PROPIOS_LUMINARIAS: Hoja1!$I$49
Name Anyela_SALUD: Hoja1!$I$23
Name Dalila: Hoja1!$F$36
Name Dalila_EMPRESA: Hoja1!$I$54
Name Ingrid: Hoja1!$F$23:$F$28
Name Ingrid_ACUEDUCTO: Hoja1!$K$4:$K$8
Name Ingrid_ACUEDUCTO_DESCENTRALIZADO: Hoja1!$K$37:$K$40
Name Ingrid_EDUCACION: Hoja1!$K$51:$K$55
Name Ingrid_PRIVADO: Hoja1!$K$12:$K$34
Name Ingrid_PROPIOS: Hoja1!$K$43:$K$47
Name Ingrid_SALUD: Hoja1!$K$59:$K$63
Name Paola: Hoja1!$F$4:$F$17
Name Paola____SUPERCEL_EU___: Hoja1!$M$3
Name Paola___SIVA_SISTEMA_INTEGRADO_DE_TRANSPORTE: Hoja1!$M$36
Name Paola_ACUEDUCTO: Hoja1!$M$53
Name Paola_EDUCACION: Hoja1!$M$6:$M$7
Name Paola_EMDUPAR: Hoja1!$M$40
Name Paola_FONVISOCIAL: Hoja1!$M$56
Name Paola_HEAD: Hoja1!$M$10
Name Paola_IDECESAR: Hoja1!$M$44
Name Paola_INDER: Hoja1!$M$59
Name Paola_INDER_SEDE_PERMANENTE_12_DE_OCTUBRE_: Hoja1!$M$13
Name Paola_INTERASEO_S.A.E.S.P: Hoja1!$M$47
Name Paola_MERCABASTOS: Hoja1!$M$63
Name Paola_PRIVADO: Hoja1!$M$16:$M$33
Name Paola_PROPIO_SIN_PARQUE: Hoja1!$M$50
Name Roberto: Hoja1!$D$36:$D$41
Name Roberto_ACUEDUCTO_CENTRALIZADO: Hoja1!$O$11
Name Roberto_ACUEDUCTO_DESCENTRALIZADO: Hoja1!$O$3:$O$5
Name Roberto_CENTRALIZADA: Hoja1!$O$31:$O$32
Name Roberto_EDUCACION: Hoja1!$O$20:$O$28
Name Roberto_PRIVADO: Hoja1!$O$8
Name Roberto_PROPIOS: Hoja1!$O$14:$O$17
Name Roberto_SALUD_DESCENTRALIZADO: Hoja1!$O$31:$O$32
Name Rocio: Hoja1!$D$26:$D$31
Name Rocio_ACUEDUCTO: Hoja1!$Q$3:$Q$6
Name Rocio_ACUEDUCTO_DESCENTRALIZADO: Hoja1!$Q$16
Name Rocio_EDUCACION: Hoja1!$Q$122:$Q$128
Name Rocio_OTROS: Hoja1!$Q$9:$Q$13
Name Rocio_PROPIOS: Hoja1!$Q$19:$Q$118
Name Rocio_SALUD: Hoja1!$Q$131:$Q$137
Name Rosmeri: Hoja1!$D$16:$D$20
Name Rosmeri_ACUEDUCTO_DESCENTRALIZADO: Hoja1!$S$3:$S$4
Name Rosmeri_CONCEJO_DESCENTRALIZADO: Hoja1!$S$77
Name Rosmeri_EDUCACION: Hoja1!$S$85:$S$88
Name Rosmeri_PRIVADO: Hoja1!$S$7:$S$73
Name Rosmeri_PROPIOS: Hoja1!$S$81:$S$82
Name SegmentaciónDeDatos_EJECUTIVO: #N/A
Name SegmentaciónDeDatos_SEGMENTO_CUENTA: #N/A
Name SegmentaciónDeDatos_TITULAR_DE_PAGO: #N/A
Name Yeisver: Hoja1!$D$4:$D$10
Name Yeisver_ACUEDUCTO_DESCENTRALIZADO: Hoja1!$U$4
Name Yeisver_ACUEDUCTO_EMPASO_DESCENTRALIZADO: Hoja1!$U$17

Sheet R.V.
A2: EJECUTIVO | B2: NIC | C2: TITULAR DE PAGO | D2: DESCRIPCIÓN DE SUMINISTRO | E2: SEGMENTO_CUENTA | F2: DOBLE ENTREGA (SI/NO) | G2: Donde se entrega PAQUETE 1 | H2: Donde se entrega PAQUETE 2 | I2: OBSERVACION ADICIONAL | K2: filtro | L2: NIC | M2: CRUCE INFOS | N2: CRUCE CENTRALIZADA
A3: Dalila Michela Bracho Acosta | B3: 5312024 | C3: COMERCIALIZADORA COLANTA | D3: PRIVADO | E3: EMPRESA | F3: NO | G3: DG 21, 54 6 P1 LOC 3B CENTRAL DE ABASTOS | K3: Dalila Michela Bracho AcostaCOMERCIALIZADORA COLANTAEMPRESA | L3: 5312024 | N3: =_xlfn.XLOOKUP(L3,CENTRALIZADAS!A:A,CENTRALIZADAS!C:C) -> #N/A
A4: Paola De la Hoz Bastidas | B4: 1413166 | C4: MUNICIPIO DE VALLEDUPAR | D4: ACUEDUCTO CGTO VALENCIA- CARRET VIA PUEBLOBELLO | E4: ACUEDUCTO | F4: NO | G4: CR 5 No.15- 65 Secretraia Gral _Alcaldia Muncipal | I4: Impresión y entrega direcata por Ventas -Territorial, para revisión previa de Facturación, en cumplimiento a compromisos ante la SSPD. | K4: Paola De la Hoz BastidasMUNICIPIO DE VALLEDUPARACUEDUCTO | L4: 1413166 | M4: =_xlfn.XLOOKUP(L4,INFO!F:F,INFO!K:K) -> 50 | N4: =_xlfn.XLOOKUP(L4,CENTRALIZADAS!A:A,CENTRALIZADAS!C:C) -> #N/A
A5: Paola De la Hoz Bastidas | B5: 5357495 | C5: MUNICIPIO DE VALLEDUPAR | D5: ACDTO CMTARIO LAS RAICES_CGTO LAS RAICES | E5: ACUEDUCTO | F5: NO | G5: CR 5 No.15- 65 Secretraia Gral _Alcaldia Muncipal | I5: Impresión y entrega direcata por Ventas -Territorial, para revisión previa de Facturación, en cumplimiento a compromisos ante la SSPD. | K5: Paola De la Hoz BastidasMUNICIPIO DE VALLEDUPARACUEDUCTO | L5: 5357495 | M5: =_xlfn.XLOOKUP(L5,INFO!F:F,INFO!K:K) -> 26 | N5: =_xlfn.XLOOKUP(L5,CENTRALIZADAS!A:A,CENTRALIZADAS!C:C) -> #N/A
A6: Paola De la Hoz Bastidas | B6: 5358999 | C6: MUNICIPIO DE VALLEDUPAR | D6: ACUEDUCTO GUACOCHE_CGTO GUACOCHE | E6: ACUEDUCTO | F6: NO | G6: CR 5 No.15- 65 Secretraia Gral _Alcaldia Muncipal | I6: Impresión y entrega direcata por Ventas -Territorial, para revisión previa de Facturación, en cumplimiento a compromisos ante la SSPD. | K6: Paola De la Hoz BastidasMUNICIPIO DE VALLEDUPARACUEDUCTO | L6: 5358999 | M6: =_xlfn.XLOOKUP(L6,INFO!F:F,INFO!K:K) -> 26 | N6: =_xlfn.XLOOKUP(L6,CENTRALIZADAS!A:A,CENTRALIZADAS!C:C) -> #N/A
A7: Paola De la Hoz Bastidas | B7: 5359176 | C7: MUNICIPIO DE VALLEDUPAR | D7: ACUEDUCTO BOMBA EL JABO_EL JAVO RURAL | E7: ACUEDUCTO | F7: NO | G7: CR 5 No.15- 65 Secretraia Gral _Alcaldia Muncipal | I7: Impresión y entrega direcata por Ventas -Territorial, para revisión previa de Facturación, en cumplimiento a compromisos ante la SSPD. | K7: Paola De la Hoz BastidasMUNICIPIO DE VALLEDUPARACUEDUCTO | L7: 5359176 | M7: =_xlfn.XLOOKUP(L7,INFO!F:F,INFO!K:K) -> 26 | N7: =_xlfn.XLOOKUP(L7,CENTRALIZADAS!A:A,CENTRALIZADAS!C:C) -> #N/A
A8: Paola De la Hoz Bastidas | B8: 5359669 | C8: MUNICIPIO DE VALLEDUPAR | D8: ACUEDUCTO LOS CALABAZOS_CGTO LOS CALABAZOS | E8: ACUEDUCTO | F8: NO | G8: CR 5 No.15- 65 Secretraia Gral _Alcaldia Muncipal | I8: Impresión y entrega direcata por Ventas -Territorial, para revisión previa de Facturación, en cumplimiento a compromisos ante la SSPD. | K8: Paola De la Hoz BastidasMUNICIPIO DE VALLEDUPARACUEDUCTO | L8: 5359669 | M8: =_xlfn.XLOOKUP(L8,INFO!F:F,INFO!K:K) -> 38 | N8: =_xlfn.XLOOKUP(L8,CENTRALIZADAS!A:A,CENTRALIZADAS!C:C) -> #N/A
A9: Paola De la Hoz Bastidas | B9: 5360243 | C9: MUNICIPIO DE VALLEDUPAR | D9: ACUEDUCTO AGUAS BLANCAS_CGTO AGUAS BLANCAS | E9: ACUEDUCTO | F9: NO | G9: CR 5 No.15- 65 Secretraia Gral _Alcaldia Muncipal | I9: Impresión y entrega direcata por Ventas -Territorial, para revisión previa de Facturación, en cumplimiento a compromisos ante la SSPD. | K9: Paola De la Hoz BastidasMUNICIPIO DE VALLEDUPARACUEDUCTO | L9: 5360243 | M9: =_xlfn.XLOOKUP(L9,INFO!F:F,INFO!K:K) -> 27 | N9: =_xlfn.XLOOKUP(L9,CENTRALIZADAS!A:A,CENTRALIZADAS!C:C) -> #N/A
A10: Paola De la Hoz Bastidas | B10: 5360245 | C10: MUNICIPIO DE VALLEDUPAR | D10: ACUEDUCTO AGUAS BLANCAS_CGTO AGUAS BLANCAS | E10: ACUEDUCTO | F10: NO | G10: CR 5 No.15- 65 Secretraia Gral _Alcaldia Muncipal | I10: Impresión y entrega direcata por Ventas -Territorial, para revisión previa de Facturación, en cumplimiento a compromisos ante la SSPD. | K10: Paola De la Hoz BastidasMUNICIPIO DE VALLEDUPARACUEDUCTO | L10: 5360245 | M10: =_xlfn.XLOOKUP(L10,INFO!F:F,INFO!K:K) -> 27 | N10: =_xlfn.XLOOKUP(L10,CENTRALIZADAS!A:A,CENTRALIZADAS!C:C) -> #N/A
A11: Paola De la Hoz Bastidas | B11: 5361891 | C11: MUNICIPIO DE VALLEDUPAR | D11: ACUEDUCTO GUAYMARAL_CGTO GUAIMARAL | E11: ACUEDUCTO | F11: NO | G11: CR 5 No.15- 65 Secretraia Gral _Alcaldia Muncipal | I11: Impresión y entrega direcata por Ventas -Territorial, para revisión previa de Facturación, en cumplimiento a compromisos ante la SSPD. | K11: Paola De la Hoz BastidasMUNICIPIO DE VALLEDUPARACUEDUCTO | L11: 5361891 | M11: =_xlfn.XLOOKUP(L11,INFO!F:F,INFO!K:K) -> 27 | N11: =_xlfn.XLOOKUP(L11,CENTRALIZADAS!A:A,CENTRALIZADAS!C:C) -> #N/A
A12: Paola De la Hoz Bastidas | B12: 5361969 | C12: MUNICIPIO DE VALLEDUPAR | D12: ACUEDUCTO SAN MARTIN_CGTO EL PERRO | E12: ACUEDUCTO | F12: NO | G12: CR 5 No.15- 65 Secretraia Gral _Alcaldia Muncipal | I12: Impresión y entrega direcata por Ventas -Territorial, para revisión previa de Facturación, en cumplimiento a compromisos ante la SSPD. | K12: Paola De la Hoz BastidasMUNICIPIO DE VALLEDUPARACUEDUCTO | L12: 5361969 | M12: =_xlfn.XLOOKUP(L12,INFO!F:F,INFO!K:K) -> 27 | N12: =_xlfn.XLOOKUP(L12,CENTRALIZADAS!A:A,CENTRALIZADAS!C:C) -> #N/A
A13: Paola De la Hoz Bastidas | B13: 6238148 | C13: MUNICIPIO DE VALLEDUPAR | D13: ACDTO BOMBA LA VEGA _CGTO LA VEGA ARRIBA | E13: ACUEDUCTO | F13: NO | G13: CR 5 No.15- 65 Secretraia Gral _Alcaldia Muncipal | I13: Impresión y entrega direcata por Ventas -Territorial, para revisión previa de Facturación, en cumplimiento a compromisos ante la SSPD. | K13: Paola De la Hoz BastidasMUNICIPIO DE VALLEDUPARACUEDUCTO | L13: 6238148 | M13: =_xlfn.XLOOKUP(L13,INFO!F:F,INFO!K:K) -> 38 | N13: =_xlfn.XLOOKUP(L13,CENTRALIZADAS!A:A,CENTRALIZADAS!C:C) -> #N/A
A14: Paola De la Hoz Bastidas | B14: 6634302 | C14: MUNICIPIO DE VALLEDUPAR | D14: ACUEDUCTO DE ATANQUEZ_CGTO ATANQUEZ | E14: ACUEDUCTO | F14: NO | G14: CR 5 No.15- 65 Secretraia Gral _Alcaldia Muncipal | I14: Impresión y entrega direcata por Ventas -Territorial, para revisión previa de Facturación, en cumplimiento a compromisos ante la SSPD. | K14: Paola De la Hoz BastidasMUNICIPIO DE VALLEDUPARACUEDUCTO | L14: 6634302 | M14: =_xlfn.XLOOKUP(L14,INFO!F:F,INFO!K:K) -> 26 | N14: =_xlfn.XLOOKUP(L14,CENTRALIZADAS!A:A,CENTRALIZADAS!C:C) -> #N/A
A15: Paola De la Hoz Bastidas | B15: 6634330 | C15: MUNICIPIO DE VALLEDUPAR | D15: POZOS PROFUNDOS LAS CASITAS_VALLEDUPAR | E15: ACUEDUCTO | F15: NO | G15: CR 5 No.15- 65 Secretraia Gral _Alcaldia Muncipal | I15: Impresión y entrega direcata por Ventas -Territorial, para revisión previa de Facturación, en cumplimiento a compromisos ante la SSPD. | K15: Paola De la Hoz BastidasMUNICIPIO DE VALLEDUPARACUEDUCTO | L15: 6634330 | M15: =_xlfn.XLOOKUP(L15,INFO!F:F,INFO!K:K) -> 10 | N15: =_xlfn.XLOOKUP(L15,CENTRALIZADAS!A:A,CENTRALIZADAS!C:C) -> #N/A
... A332: Paola De la Hoz Bastidas | B332: 7958047 | C332: MUNICIPIO DE VALLEDUPAR | D332: PARQUE LA PROVINCIA_VALLEDUPAR | E332: MERCABASTOS | F332: NO | G332: CR 5 No.15- 65 Secretraia Gral _Alcaldia Muncipal | I332: Impresión y entrega direcata por Ventas -Territorial, para revisión previa de Facturación, en cumplimiento a compromisos ante la SSPD. | K332: Paola De la Hoz BastidasMUNICIPIO DE VALLEDUPARMERCABASTOS | L332: 7958047 | M332: =_xlfn.XLOOKUP(L332,INFO!F:F,INFO!K:K) -> 50 | N332: =_xlfn.XLOOKUP(L332,CENTRALIZADAS!A:A,CENTRALIZADAS!C:C) -> #N/A
A333: Paola De la Hoz Bastidas | B333: 5300000 | C333: HOSPITAL EDUARDO ARREDONDO DAZA | D333: PUESTO DE SALUD DE LA MESA- | E333: HEAD | F333: NO | G333: CL 44, 20 30 PUESTO DE SALUD VILLA LEONOR VILLA LEONOR VALLEDUPAR | K333: Paola De la Hoz BastidasHOSPITAL EDUARDO ARREDONDO DAZAHEAD | L333: 5300000 | N333: =_xlfn.XLOOKUP(L333,CENTRALIZADAS!A:A,CENTRALIZADAS!C:C) -> #N/A
A334: Paola De la Hoz Bastidas | B334: 5300010 | C334: HOSPITAL EDUARDO ARREDONDO DAZA | D334: PTO. SALUD B. EL CARMEN | E334: HEAD | F334: NO | G334: CL 44, 20 30 PUESTO DE SALUD VILLA LEONOR VILLA LEONOR VALLEDUPAR | K334: Paola De la Hoz BastidasHOSPITAL EDUARDO ARREDONDO DAZAHEAD | L334: 5300010 | N334: =_xlfn.XLOOKUP(L334,CENTRALIZADAS!A:A,CENTRALIZADAS!C:C) -> #N/A
A335: Paola De la Hoz Bastidas | B335: 5300017 | C335: HOSPITAL EDUARDO ARREDONDO DAZA | D335: PUESTO DE SALUD C.D.V. MANANTIAL | E335: HEAD | F335: NO | G335: CL 44, 20 30 PUESTO DE SALUD VILLA LEONOR VILLA LEONOR VALLEDUPAR | K335: Paola De la Hoz BastidasHOSPITAL EDUARDO ARREDONDO DAZAHEAD | L335: 5300017 | N335: =_xlfn.XLOOKUP(L335,CENTRALIZADAS!A:A,CENTRALIZADAS!C:C) -> #N/A
A336: Paola De la Hoz Bastidas | B336: 5302684 | C336: HOSPITAL EDUARDO ARREDONDO DAZA | D336: PUESTO DE SALUD DE RIO SECO | E336: HEAD | F336: NO | G336: CL 44, 20 30 PUESTO DE SALUD VILLA LEONOR VILLA LEONOR VALLEDUPAR | K336: Paola De la Hoz BastidasHOSPITAL EDUARDO ARREDONDO DAZAHEAD | L336: 5302684 | N336: =_xlfn.XLOOKUP(L336,CENTRALIZADAS!A:A,CENTRALIZADAS!C:C) -> #N/A
A337: Paola De la Hoz Bastidas | B337: 5303424 | C337: HOSPITAL EDUARDO ARREDONDO DAZA | D337: PUESTO DE SALUD VICTORIA | E337: HEAD | F337: NO | G337: CL 44, 20 30 PUESTO DE SALUD VILLA LEONOR VILLA LEONOR VALLEDUPAR | K337: Paola De la Hoz BastidasHOSPITAL EDUARDO ARREDONDO DAZAHEAD | L337: 5303424 | N337: =_xlfn.XLOOKUP(L337,CENTRALIZADAS!A:A,CENTRALIZADAS!C:C) -> #N/A
A338: Paola De la Hoz Bastidas | B338: 5308710 | C338: HOSPITAL EDUARDO ARREDONDO DAZA | D338: PUESTO DE SALUD LA NEVADA | E338: HEAD | F338: NO | G338: CL 44, 20 30 PUESTO DE SALUD VILLA LEONOR VILLA LEONOR VALLEDUPAR | K338: Paola De la Hoz BastidasHOSPITAL EDUARDO ARREDONDO DAZAHEAD | L338: 5308710 | N338: =_xlfn.XLOOKUP(L338,CENTRALIZADAS!A:A,CENTRALIZADAS!C:C) -> #N/A
A339: Paola De la Hoz Bastidas | B339: 5309634 | C339: HOSPITAL EDUARDO ARREDONDO DAZA | D339: HOSPITAL EDO. ARREDONDO DAZA -VILLALEONOR | E339: HEAD | F339: NO | G339: CL 44, 20 30 PUESTO DE SALUD VILLA LEONOR VILLA LEONOR VALLEDUPAR | K339: Paola De la Hoz BastidasHOSPITAL EDUARDO ARREDONDO DAZAHEAD | L339: 5309634 | N339: =_xlfn.XLOOKUP(L339,CENTRALIZADAS!A:A,CENTRALIZADAS!C:C) -> #N/A
A340: Paola De la Hoz Bastidas | B340: 5313114 | C340: HOSPITAL EDUARDO ARREDONDO DAZA | D340: PUESTO DE SALUD LAS VEGAS | E340: HEAD | F340: NO | G340: CL 44, 20 30 PUESTO DE SALUD VILLA LEONOR VILLA LEONOR VALLEDUPAR | K340: Paola De la Hoz BastidasHOSPITAL EDUARDO ARREDONDO DAZAHEAD | L340: 5313114 | N340: =_xlfn.XLOOKUP(L340,CENTRALIZADAS!A:A,CENTRALIZADAS!C:C) -> #N/A
A341: Paola De la Hoz Bastidas | B341: 5319050 | C341: HOSPITAL EDUARDO ARREDONDO DAZA | D341: PUESTO DE SALUD GUACOCHE | E341: HEAD | F341: NO | G341: CL 44, 20 30 PUESTO DE SALUD VILLA LEONOR VILLA LEONOR VALLEDUPAR | K341: Paola De la Hoz BastidasHOSPITAL EDUARDO ARREDONDO DAZAHEAD | L341: 5319050 | N341: =_xlfn.XLOOKUP(L341,CENTRALIZADAS!A:A,CENTRALIZADAS!C:C) -> #N/A
A342: Paola De la Hoz Bastidas | B342: 5354933 | C342: HOSPITAL EDUARDO ARREDONDO DAZA | D342: PUESTO DE SALUD SAN JOAQUIN | E342: HEAD | F342: NO | G342: CL 44, 20 30 PUESTO DE SALUD VILLA LEONOR VILLA LEONOR VALLEDUPAR | K342: Paola De la Hoz BastidasHOSPITAL EDUARDO ARREDONDO DAZAHEAD | L342: 5354933 | N342: =_xlfn.XLOOKUP(L342,CENTRALIZADAS!A:A,CENTRALIZADAS!C:C) -> #N/A
A343: Paola De la Hoz Bastidas | B343: 5357269 | C343: HOSPITAL EDUARDO ARREDONDO DAZA | D343: PUESTO DE SALUD PATILLAL | E343: HEAD | F343: NO | G343: CL 44, 20 30 PUESTO DE SALUD VILLA LEONOR VILLA LEONOR VALLEDUPAR | K343: Paola De la Hoz BastidasHOSPITAL EDUARDO ARREDONDO DAZAHEAD | L343: 5357269 | N343: =_xlfn.XLOOKUP(L343,CENTRALIZADAS!A:A,CENTRALIZADAS!C:C) -> #N/A
A344: Paola De la Hoz Bastidas | B344: 5357554 | C344: HOSPITAL EDUARDO ARREDONDO DAZA | D344: PUESTO DE SALUD LA MINA | E344: HEAD | F344: NO | G344: CL 44, 20 30 PUESTO DE SALUD VILLA LEONOR VILLA LEONOR VALLEDUPAR | K344: Paola De la Hoz BastidasHOSPITAL EDUARDO ARREDONDO DAZAHEAD | L344: 5357554 | N344: =_xlfn.XLOOKUP(L344,CENTRALIZADAS!A:A,CENTRALIZADAS!C:C) -> #N/A
... A414: Paola De la Hoz Bastidas | B414: 5330743 | C414: SAS HOTEL UCLA CENTER CONS EN GESTION FINANCIERA Y DE RES | D414: SAS HOTEL UCLA CENTER CONS EN GESTION FINANCIERA Y DE RES | E414: PRIVADO | F414: NO | G414: CL 22C 18A 31 _SIMON BOLIVAR | K414: Paola De la Hoz BastidasSAS HOTEL UCLA CENTER CONS EN GESTION FINANCIERA Y DE RESPRIVADO | L414: 5330743 | N414: =_xlfn.XLOOKUP(L414,CENTRALIZADAS!A:A,CENTRALIZADAS!C:C) -> #N/A
A415: Paola De la Hoz Bastidas | B415: 5302399 | C415: FAMISANAR ENTIDAD PROMOTORA DE SALUD | D415: FAMISANAR ENTIDAD PROMOTORA DE SALUD | E415: EDUCACION | F415: NO | G415: CL 17 12 74 _LOPERENA | I415: Centralizada | K415: Paola De la Hoz BastidasFAMISANAR ENTIDAD PROMOTORA DE SALUDEDUCACION | L415: 5302399 | N415: =_xlfn.XLOOKUP(L415,CENTRALIZADAS!A:A,CENTRALIZADAS!C:C) -> SSGMTO
A416: Roberto Pavajeau Hernandez | B416: 5802788 | C416: Municipio de Algarrobo | D416: COL DPAL RAFAEL NUÑEZ | E416: EDUCACION | F416: NO | G416: Carrera 9 # 8 - 44 - Parque Central, Algarrobo-Magdalena | K416: Roberto Pavajeau HernandezMunicipio de AlgarroboEDUCACION | L416: 5802788 | N416: =_xlfn.XLOOKUP(L416,CENTRALIZADAS!A:A,CENTRALIZADAS!C:C) -> #N/A
A417: Roberto Pavajeau Hernandez | B417: 5808911 | C417: Municipio de Algarrobo | D417: COLE DPTAL 26 DE JULIO | E417: EDUCACION | F417: NO | G417: Carrera 9 # 8 - 44 - Parque Central, Algarrobo-Magdalena | K417: Roberto Pavajeau HernandezMunicipio de AlgarroboEDUCACION | L417: 5808911 | N417: =_xlfn.XLOOKUP(L417,CENTRALIZADAS!A:A,CENTRALIZADAS!C:C) -> #N/A
A418: Roberto Pavajeau Hernandez | B418: 5809128 | C418: Municipio de Algarrobo | D418: INS EDUCATIVO ALGARROBO | E418: EDUCACION | F418: NO | G418: Carrera 9 # 8 - 44 - Parque Central, Algarrobo-Magdalena | K418: Roberto Pavajeau HernandezMunicipio de AlgarroboEDUCACION | L418: 5809128 | N418: =_xlfn.XLOOKUP(L418,CENTRALIZADAS!A:A,CENTRALIZADAS!C:C) -> #N/A
A419: Roberto Pavajeau Hernandez | B419: 5809277 | C419: Municipio de Algarrobo | D419: COLEGIO MIRAFLOREZ | E419: EDUCACION | F419: NO | G419: Carrera 9 # 8 - 44 - Parque Central, Algarrobo-Magdalena | K419: Roberto Pavajeau HernandezMunicipio de AlgarroboEDUCACION | L419: 5809277 | N419: =_xlfn.XLOOKUP(L419,CENTRALIZADAS!A:A,CENTRALIZADAS!C:C) -> #N/A
A420: Roberto Pavajeau Hernandez | B420: 5809837 | C420: Municipio de Algarrobo | D420: COL SAGRADO CORAZÓN | E420: EDUCACION | F420: NO | G420: Carrera 9 # 8 - 44 - Parque Central, Algarrobo-Magdalena | K420: Roberto Pavajeau HernandezMunicipio de AlgarroboEDUCACION | L420: 5809837 | N420: =_xlfn.XLOOKUP(L420,CENTRALIZADAS!A:A,CENTRALIZADAS!C:C) -> #N/A
A421: Roberto Pavajeau Hernandez | B421: 5809970 | C421: Municipio de Algarrobo | D421: ESC LOMA DEL BALSAMO | E421: EDUCACION | F421: NO | G421: Carrera 9 # 8 - 44 - Parque Central, Algarrobo-Magdalena | K421: Roberto Pavajeau HernandezMunicipio de AlgarroboEDUCACION | L421: 5809970 | N421: =_xlfn.XLOOKUP(L421,CENTRALIZADAS!A:A,CENTRALIZADAS!C:C) -> #N/A
A422: Roberto Pavajeau Hernandez | B422: 6316672 | C422: Municipio de Algarrobo | D422: COLE MARIA AUXILIADORA | E422: EDUCACION | F422: NO | G422: Carrera 9 # 8 - 44 - Parque Central, Algarrobo-Magdalena | K422: Roberto Pavajeau HernandezMunicipio de AlgarroboEDUCACION | L422: 6316672 | N422: =_xlfn.XLOOKUP(L422,CENTRALIZADAS!A:A,CENTRALIZADAS!C:C) -> #N/A
A423: Roberto Pavajeau Hernandez | B423: 6649200 | C423: Municipio de Algarrobo | D423: LA LOMA DEL BALSAMO ZONA RURAL | E423: EDUCACION | F423: NO | G423: Carrera 9 # 8 - 44 - Parque Central, Algarrobo-Magdalena | K423: Roberto Pavajeau HernandezMunicipio de AlgarroboEDUCACION | L423: 6649200 | N423: =_xlfn.XLOOKUP(L423,CENTRALIZADAS!A:A,CENTRALIZADAS!C:C) -> #N/A
A424: Roberto Pavajeau Hernandez | B424: 6892346 | C424: Municipio de Algarrobo | D424: CENTRO EDUCATIVO ESTACIÓN LLERAS | E424: EDUCACION | F424: NO | G424: Carrera 9 # 8 - 44 - Parque Central, Algarrobo-Magdalena | K424: Roberto Pavajeau HernandezMunicipio de AlgarroboEDUCACION | L424: 6892346 | N424: =_xlfn.XLOOKUP(L424,CENTRALIZADAS!A:A,CENTRALIZADAS!C:C) -> #N/A
A425: Roberto Pavajeau Hernandez | B425: 6918563 | C425: Municipio de Algarrobo | D425: ESC INMACULADA CONCEPCIÓN RIOMAR | E425: EDUCACION | F425: NO | G425: Carrera 9 # 8 - 44 - Parque Central, Algarrobo-Magdalena | K425: Roberto Pavajeau HernandezMunicipio de AlgarroboEDUCACION | L425: 6918563 | N425: =_xlfn.XLOOKUP(L425,CENTRALIZADAS!A:A,CENTRALIZADAS!C:C) -> #N/A
A426: Roberto Pavajeau Hernandez | B426: 7502742 | C426: Municipio de Algarrobo | D426: ESC RAFAEL NUÑEZ | E426: EDUCACION | F426: NO | G426: Carrera 9 # 8 - 44 - Parque Central, Algarrobo-Magdalena | K426: Roberto Pavajeau HernandezMunicipio de AlgarroboEDUCACION | L426: 7502742 | N426: =_xlfn.XLOOKUP(L426,CENTRALIZADAS!A:A,CENTRALIZADAS!C:C) -> #N/A
A427: Roberto Pavajeau Hernandez | B427: 7547292 | C427: Municipio de Algarrobo | D427: COLEGIO BELLAVISTA | E427: EDUCACION | F427: NO | G427: Carrera 9 # 8 - 44 - Parque Central, Algarrobo-Magdalena | K427: Roberto Pavajeau HernandezMunicipio de AlgarroboEDUCACION | L427: 7547292 | N427: =_xlfn.XLOOKUP(L427,CENTRALIZADAS!A:A,CENTRALIZADAS!C:C) -> #N/A
... A630: Rosmeri Rivera Rodriguez | B630: 1380305 | C630: MUNICIPIO DE LA PAZ | D630: COLEGIO CIRO PUPO MARTINEZ | E630: EDUCACION | F630: NO | G630: CR 9 6 36 - LA PAZ | K630: Rosmeri Rivera RodriguezMUNICIPIO DE LA PAZEDUCACION | L630: 1380305 | N630: =_xlfn.XLOOKUP(L630,CENTRALIZADAS!A:A,CENTRALIZADAS!C:C) -> #N/A
A631: Rosmeri Rivera Rodriguez | B631: 5824755 | C631: HOSPITAL MARINO ZULETA RAMIREZ | E631: EDUCACION | F631: NO | G631: CR 6 CL 6 25 - LA PAZ | K631: Rosmeri Rivera RodriguezHOSPITAL MARINO ZULETA RAMIREZEDUCACION | L631: 5824755 | N631: =_xlfn.XLOOKUP(L631,CENTRALIZADAS!A:A,CENTRALIZADAS!C:C) -> #N/A
A632: Rosmeri Rivera Rodriguez | B632: 5858057 | C632: HOSPITAL MARINO ZULETA RAMIREZ | E632: EDUCACION | F632: NO | G632: CR 6 CL 6 25 - LA PAZ | K632: Rosmeri Rivera RodriguezHOSPITAL MARINO ZULETA RAMIREZEDUCACION | L632: 5858057 | N632: =_xlfn.XLOOKUP(L632,CENTRALIZADAS!A:A,CENTRALIZADAS!C:C) -> #N/A
A633: Rosmeri Rivera Rodriguez | B633: 5858751 | C633: HOSPITAL JOSE ANTONIO SOCARRAS ESE | E633: EDUCACION | F633: NO | G633: CR 6 2F 12 - MANAURE CESAR | K633: Rosmeri Rivera RodriguezHOSPITAL JOSE ANTONIO SOCARRAS ESEEDUCACION | L633: 5858751 | N633: =_xlfn.XLOOKUP(L633,CENTRALIZADAS!A:A,CENTRALIZADAS!C:C) -> #N/A
A634: Rosmeri Rivera Rodriguez | B634: 5839319 | C634: EMPAZ | E634: ACUEDUCTO_DESCENTRALIZADO | F634: NO | G634: CR 9 6 36 - LA PAZ | K634: Rosmeri Rivera RodriguezEMPAZ ACUEDUCTO_DESCENTRALIZADO | L634: 5839319 | N634: =_xlfn.XLOOKUP(L634,CENTRALIZADAS!A:A,CENTRALIZADAS!C:C) -> #N/A
A635: Rosmeri Rivera Rodriguez | B635: 5840545 | C635: CONCEJO MUNICIPAL | E635: CONCEJO_DESCENTRALIZADO | F635: NO | G635: CL 8A CR 7 5 - LA PAZ | I635: Se envía por correo electrónico | K635: Rosmeri Rivera RodriguezCONCEJO MUNICIPALCONCEJO_DESCENTRALIZADO | L635: 5840545 | N635: =_xlfn.XLOOKUP(L635,CENTRALIZADAS!A:A,CENTRALIZADAS!C:C) -> #N/A
A636: Rosmeri Rivera Rodriguez | B636: 5808643 | C636: ESPUMA ESP | E636: ACUEDUCTO_DESCENTRALIZADO | F636: NO | G636: CR 1 CL 3 90 - MANAURE CESAR | I636: Se envía por correo electrónico | K636: Rosmeri Rivera RodriguezESPUMA ESPACUEDUCTO_DESCENTRALIZADO | L636: 5808643 | N636: =_xlfn.XLOOKUP(L636,CENTRALIZADAS!A:A,CENTRALIZADAS!C:C) -> #N/A
A637: Rosmeri Rivera Rodriguez | B637: 5800118 | C637: MUNICIPIO DE MANAURE BALCON DEL CESAR | D637: ESCUELA JUAN XXII | E637: EDUCACION | F637: NO | G637: CL 3 6A 68 - MANAURE CESAR | K637: Rosmeri Rivera RodriguezMUNICIPIO DE MANAURE BALCON DEL CESAREDUCACION | L637: 5800118 | N637: =_xlfn.XLOOKUP(L637,CENTRALIZADAS!A:A,CENTRALIZADAS!C:C) -> #N/A
A638: Rosmeri Rivera Rodriguez | B638: 5800119 | C638: MUNICIPIO DE MANAURE BALCON DEL CESAR | D638: ESCUELA MARIA AUXILIADORA | E638: EDUCACION | F638: NO | G638: CL 3 6A 68 - MANAURE CESAR | K638: Rosmeri Rivera RodriguezMUNICIPIO DE MANAURE BALCON DEL CESAREDUCACION | L638: 5800119 | N638: =_xlfn.XLOOKUP(L638,CENTRALIZADAS!A:A,CENTRALIZADAS!C:C) -> #N/A
A639: Rosmeri Rivera Rodriguez | B639: 5808641 | C639: MUNICIPIO DE MANAURE BALCON DEL CESAR | D639: ESCUELA NUEVA S DEL L | E639: EDUCACION | F639: NO | G639: CL 3 6A 68 - MANAURE CESAR | K639: Rosmeri Rivera RodriguezMUNICIPIO DE MANAURE BALCON DEL CESAREDUCACION | L639: 5808641 | N639: =_xlfn.XLOOKUP(L639,CENTRALIZADAS!A:A,CENTRALIZADAS!C:C) -> #N/A
A640: Rosmeri Rivera Rodriguez | B640: 5808647 | C640: MUNICIPIO DE MANAURE BALCON DEL CESAR | D640: ESCUELA ANEXA | E640: EDUCACION | F640: NO | G640: CL 3 6A 68 - MANAURE CESAR | K640: Rosmeri Rivera RodriguezMUNICIPIO DE MANAURE BALCON DEL CESAREDUCACION | L640: 5808647 | N640: =_xlfn.XLOOKUP(L640,CENTRALIZADAS!A:A,CENTRALIZADAS!C:C) -> #N/A
A641: Rosmeri Rivera Rodriguez | B641: 5808649 | C641: MUNICIPIO DE MANAURE BALCON DEL CESAR | D641: NORMAL MARIA INMACULADA | E641: EDUCACION | F641: NO | G641: CL 3 6A 68 - MANAURE CESAR | K641: Rosmeri Rivera RodriguezMUNICIPIO DE MANAURE BALCON DEL CESAREDUCACION | L641: 5808649 | N641: =_xlfn.XLOOKUP(L641,CENTRALIZADAS!A:A,CENTRALIZADAS!C:C) -> #N/A
A642: Rosmeri Rivera Rodriguez | B642: 5808651 | C642: MUNICIPIO DE MANAURE BALCON DEL CESAR | D642: CONCENTRACION DESARROLLO RURAL | E642: EDUCACION | F642: NO | G642: CL 3 6A 68 - MANAURE CESAR | K642: Rosmeri Rivera RodriguezMUNICIPIO DE MANAURE BALCON DEL CESAREDUCACION | L642: 5808651 | N642: =_xlfn.XLOOKUP(L642,CENTRALIZADAS!A:A,CENTRALIZADAS!C:C) -> #N/A
A643: Rosmeri Rivera Rodriguez | B643: 7904766 | C643: MUNICIPIO DE MANAURE BALCON DEL CESAR | D643: CONCENTRACION DESARROLLO RURAL | E643: EDUCACION | F643: NO | G643: CL 3 6A 68 - MANAURE CESAR | K643: Rosmeri Rivera RodriguezMUNICIPIO DE MANAURE BALCON DEL CESAREDUCACION | L643: 7904766 | N643: =_xlfn.XLOOKUP(L643,CENTRALIZADAS!A:A,CENTRALIZADAS!C:C) -> #N/A
A644: Rosmeri Rivera Rodriguez | B644: 5858769 | C644: MUNICIPIO DE MANAURE BALCON DEL CESAR | D644: NUESTRA SEÑORA DEL CARMEN | E644: EDUCACION | F644: NO | G644: CL 3 6A 68 - MANAURE CESAR | K644: Rosmeri Rivera RodriguezMUNICIPIO DE MANAURE BALCON DEL CESAREDUCACION | L644: 5858769 | N644: =_xlfn.XLOOKUP(L644,CENTRALIZADAS!A:A,CENTRALIZADAS!C:C) -> #N/A
A645: Rosmeri Rivera Rodriguez | B645: 6806610 | C645: MUNICIPIO DE MANAURE BALCON DEL CESAR | D645: ESCUELA RURAL | E645: EDUCACION | F645: NO | G645: CL 3 6A 68 - MANAURE CESAR | K645: Rosmeri Rivera RodriguezMUNICIPIO DE MANAURE BALCON DEL CESAREDUCACION | L645: 6806610 | N645: =_xlfn.XLOOKUP(L645,CENTRALIZADAS!A:A,CENTRALIZADAS!C:C) -> #N/A
A646: Rosmeri Rivera Rodriguez | B646: 7971775 | C646: MUNICIPIO DE MANAURE BALCON DEL CESAR | D646: ESCUELA VEREDA CANADA | E646: EDUCACION | F646: NO | G646: CL 3 6A 68 - MANAURE CESAR | K646: Rosmeri Rivera RodriguezMUNICIPIO DE MANAURE BALCON DEL CESAREDUCACION | L646: 7971775 | N646: =_xlfn.XLOOKUP(L646,CENTRALIZADAS!A:A,CENTRALIZADAS!C:C) -> #N/A
A647: Rosmeri Rivera Rodriguez | B647: 7971974 | C647: MUNICIPIO DE MANAURE BALCON DEL CESAR | D647: COLEGIO SAN ANTONIO | E647: EDUCACION | F647: NO | G647: CL 3 6A 68 - MANAURE CESAR | K647: Rosmeri Rivera RodriguezMUNICIPIO DE MANAURE BALCON DEL CESAREDUCACION | L647: 7971974 | N647: =_xlfn.XLOOKUP(L647,CENTRALIZADAS!A:A,CENTRALIZADAS!C:C) -> #N/A
A648: Rosmeri Rivera Rodriguez | B648: 7971724 | C648: MUNICIPIO DE MANAURE BALCON DEL CESAR | D648: COLEGIO VEREDA CASA GRANDE | E648: EDUCACION | F648: NO | G648: CL 3 6A 68 - MANAURE CESAR | K648: Rosmeri Rivera RodriguezMUNICIPIO DE MANAURE BALCON DEL CESAREDUCACION | L648: 7971724 | N648: =_xlfn.XLOOKUP(L648,CENTRALIZADAS!A:A,CENTRALIZADAS!C:C) -> #N/A
... A665: Rosmeri Rivera Rodriguez | B665: 5858448 | C665: MUNICIPIO DE MANAURE BALCON DEL CESAR | D665: CENTRO RECREACIONAL LOS KIOSKOS | E665: PROPIOS | F665: NO | G665: CL 3 6A 68 - MANAURE CESAR | K665: Rosmeri Rivera RodriguezMUNICIPIO DE MANAURE BALCON DEL CESARPROPIOS | L665: 5858448 | N665: =_xlfn.XLOOKUP(L665,CENTRALIZADAS!A:A,CENTRALIZADAS!C:C) -> #N/A
A666: Rosmeri Rivera Rodriguez | B666: 5309640 | C666: PROPIEDAD HORIZONTAL ED GALERIA POPULAR | E666: PRIVADO | F666: NO | G666: CR 7 18A 40 ADMINISTRACION - VALLEDUPAR | I666: Se envía por correo electrónico | K666: Rosmeri Rivera RodriguezPROPIEDAD HORIZONTAL ED GALERIA POPULARPRIVADO | L666: 5309640 | N666: =_xlfn.XLOOKUP(L666,CENTRALIZADAS!A:A,CENTRALIZADAS!C:C) -> #N/A
A667: Rosmeri Rivera Rodriguez | B667: 5309641 | C667: PROPIEDAD HORIZONTAL ED GALERIA POPULAR | E667: PRIVADO | F667: NO | G667: CR 7 18A 40 ADMINISTRACION - VALLEDUPAR | I667: Se envía por correo electrónico | K667: Rosmeri Rivera RodriguezPROPIEDAD HORIZONTAL ED GALERIA POPULARPRIVADO | L667: 5309641 | N667: =_xlfn.XLOOKUP(L667,CENTRALIZADAS!A:A,CENTRALIZADAS!C:C) -> #N/A
A668: Rosmeri Rivera Rodriguez | B668: 5332064 | C668: PROPIEDAD HORIZONTAL ED GALERIA POPULAR | E668: PRIVADO | F668: NO | G668: CR 7 18A 40 ADMINISTRACION - VALLEDUPAR | I668: Se envía por correo electrónico | K668: Rosmeri Rivera RodriguezPROPIEDAD HORIZONTAL ED GALERIA POPULARPRIVADO | L668: 5332064 | N668: =_xlfn.XLOOKUP(L668,CENTRALIZADAS!A:A,CENTRALIZADAS!C:C) -> #N/A
A669: Rosmeri Rivera Rodriguez | B669: 5332065 | C669: PROPIEDAD HORIZONTAL ED GALERIA POPULAR | E669: PRIVADO | F669: NO | G669: CR 7 18A 40 ADMINISTRACION - VALLEDUPAR | I669: Se envía por correo electrónico | K669: Rosmeri Rivera RodriguezPROPIEDAD HORIZONTAL ED GALERIA POPULARPRIVADO | L669: 5332065 | N669: =_xlfn.XLOOKUP(L669,CENTRALIZADAS!A:A,CENTRALIZADAS!C:C) -> #N/A
A670: Rosmeri Rivera Rodriguez | B670: 5333181 | C670: PROPIEDAD HORIZONTAL ED GALERIA POPULAR | E670: PRIVADO | F670: NO | G670: CR 7 18A 40 ADMINISTRACION - VALLEDUPAR | I670: Se envía por correo electrónico | K670: Rosmeri Rivera RodriguezPROPIEDAD HORIZONTAL ED GALERIA POPULARPRIVADO | L670: 5333181 | N670: =_xlfn.XLOOKUP(L670,CENTRALIZADAS!A:A,CENTRALIZADAS!C:C) -> #N/A
A671: Rosmeri Rivera Rodriguez | B671: 5338094 | C671: PROPIEDAD HORIZONTAL ED GALERIA POPULAR | E671: PRIVADO | F671: NO | G671: CR 7 18A 40 ADMINISTRACION - VALLEDUPAR | K671: Rosmeri Rivera RodriguezPROPIEDAD HORIZONTAL ED GALERIA POPULARPRIVADO | L671: 5338094 | N671: =_xlfn.XLOOKUP(L671,CENTRALIZADAS!A:A,CENTRALIZADAS!C:C) -> #N/A
A672: Rosmeri Rivera Rodriguez | B672: 5348677 | C672: CLINICA BUENOS AIRES SAS | D672: CLINICA BUENOS AIRES | E672: PRIVADO | F672: NO | G672: CR 15 14 36 - VALLEDUPAR | I672: Se envía por correo electrónico | K672: Rosmeri Rivera RodriguezCLINICA BUENOS AIRES SASPRIVADO | L672: 5348677 | N672: =_xlfn.XLOOKUP(L672,CENTRALIZADAS!A:A,CENTRALIZADAS!C:C) -> #N/A
A673: Rosmeri Rivera Rodriguez | B673: 6561337 | C673: UNIVERSIDAD DE SANTANDER UDES | E673: PRIVADO | F673: NO | G673: CR 6 14 27 - VALLEDUPAR | I673: Se envía por correo electrónico | K673: Rosmeri Rivera RodriguezUNIVERSIDAD DE SANTANDER UDESPRIVADO | L673: 6561337 | N673: =_xlfn.XLOOKUP(L673,CENTRALIZADAS!A:A,CENTRALIZADAS!C:C) -> #N/A
A674: Rosmeri Rivera Rodriguez | B674: 7536333 | C674: UNIVERSIDAD DE SANTANDER UDES | E674: PRIVADO | F674: NO | G674: CR 6 14 27 - VALLEDUPAR | I674: Se envía por correo electrónico | K674: Rosmeri Rivera RodriguezUNIVERSIDAD DE SANTANDER UDESPRIVADO | L674: 7536333 | N674: =_xlfn.XLOOKUP(L674,CENTRALIZADAS!A:A,CENTRALIZADAS!C:C) -> #N/A
A675: Rosmeri Rivera Rodriguez | B675: 5352184 | C675: UNIVERSIDAD DE SANTANDER UDES | D675: CORP UNIVERSITARIA DE SANTANDER UDES | E675: PRIVADO | F675: NO | G675: CR 6 14 27 - VALLEDUPAR | I675: Se envía por correo electrónico | K675: Rosmeri Rivera RodriguezUNIVERSIDAD DE SANTANDER UDESPRIVADO | L675: 5352184 | N675: =_xlfn.XLOOKUP(L675,CENTRALIZADAS!A:A,CENTRALIZADAS!C:C) -> #N/A
A676: Rosmeri Rivera Rodriguez | B676: 5327630 | C676: FEDERACION NACIONAL DE ARROCEROS FEDEARROZ | E676: PRIVADO | F676: NO | G676: CR 16 CL 21 84 | I676: Se envía por correo electrónico | K676: Rosmeri Rivera RodriguezFEDERACION NACIONAL DE ARROCEROS FEDEARROZPRIVADO | L676: 5327630 | N676: =_xlfn.XLOOKUP(L676,CENTRALIZADAS!A:A,CENTRALIZADAS!C:C) -> #N/A
A677: Rosmeri Rivera Rodriguez | B677: 7786163 | C677: FEDERACION NACIONAL DE ARROCEROS FEDEARROZ | E677: PRIVADO | F677: NO | G677: CARRT VIA A VALENCIA KM 12 100 | I677: Se envía por correo electrónico | K677: Rosmeri Rivera RodriguezFEDERACION NACIONAL DE ARROCEROS FEDEARROZPRIVADO | L677: 7786163 | N677: =_xlfn.XLOOKUP(L677,CENTRALIZADAS!A:A,CENTRALIZADAS!C:C) -> #N/A
A678: Rosmeri Rivera Rodriguez | B678: 5329011 | C678: RADIO GUATAPURI | D678: RADIO GUATAPURI | E678: PRIVADO | F678: NO | G678: CL 17 15 67 | I678: Se envía por correo electrónico | K678: Rosmeri Rivera RodriguezRADIO GUATAPURIPRIVADO | L678: 5329011 | N678: =_xlfn.XLOOKUP(L678,CENTRALIZADAS!A:A,CENTRALIZADAS!C:C) -> #N/A
A679: Rosmeri Rivera Rodriguez | B679: 5335013 | C679: RADIO GUATAPURI | E679: PRIVADO | F679: NO | G679: CL 17 15 67 | I679: Se envía por correo electrónico | K679: Rosmeri Rivera RodriguezRADIO GUATAPURIPRIVADO | L679: 5335013 | N679: =_xlfn.XLOOKUP(L679,CENTRALIZADAS!A:A,CENTRALIZADAS!C:C) -> #N/A
A680: Rosmeri Rivera Rodriguez | B680: 5828015 | C680: FUNDACION MEDICO PREVENTIVA | E680: PRIVADO | F680: NO | G680: CL 16 17 261 OFI 3 - VALLEDUPAR | K680: Rosmeri Rivera RodriguezFUNDACION MEDICO PREVENTIVAPRIVADO | L680: 5828015 | N680: =_xlfn.XLOOKUP(L680,CENTRALIZADAS!A:A,CENTRALIZADAS!C:C) -> #N/A
A681: Rosmeri Rivera Rodriguez | B681: 6557139 | C681: FUNDACION MEDICO PREVENTIVA | E681: PRIVADO | F681: NO | G681: CL 16 17 261 OFI 3 - VALLEDUPAR | K681: Rosmeri Rivera RodriguezFUNDACION MEDICO PREVENTIVAPRIVADO | L681: 6557139 | N681: =_xlfn.XLOOKUP(L681,CENTRALIZADAS!A:A,CENTRALIZADAS!C:C) -> #N/A
A682: Rosmeri Rivera Rodriguez | B682: 6591602 | C682: BANCO POPULAR SA | D682: BANCO POPULAR | E682: PRIVADO | F682: NO | G682: CL 16 8 20 - VALLEDUPAR | K682: Rosmeri Rivera RodriguezBANCO POPULAR SAPRIVADO | L682: 6591602 | N682: =_xlfn.XLOOKUP(L682,CENTRALIZADAS!A:A,CENTRALIZADAS!C:C) -> #N/A
A683: Rosmeri Rivera Rodriguez | B683: 6610423 | C683: BANCO POPULAR SA | E683: PRIVADO | F683: NO | G683: CL 16 8 20 - VALLEDUPAR | K683: Rosmeri Rivera RodriguezBANCO POPULAR SAPRIVADO | L683: 6610423 | N683: =_xlfn.XLOOKUP(L683,CENTRALIZADAS!A:A,CENTRALIZADAS!C:C) -> #N/A
A684: Rosmeri Rivera Rodriguez | B684: 6866555 | C684: BANCO POPULAR SA | D684: BANCO POPULAR | E684: PRIVADO | F684: NO | G684: CL 16 8 20 - VALLEDUPAR | K684: Rosmeri Rivera RodriguezBANCO POPULAR SAPRIVADO | L684: 6866555 | N684: =_xlfn.XLOOKUP(L684,CENTRALIZADAS!A:A,CENTRALIZADAS!C:C) -> #N/A
A685: Rosmeri Rivera Rodriguez | B685: 5320564 | C685: BANCO POPULAR SA | E685: PRIVADO | F685: NO | G685: CL 16 8 20 - VALLEDUPAR | K685: Rosmeri Rivera RodriguezBANCO POPULAR SAPRIVADO | L685: 5320564 | N685: =_xlfn.XLOOKUP(L685,CENTRALIZADAS!A:A,CENTRALIZADAS!C:C) -> #N/A
A686: Rosmeri Rivera Rodriguez | B686: 7851801 | C686: BANCO POPULAR SA | E686: PRIVADO | F686: NO | G686: CL 16 8 20 - VALLEDUPAR | K686: Rosmeri Rivera RodriguezBANCO POPULAR SAPRIVADO | L686: 7851801 | N686: =_xlfn.XLOOKUP(L686,CENTRALIZADAS!A:A,CENTRALIZADAS!C:C) -> #N/A
A687: Rosmeri Rivera Rodriguez | B687: 5300338 | C687: BANCO DAVIVIENDA SA | E687: PRIVADO | F687: NO | G687: CR 16 16 75 - VALLEDUPAR | I687: Se envía por correo electrónico | K687: Rosmeri Rivera RodriguezBANCO DAVIVIENDA SAPRIVADO | L687: 5300338 | N687: =_xlfn.XLOOKUP(L687,CENTRALIZADAS!A:A,CENTRALIZADAS!C:C) -> SSGMTO
A688: Rosmeri Rivera Rodriguez | B688: 5824711 | C688: BANCO DAVIVIENDA SA | E688: PRIVADO | F688: NO | G688: CR 16 16 75 - VALLEDUPAR | K688: Rosmeri Rivera RodriguezBANCO DAVIVIENDA SAPRIVADO | L688: 5824711 | N688: =_xlfn.XLOOKUP(L688,CENTRALIZADAS!A:A,CENTRALIZADAS!C:C) -> SSGMTO
A689: Rosmeri Rivera Rodriguez | B689: 6601934 | C689: BANCO DAVIVIENDA SA | D689: BANCO DAVIVIENDA S.A | E689: PRIVADO | F689: NO | G689: CR 16 16 75 - VALLEDUPAR | K689: Rosmeri Rivera RodriguezBANCO DAVIVIENDA SAPRIVADO | L689: 6601934 | N689: =_xlfn.XLOOKUP(L689,CENTRALIZADAS!A:A,CENTRALIZADAS!C:C) -> SSGMTO
A690: Rosmeri Rivera Rodriguez | B690: 6887213 | C690: BANCO DAVIVIENDA SA | D690: BANCO DAVIVIENDA S.A | E690: PRIVADO | F690: NO | G690: CR 16 16 75 - VALLEDUPAR | K690: Rosmeri Rivera RodriguezBANCO DAVIVIENDA SAPRIVADO | L690: 6887213 | N690: =_xlfn.XLOOKUP(L690,CENTRALIZADAS!A:A,CENTRALIZADAS!C:C) -> SSGMTO
A691: Rosmeri Rivera Rodriguez | B691: 7519962 | C691: BANCO DAVIVIENDA SA | E691: PRIVADO | F691: NO | G691: CR 16 16 75 - VALLEDUPAR | K691: Rosmeri Rivera RodriguezBANCO DAVIVIENDA SAPRIVADO | L691: 7519962 | N691: =_xlfn.XLOOKUP(L691,CENTRALIZADAS!A:A,CENTRALIZADAS!C:C) -> SSGMTO
A692: Rosmeri Rivera Rodriguez | B692: 7671691 | C692: BANCO DAVIVIENDA SA | E692: PRIVADO | F692: NO | G692: CR 16 16 75 - VALLEDUPAR | K692: Rosmeri Rivera RodriguezBANCO DAVIVIENDA SAPRIVADO | L692: 7671691 | N692: =_xlfn.XLOOKUP(L692,CENTRALIZADAS!A:A,CENTRALIZADAS!C:C) -> #N/A
A693: Rosmeri Rivera Rodriguez | B693: 7879320 | C693: BANCO DAVIVIENDA SA | E693: PRIVADO | F693: NO | G693: CR 16 16 75 - VALLEDUPAR | K693: Rosmeri Rivera RodriguezBANCO DAVIVIENDA SAPRIVADO | L693: 7879320 | N693: =_xlfn.XLOOKUP(L693,CENTRALIZADAS!A:A,CENTRALIZADAS!C:C) -> SSGMTO
A694: Rosmeri Rivera Rodriguez | B694: 7816288 | C694: BANCO DAVIVIENDA SA | E694: PRIVADO | F694: NO | G694: CR 16 16 75 - VALLEDUPAR | K694: Rosmeri Rivera RodriguezBANCO DAVIVIENDA SAPRIVADO | L694: 7816288 | N694: =_xlfn.XLOOKUP(L694,CENTRALIZADAS!A:A,CENTRALIZADAS!C:C) -> SSGMTO
A695: Rosmeri Rivera Rodriguez | B695: 5331212 | C695: ORGANIZACIÓN MEDICA SANTA ISABEL SAS | D695: CLINICA SANTA ISABEL | E695: PRIVADO | F695: NO | G695: CR 19 14 47 - VALLEDUPAR | K695: Rosmeri Rivera RodriguezORGANIZACIÓN MEDICA SANTA ISABEL SASPRIVADO | L695: 5331212 | N695: =_xlfn.XLOOKUP(L695,CENTRALIZADAS!A:A,CENTRALIZADAS!C:C) -> #N/A
A696: Rosmeri Rivera Rodriguez | B696: 6587914 | C696: ORGANIZACIÓN MEDICA SANTA ISABEL SAS | D696: CLINICA SANTA ISABEL | E696: PRIVADO | F696: NO | G696: CR 19 14 47 - VALLEDUPAR | K696: Rosmeri Rivera RodriguezORGANIZACIÓN MEDICA SANTA ISABEL SASPRIVADO | L696: 6587914 | N696: =_xlfn.XLOOKUP(L696,CENTRALIZADAS!A:A,CENTRALIZADAS!C:C) -> #N/A
A697: Rosmeri Rivera Rodriguez | B697: 6826046 | C697: ORGANIZACIÓN MEDICA SANTA ISABEL SAS | D697: CLINICA SANTA ISABEL | E697: PRIVADO | F697: NO | G697: CR 19 14 47 - VALLEDUPAR | K697: Rosmeri Rivera RodriguezORGANIZACIÓN MEDICA SANTA ISABEL SASPRIVADO | L697: 6826046 | N697: =_xlfn.XLOOKUP(L697,CENTRALIZADAS!A:A,CENTRALIZADAS!C:C) -> #N/A
A698: Rosmeri Rivera Rodriguez | B698: 5332777 | C698: ORGANIZACIÓN MEDICA SANTA ISABEL SAS | D698: CLINICA SANTA ISABEL | E698: PRIVADO | F698: NO | G698: CR 19 14 47 - VALLEDUPAR | K698: Rosmeri Rivera RodriguezORGANIZACIÓN MEDICA SANTA ISABEL SASPRIVADO | L698: 5332777 | N698: =_xlfn.XLOOKUP(L698,CENTRALIZADAS!A:A,CENTRALIZADAS!C:C) -> #N/A
A699: Rosmeri Rivera Rodriguez | B699: 5362898 | C699: ORGANIZACIÓN MEDICA SANTA ISABEL SAS | D699: CLINICA SANTA ISABEL | E699: PRIVADO | F699: NO | G699: CR 19 14 47 - VALLEDUPAR | K699: Rosmeri Rivera RodriguezORGANIZACIÓN MEDICA SANTA ISABEL SASPRIVADO | L699: 5362898 | N699: =_xlfn.XLOOKUP(L699,CENTRALIZADAS!A:A,CENTRALIZADAS!C:C) -> #N/A
A700: Rosmeri Rivera Rodriguez | B700: 5360554 | C700: CLINICA MEDICOS SA | E700: PRIVADO | F700: NO | G700: CL 14 17 47 - VALLEDUPAR | K700: Rosmeri Rivera RodriguezCLINICA MEDICOS SAPRIVADO | L700: 5360554 | N700: =_xlfn.XLOOKUP(L700,CENTRALIZADAS!A:A,CENTRALIZADAS!C:C) -> #N/A
A701: Rosmeri Rivera Rodriguez | B701: 6692939 | C701: CLINICA MEDICOS SA | D701: CLINICA MEDICOS S.A. | E701: PRIVADO | F701: NO | G701: CL 14 17 47 - VALLEDUPAR | K701: Rosmeri Rivera RodriguezCLINICA MEDICOS SAPRIVADO | L701: 6692939 | N701: =_xlfn.XLOOKUP(L701,CENTRALIZADAS!A:A,CENTRALIZADAS!C:C) -> #N/A
A702: Rosmeri Rivera Rodriguez | B702: 5348789 | C702: CLINICA MEDICOS SA | D702: CLINICA MEDICOS S.A. | E702: PRIVADO | F702: NO | G702: CL 14 17 47 - VALLEDUPAR | K702: Rosmeri Rivera RodriguezCLINICA MEDICOS SAPRIVADO | L702: 5348789 | N702: =_xlfn.XLOOKUP(L702,CENTRALIZADAS!A:A,CENTRALIZADAS!C:C) -> #N/A
A703: Rosmeri Rivera Rodriguez | B703: 7796096 | C703: CLINICA MEDICOS SA | E703: PRIVADO | F703: NO | G703: CL 14 17 47 - VALLEDUPAR | K703: Rosmeri Rivera RodriguezCLINICA MEDICOS SAPRIVADO | L703: 7796096 | N703: =_xlfn.XLOOKUP(L703,CENTRALIZADAS!A:A,CENTRALIZADAS!C:C) -> #N/A
A704: Rosmeri Rivera Rodriguez | B704: 7677294 | C704: CLINICA MEDICOS SA | E704: PRIVADO | F704: NO | G704: CL 14 17 47 - VALLEDUPAR | K704: Rosmeri Rivera RodriguezCLINICA MEDICOS SAPRIVADO | L704: 7677294 | N704: =_xlfn.XLOOKUP(L704,CENTRALIZADAS!A:A,CENTRALIZADAS!C:C) -> #N/A
...

Sheet Relación Valorada
D1: FORMATO ENTREGA FACTURACIÓN ESPECIAL
J3: Rosmeri
A4: ALIADO COMERCIAL: | D4: INMEL | E4: REPARTIDOR ASIGNADO:
J5: =J6&D6&D10 -> Rosmeri Rivera RodriguezMUNICIPIO DE LA PAZEDUCACION
A6: TITULAR DE PAGO: | D6: MUNICIPIO DE LA PAZ | J6: {=_xlfn.IFS(J3="Anyela","Anyela Maria Gutierrez Ochoa",J3="Dalila","Dalila Michela Bracho Acosta",J3="Ingrid","Ingrid Johana Giraldo Quinonez",J3="Paola","Paola De la Hoz Bastidas",J3="Roberto","Roberto Pavajeau Hernandez",J3="Rocio","Rocio Gutierrez Ochoa",J3="Rosmeri","Rosmeri Rivera Rodriguez",J3="Yeisver","Yeisver Jimenéz Quiroz")} -> Rosmeri Rivera Rodriguez
A8: DIRECCION: | D8: =IFERROR(VLOOKUP(C13,[1]INFO!A:E,5,0)," ") -> CENTRO LA PAZ CR 9 6-36
A10: SEGMENTO / CUENTA: | D10: EDUCACION
A12: Nº | C12: NIC | D12: DESCRIPCION DE SUMINISTRO | E12: SIMB VAR | F12: IMPORTE MES | G12: DEUDA | H12: TOTAL
A13: 1 | B13: {=_xlfn._xlws.FILTER('R.V.'!K3:L2141,'R.V.'!K3:K2141=J5,"error")} -> Rosmeri Rivera RodriguezMUNICIPIO DE LA PAZEDUCACION | C13: 5819128 | D13: =IFERROR(VLOOKUP(C13,'R.V.'!B:D,3,0)," ") -> ESCUELA DE VARAS BLANCAS | E13: =IFERROR(VLOOKUP($C13,INFO!$F:$AK,2,0)," ") -> 5819128328 | F13: =IFERROR(VLOOKUP(C13,INFO!F:T,11,0)," ") -> 231580 | G13: =IFERROR(H13-F13," ") -> 205010 | H13: =IFERROR(VLOOKUP(C13,INFO!$F:$AK,32,0)," ") -> 436590
A14: 2 | B14: Rosmeri Rivera RodriguezMUNICIPIO DE LA PAZEDUCACION | C14: 5839301 | D14: =IFERROR(VLOOKUP(C14,'R.V.'!B:D,3,0)," ") -> COLEGIO 19 DE MARZO F | E14: =IFERROR(VLOOKUP($C14,INFO!$F:$AK,2,0)," ") -> 5839301298 | F14: =IFERROR(VLOOKUP(C14,INFO!F:T,11,0)," ") -> 609960 | G14: =IFERROR(H14-F14," ") -> 332650 | H14: =IFERROR(VLOOKUP(C14,INFO!$F:$AK,32,0)," ") -> 942610
A15: 3 | B15: Rosmeri Rivera RodriguezMUNICIPIO DE LA PAZEDUCACION | C15: 5839391 | D15: =IFERROR(VLOOKUP(C15,'R.V.'!B:D,3,0)," ") -> ESCUELA URBANA MINAS F | E15: =IFERROR(VLOOKUP($C15,INFO!$F:$AK,2,0)," ") -> 5839391323 | F15: =IFERROR(VLOOKUP(C15,INFO!F:T,11,0)," ") -> 502970 | G15: =IFERROR(H15-F15," ") -> 379730 | H15: =IFERROR(VLOOKUP(C15,INFO!$F:$AK,32,0)," ") -> 882700
A16: 4 | B16: Rosmeri Rivera RodriguezMUNICIPIO DE LA PAZEDUCACION | C16: 5839519 | D16: =IFERROR(VLOOKUP(C16,'R.V.'!B:D,3,0)," ") -> ESCUELA DE VARONES | E16: =IFERROR(VLOOKUP($C16,INFO!$F:$AK,2,0)," ") -> 5839519298 | F16: =IFERROR(VLOOKUP(C16,INFO!F:T,11,0)," ") -> 358710 | G16: =IFERROR(H16-F16," ") -> 297840 | H16: =IFERROR(VLOOKUP(C16,INFO!$F:$AK,32,0)," ") -> 656550
A17: 5 | B17: Rosmeri Rivera RodriguezMUNICIPIO DE LA PAZEDUCACION | C17: 5839954 | D17: =IFERROR(VLOOKUP(C17,'R.V.'!B:D,3,0)," ") -> ESCUELA URBANA LA FLORIDA | E17: =IFERROR(VLOOKUP($C17,INFO!$F:$AK,2,0)," ") -> 5839954258 | F17: =IFERROR(VLOOKUP(C17,INFO!F:T,11,0)," ") -> 1438800 | G17: =IFERROR(H17-F17," ") -> 1167980 | H17: =IFERROR(VLOOKUP(C17,INFO!$F:$AK,32,0)," ") -> 2606780
A18: 6 | B18: Rosmeri Rivera RodriguezMUNICIPIO DE LA PAZEDUCACION | C18: 5840080 | D18: =IFERROR(VLOOKUP(C18,'R.V.'!B:D,3,0)," ") -> COLEGIO CIRO PUPO MARTINEZ | E18: =IFERROR(VLOOKUP($C18,INFO!$F:$AK,2,0)," ") -> 5840080327 | F18: =IFERROR(VLOOKUP(C18,INFO!F:T,11,0)," ") -> 4980630 | G18: =IFERROR(H18-F18," ") -> 4148850 | H18: =IFERROR(VLOOKUP(C18,INFO!$F:$AK,32,0)," ") -> 9129480
A19: 7 | B19: Rosmeri Rivera RodriguezMUNICIPIO DE LA PAZEDUCACION | C19: 5840113 | D19: =IFERROR(VLOOKUP(C19,'R.V.'!B:D,3,0)," ") -> COLEGIO ALFONSO ARAUJO | E19: =IFERROR(VLOOKUP($C19,INFO!$F:$AK,2,0)," ") -> 5840113327 | F19: =IFERROR(VLOOKUP(C19,INFO!F:T,11,0)," ") -> 935850 | G19: =IFERROR(H19-F19," ") -> 589600 | H19: =IFERROR(VLOOKUP(C19,INFO!$F:$AK,32,0)," ") -> 1525450
A20: 8 | B20: Rosmeri Rivera RodriguezMUNICIPIO DE LA PAZEDUCACION | C20: 5840343 | D20: =IFERROR(VLOOKUP(C20,'R.V.'!B:D,3,0)," ") -> ESCUELA LAS DELICIAS | E20: =IFERROR(VLOOKUP($C20,INFO!$F:$AK,2,0)," ") -> 5840343307 | F20: =IFERROR(VLOOKUP(C20,INFO!F:T,11,0)," ") -> 143780 | G20: =IFERROR(H20-F20," ") -> 94290 | H20: =IFERROR(VLOOKUP(C20,INFO!$F:$AK,32,0)," ") -> 238070
A21: 9 | B21: Rosmeri Rivera RodriguezMUNICIPIO DE LA PAZEDUCACION | C21: 5840854 | D21: =IFERROR(VLOOKUP(C21,'R.V.'!B:D,3,0)," ") -> ESCUELA FRAY JOAQUIN F | E21: =IFERROR(VLOOKUP($C21,INFO!$F:$AK,2,0)," ") -> 5840854331 | F21: =IFERROR(VLOOKUP(C21,INFO!F:T,11,0)," ") -> 542310 | G21: =IFERROR(H21-F21," ") -> 522160 | H21: =IFERROR(VLOOKUP(C21,INFO!$F:$AK,32,0)," ") -> 1064470
A22: 10 | B22: Rosmeri Rivera RodriguezMUNICIPIO DE LA PAZEDUCACION | C22: 5858000 | D22: =IFERROR(VLOOKUP(C22,'R.V.'!B:D,3,0)," ") -> COLEGIO MIXTO - SAN JOSE DE ORIENTE | E22: =IFERROR(VLOOKUP($C22,INFO!$F:$AK,2,0)," ") -> 5858000345 | F22: =IFERROR(VLOOKUP(C22,INFO!F:T,11,0)," ") -> 203270 | G22: =IFERROR(H22-F22," ") -> 150020 | H22: =IFERROR(VLOOKUP(C22,INFO!$F:$AK,32,0)," ") -> 353290
A23: 11 | B23: Rosmeri Rivera RodriguezMUNICIPIO DE LA PAZEDUCACION | C23: 5858193 | D23: =IFERROR(VLOOKUP(C23,'R.V.'!B:D,3,0)," ") -> COLEGIO COOPERATIVO SAN JOSE DE ORIENTE | E23: =IFERROR(VLOOKUP($C23,INFO!$F:$AK,2,0)," ") -> 5858193329 | F23: =IFERROR(VLOOKUP(C23,INFO!F:T,11,0)," ") -> 1807220 | G23: =IFERROR(H23-F23," ") -> 959430 | H23: =IFERROR(VLOOKUP(C23,INFO!$F:$AK,32,0)," ") -> 2766650
A24: 12 | B24: Rosmeri Rivera RodriguezMUNICIPIO DE LA PAZEDUCACION | C24: 6639172 | D24: =IFERROR(VLOOKUP(C24,'R.V.'!B:D,3,0)," ") -> COLEGIO TECNICO AGROPECUARIO BETANIA | E24: =IFERROR(VLOOKUP($C24,INFO!$F:$AK,2,0)," ") -> 6639172264 | F24: =IFERROR(VLOOKUP(C24,INFO!F:T,11,0)," ") -> 259790 | G24: =IFERROR(H24-F24," ") -> 195610 | H24: =IFERROR(VLOOKUP(C24,INFO!$F:$AK,32,0)," ") -> 455400
A25: 13 | B25: Rosmeri Rivera RodriguezMUNICIPIO DE LA PAZEDUCACION | C25: 6658036 | D25: =IFERROR(VLOOKUP(C25,'R.V.'!B:D,3,0)," ") -> COLEGIO VEREDA LA LAGUNA SAN JOSE DE ORIENTE | E25: =IFERROR(VLOOKUP($C25,INFO!$F:$AK,2,0)," ") -> 6658036263 | F25: =IFERROR(VLOOKUP(C25,INFO!F:T,11,0)," ") -> 33300 | G25: =IFERROR(H25-F25," ") -> 51070 | H25: =IFERROR(VLOOKUP(C25,INFO!$F:$AK,32,0)," ") -> 84370
... A39: 27 | B39: Rosmeri Rivera RodriguezMUNICIPIO DE LA PAZEDUCACION | C39: 1380305 | D39: =IFERROR(VLOOKUP(C39,'R.V.'!B:D,3,0)," ") -> COLEGIO CIRO PUPO MARTINEZ | E39: =IFERROR(VLOOKUP($C39,INFO!$F:$AK,2,0)," ") -> 1380305024 | F39: =IFERROR(VLOOKUP(C39,INFO!F:T,11,0)," ") -> 1731000 | G39: =IFERROR(H39-F39," ") -> 1384600 | H39: =IFERROR(VLOOKUP(C39,INFO!$F:$AK,32,0)," ") -> 3115600
A40: 28 | D40: =IFERROR(VLOOKUP(C40,'R.V.'!B:D,3,0)," ") | E40: =IFERROR(VLOOKUP($C40,INFO!$F:$AK,2,0)," ") | F40: =IFERROR(VLOOKUP(C40,INFO!F:T,11,0)," ") | G40: =IFERROR(H40-F40," ") | H40: =IFERROR(VLOOKUP(C40,INFO!$F:$AK,32,0)," ")
A41: 29 | D41: =IFERROR(VLOOKUP(C41,'R.V.'!B:D,3,0)," ") | E41: =IFERROR(VLOOKUP($C41,INFO!$F:$AK,2,0)," ") | F41: =IFERROR(VLOOKUP(C41,INFO!F:T,11,0)," ") | G41: =IFERROR(H41-F41," ") | H41: =IFERROR(VLOOKUP(C41,INFO!$F:$AK,32,0)," ")
A42: 30 | D42: =IFERROR(VLOOKUP(C42,'R.V.'!B:D,3,0)," ") | E42: =IFERROR(VLOOKUP($C42,INFO!$F:$AK,2,0)," ") | F42: =IFERROR(VLOOKUP(C42,INFO!F:T,11,0)," ") | G42: =IFERROR(H42-F42," ") | H42: =IFERROR(VLOOKUP(C42,INFO!$F:$AK,32,0)," ")
A43: 31 | D43: =IFERROR(VLOOKUP(C43,'R.V.'!B:D,3,0)," ") | E43: =IFERROR(VLOOKUP($C43,INFO!$F:$AK,2,0)," ") | F43: =IFERROR(VLOOKUP(C43,INFO!F:T,11,0)," ") | G43: =IFERROR(H43-F43," ") | H43: =IFERROR(VLOOKUP(C43,INFO!$F:$AK,32,0)," ")
A44: 32 | D44: =IFERROR(VLOOKUP(C44,'R.V.'!B:D,3,0)," ") | E44: =IFERROR(VLOOKUP($C44,INFO!$F:$AK,2,0)," ") | F44: =IFERROR(VLOOKUP(C44,INFO!F:T,11,0)," ") | G44: =IFERROR(H44-F44," ") | H44: =IFERROR(VLOOKUP(C44,INFO!$F:$AK,32,0)," ")
A45: 33 | D45: =IFERROR(VLOOKUP(C45,'R.V.'!B:D,3,0)," ") | E45: =IFERROR(VLOOKUP($C45,INFO!$F:$AK,2,0)," ") | F45: =IFERROR(VLOOKUP(C45,INFO!F:T,11,0)," ") | G45: =IFERROR(H45-F45," ") | H45: =IFERROR(VLOOKUP(C45,INFO!$F:$AK,32,0)," ")
A46: 34 | D46: =IFERROR(VLOOKUP(C46,'R.V.'!B:D,3,0)," ") | E46: =IFERROR(VLOOKUP($C46,INFO!$F:$AK,2,0)," ") | F46: =IFERROR(VLOOKUP(C46,INFO!F:T,11,0)," ") | G46: =IFERROR(H46-F46," ") | H46: =IFERROR(VLOOKUP(C46,INFO!$F:$AK,32,0)," ")
A47: 35 | D47: =IFERROR(VLOOKUP(C47,'R.V.'!B:D,3,0)," ") | E47: =IFERROR(VLOOKUP($C47,INFO!$F:$AK,2,0)," ") | F47: =IFERROR(VLOOKUP(C47,INFO!F:T,11,0)," ") | G47: =IFERROR(H47-F47," ") | H47: =IFERROR(VLOOKUP(C47,INFO!$F:$AK,32,0)," ")
A48: 36 | D48: =IFERROR(VLOOKUP(C48,'R.V.'!B:D,3,0)," ") | E48: =IFERROR(VLOOKUP($C48,INFO!$F:$AK,2,0)," ") | F48: =IFERROR(VLOOKUP(C48,INFO!F:T,11,0)," ") | G48: =IFERROR(H48-F48," ") | H48: =IFERROR(VLOOKUP(C48,INFO!$F:$AK,32,0)," ")
A49: 37 | D49: =IFERROR(VLOOKUP(C49,'R.V.'!B:D,3,0)," ") | E49: =IFERROR(VLOOKUP($C49,INFO!$F:$AK,2,0)," ") | F49: =IFERROR(VLOOKUP(C49,INFO!F:T,11,0)," ") | G49: =IFERROR(H49-F49," ") | H49: =IFERROR(VLOOKUP(C49,INFO!$F:$AK,32,0)," ")
A50: 38 | D50: =IFERROR(VLOOKUP(C50,'R.V.'!B:D,3,0)," ") | E50: =IFERROR(VLOOKUP($C50,INFO!$F:$AK,2,0)," ") | F50: =IFERROR(VLOOKUP(C50,INFO!F:T,11,0)," ") | G50: =IFERROR(H50-F50," ") | H50: =IFERROR(VLOOKUP(C50,INFO!$F:$AK,32,0)," ")
A51: 39 | D51: =IFERROR(VLOOKUP(C51,'R.V.'!B:D,3,0)," ") | E51: =IFERROR(VLOOKUP($C51,INFO!$F:$AK,2,0)," ") | F51: =IFERROR(VLOOKUP(C51,INFO!F:T,11,0)," ") | G51: =IFERROR(H51-F51," ") | H51: =IFERROR(VLOOKUP(C51,INFO!$F:$AK,32,0)," ")
E52: TOTAL | F52: =SUM(F13:F51) -> 14497590 | G52: =SUM(G13:G51) -> 8857888 | H52: =SUM(H13:H51) -> 23355478
A54: A CARIBEMAR DE LA COSTA S.A.S. E.S.P., le son aplicables las normas que regulan el saneamiento contable en el sector público, por tanto, nos permitimos recordar la obligacion que nos asiste de reportar a la Contaduría General de la Nación, semestralmente el Boletín de Deudores Morosos del Estado - BDME - , y trimestralmente el informe de Recíprocas (Entidades oficiales), los cuales están reglamentados en la Resolución 706 de 2016 y en el parágrafo 3° del artículo 4° de la Ley 716 de 2001, modificado por el Artículo 2° de la Ley 901 de 2004. Asi las cosas, previendo las consecuencias de quedar incluido en uno o ambos reportes, agradecemos a usted el pago oportuno y asi cumplir con las obligaciones de Ley.
A59: Nota: La deuda de las facturas relacionadas, no incluye deuda reclamada, en concordato, financiada, ni interés por mora. Estos se calculan diariamente y se liquidan el día que ingresa el pago efectivo de las facturas vencidas, considerando la tasa de interés vigente.
A65: FIRMA RECIBIDO: | E65: FECHA RECIBIDO:

Sheet GOB DEL CESAR
D1: FORMATO ENTREGA FACTURACIÓN ESPECIAL
J3: Rocio
A4: ALIADO COMERCIAL: | D4: INMEL | E4: REPARTIDOR ASIGNADO:
J5: =J6&D6&D10 -> Rocio Gutierrez OchoaGOBERNACION DEL CESARSALUD
A6: TITULAR DE PAGO: | D6: GOBERNACION DEL CESAR | J6: {=_xlfn.IFS(J3="Anyela","Anyela Maria Gutierrez Ochoa",J3="Dalila","Dalila Michela Bracho Acosta",J3="Ingrid","Ingrid Johana Giraldo Quinonez",J3="Paola","Paola De la Hoz Bastidas",J3="Roberto","Roberto Pavajeau Hernandez",J3="Rocio","Rocio Gutierrez Ochoa",J3="Rosmeri","Rosmeri Rivera Rodriguez",J3="Yeisver","Yeisver Jimenéz Quiroz")} -> Rocio Gutierrez Ochoa
A8: DIRECCION: | D8: TR 18 19 85
A10: SEGMENTO / CUENTA: | D10: SALUD
A12: Nº | C12: NIC | D12: DESCRIPCION DE SUMINISTRO | E12: SIMB VAR | F12: IMPORTE MES | G12: DEUDA | H12: TOTAL
A13: 1 | B13: {=_xlfn._xlws.FILTER('R.V.'!K3:L2141,'R.V.'!K3:K2141=J5,"error")} -> #VALUE! | C13: 5352794 | D13: =IFERROR(VLOOKUP(C13,'R.V.'!B:D,3,0)," ") -> PROGRAMAS MEDICOS ESPECIAL | E13: =IFERROR(VLOOKUP($C13,INFO!$F:$AK,2,0)," ") -> 5352794324 | F13: =IFERROR(VLOOKUP(C13,INFO!F:T,11,0)," ") -> 34682070 | G13: =IFERROR(H13-F13," ") -> 0 | H13: =IFERROR(VLOOKUP(C13,INFO!$F:$AK,32,0)," ") -> 34682070
A14: 2 | D14: =IFERROR(VLOOKUP(C14,'R.V.'!B:D,3,0)," ") | E14: =IFERROR(VLOOKUP($C14,INFO!$F:$AK,2,0)," ") | F14: =IFERROR(VLOOKUP(C14,INFO!F:T,11,0)," ") | G14: =IFERROR(H14-F14," ") | H14: =IFERROR(VLOOKUP(C14,INFO!$F:$AK,32,0)," ")
A15: 3 | D15: =IFERROR(VLOOKUP(C15,'R.V.'!B:D,3,0)," ") | E15: =IFERROR(VLOOKUP($C15,INFO!$F:$AK,2,0)," ") | F15: =IFERROR(VLOOKUP(C15,INFO!F:T,11,0)," ") | G15: =IFERROR(H15-F15," ") | H15: =IFERROR(VLOOKUP(C15,INFO!$F:$AK,32,0)," ")
A16: 4 | D16: =IFERROR(VLOOKUP(C16,'R.V.'!B:D,3,0)," ") | E16: =IFERROR(VLOOKUP($C16,INFO!$F:$AK,2,0)," ") | F16: =IFERROR(VLOOKUP(C16,INFO!F:T,11,0)," ") | G16: =IFERROR(H16-F16," ") | H16: =IFERROR(VLOOKUP(C16,INFO!$F:$AK,32,0)," ")
A17: 5 | D17: =IFERROR(VLOOKUP(C17,'R.V.'!B:D,3,0)," ") | E17: =IFERROR(VLOOKUP($C17,INFO!$F:$AK,2,0)," ") | F17: =IFERROR(VLOOKUP(C17,INFO!F:T,11,0)," ") | G17: =IFERROR(H17-F17," ") | H17: =IFERROR(VLOOKUP(C17,INFO!$F:$AK,32,0)," ")
A18: 6 | D18: =IFERROR(VLOOKUP(C18,'R.V.'!B:D,3,0)," ") | E18: =IFERROR(VLOOKUP($C18,INFO!$F:$AK,2,0)," ") | F18: =IFERROR(VLOOKUP(C18,INFO!F:T,11,0)," ") | G18: =IFERROR(H18-F18," ") | H18: =IFERROR(VLOOKUP(C18,INFO!$F:$AK,32,0)," ")
A19: 7 | D19: =IFERROR(VLOOKUP(C19,'R.V.'!B:D,3,0)," ") | E19: =IFERROR(VLOOKUP($C19,INFO!$F:$AK,2,0)," ") | F19: =IFERROR(VLOOKUP(C19,INFO!F:T,11,0)," ") | G19: =IFERROR(H19-F19," ") | H19: =IFERROR(VLOOKUP(C19,INFO!$F:$AK,32,0)," ")
A20: 8 | D20: =IFERROR(VLOOKUP(C20,'R.V.'!B:D,3,0)," ") | E20: =IFERROR(VLOOKUP($C20,INFO!$F:$AK,2,0)," ") | F20: =IFERROR(VLOOKUP(C20,INFO!F:T,11,0)," ") | G20: =IFERROR(H20-F20," ") | H20: =IFERROR(VLOOKUP(C20,INFO!$F:$AK,32,0)," ")
A21: 9 | D21: =IFERROR(VLOOKUP(C21,'R.V.'!B:D,3,0)," ") | E21: =IFERROR(VLOOKUP($C21,INFO!$F:$AK,2,0)," ") | F21: =IFERROR(VLOOKUP(C21,INFO!F:T,11,0)," ") | G21: =IFERROR(H21-F21," ") | H21: =IFERROR(VLOOKUP(C21,INFO!$F:$AK,32,0)," ")
A22: 10 | D22: =IFERROR(VLOOKUP(C22,'R.V.'!B:D,3,0)," ") | E22: =IFERROR(VLOOKUP($C22,INFO!$F:$AK,2,0)," ") | F22: =IFERROR(VLOOKUP(C22,INFO!F:T,11,0)," ") | G22: =IFERROR(H22-F22," ") | H22: =IFERROR(VLOOKUP(C22,INFO!$F:$AK,32,0)," ")
A23: 11 | D23: =IFERROR(VLOOKUP(C23,'R.V.'!B:D,3,0)," ") | E23: =IFERROR(VLOOKUP($C23,INFO!$F:$AK,2,0)," ") | F23: =IFERROR(VLOOKUP(C23,INFO!F:T,11,0)," ") | G23: =IFERROR(H23-F23," ") | H23: =IFERROR(VLOOKUP(C23,INFO!$F:$AK,32,0)," ")
A24: 12 | D24: =IFERROR(VLOOKUP(C24,'R.V.'!B:D,3,0)," ") | E24: =IFERROR(VLOOKUP($C24,INFO!$F:$AK,2,0)," ") | F24: =IFERROR(VLOOKUP(C24,INFO!F:T,11,0)," ") | G24: =IFERROR(H24-F24," ") | H24: =IFERROR(VLOOKUP(C24,INFO!$F:$AK,32,0)," ")
A25: 13 | D25: =IFERROR(VLOOKUP(C25,'R.V.'!B:D,3,0)," ") | E25: =IFERROR(VLOOKUP($C25,INFO!$F:$AK,2,0)," ") | F25: =IFERROR(VLOOKUP(C25,INFO!F:T,11,0)," ") | G25: =IFERROR(H25-F25," ") | H25: =IFERROR(VLOOKUP(C25,INFO!$F:$AK,32,0)," ")
... A51: 39 | D51: =IFERROR(VLOOKUP(C51,'R.V.'!B:D,3,0)," ") | E51: =IFERROR(VLOOKUP($C51,INFO!$F:$AK,2,0)," ") | F51: =IFERROR(VLOOKUP(C51,INFO!F:T,11,0)," ") | G51: =IFERROR(H51-F51," ") | H51: =IFERROR(VLOOKUP(C51,INFO!$F:$AK,32,0)," ")
E52: TOTAL | F52: =SUM(F13:F51) -> 34682070 | G52: =SUM(G13:G51) -> 0 | H52: =SUM(H13:H51) -> 34682070
A54: A CARIBEMAR DE LA COSTA S.A.S. E.S.P., le son aplicables las normas que regulan el saneamiento contable en el sector público, por tanto, nos permitimos recordar la obligacion que nos asiste de reportar a la Contaduría General de la Nación, semestralmente el Boletín de Deudores Morosos del Estado - BDME - , y trimestralmente el informe de Recíprocas (Entidades oficiales), los cuales están reglamentados en la Resolución 706 de 2016 y en el parágrafo 3° del artículo 4° de la Ley 716 de 2001, modificado por el Artículo 2° de la Ley 901 de 2004. Asi las cosas, previendo las consecuencias de quedar incluido en uno o ambos reportes, agradecemos a usted el pago oportuno y asi cumplir con las obligaciones de Ley.
A59: Nota: La deuda de las facturas relacionadas, no incluye deuda reclamada, en concordato, financiada, ni interés por mora. Estos se calculan diariamente y se liquidan el día que ingresa el pago efectivo de las facturas vencidas, considerando la tasa de interés vigente.
A65: FIRMA RECIBIDO: | E65: FECHA RECIBIDO:

Sheet ENTREGA DIRECTA EJECUTIVOS
A1: EJECUTIVO | B1: NIC | C1: TITULAR DE PAGO | D1: DESCRIPCIÓN DE SUMINISTRO | E1: SEGMENTO_CUENTA | F1: DOBLE ENTREGA (SI/NO) | G1: Donde se entrega PAQUETE 1 | H1: Donde se entrega PAQUETE 2 | I1: OBSERVACION ADICIONAL | K1: filtro | L1: NIC
A2: Paola De la Hoz Bastidas | B2: 1413166 | C2: MUNICIPIO DE VALLEDUPAR | D2: ACUEDUCTO CGTO VALENCIA- CARRET VIA PUEBLOBELLO | E2: ACUEDUCTO | F2: NO | G2: CR 5 No.15- 65 Secretraia Gral _Alcaldia Muncipal | I2: Impresión y entrega direcata por Ventas -Territorial, para revisión previa de Facturación, en cumplimiento a compromisos ante la SSPD. | K2: Paola De la Hoz BastidasMUNICIPIO DE VALLEDUPARACUEDUCTO | L2: 1413166
A3: Paola De la Hoz Bastidas | B3: 5357495 | C3: MUNICIPIO DE VALLEDUPAR | D3: ACDTO CMTARIO LAS RAICES_CGTO LAS RAICES | E3: ACUEDUCTO | F3: NO | G3: CR 5 No.15- 65 Secretraia Gral _Alcaldia Muncipal | I3: Impresión y entrega direcata por Ventas -Territorial, para revisión previa de Facturación, en cumplimiento a compromisos ante la SSPD. | K3: Paola De la Hoz BastidasMUNICIPIO DE VALLEDUPARACUEDUCTO | L3: 5357495
A4: Paola De la Hoz Bastidas | B4: 5358999 | C4: MUNICIPIO DE VALLEDUPAR | D4: ACUEDUCTO GUACOCHE_CGTO GUACOCHE | E4: ACUEDUCTO | F4: NO | G4: CR 5 No.15- 65 Secretraia Gral _Alcaldia Muncipal | I4: Impresión y entrega direcata por Ventas -Territorial, para revisión previa de Facturación, en cumplimiento a compromisos ante la SSPD. | K4: Paola De la Hoz BastidasMUNICIPIO DE VALLEDUPARACUEDUCTO | L4: 5358999
A5: Paola De la Hoz Bastidas | B5: 5359176 | C5: MUNICIPIO DE VALLEDUPAR | D5: ACUEDUCTO BOMBA EL JABO_EL JAVO RURAL | E5: ACUEDUCTO | F5: NO | G5: CR 5 No.15- 65 Secretraia Gral _Alcaldia Muncipal | I5: Impresión y entrega direcata por Ventas -Territorial, para revisión previa de Facturación, en cumplimiento a compromisos ante la SSPD. | K5: Paola De la Hoz BastidasMUNICIPIO DE VALLEDUPARACUEDUCTO | L5: 5359176
A6: Paola De la Hoz Bastidas | B6: 5359669 | C6: MUNICIPIO DE VALLEDUPAR | D6: ACUEDUCTO LOS CALABAZOS_CGTO LOS CALABAZOS | E6: ACUEDUCTO | F6: NO | G6: CR 5 No.15- 65 Secretraia Gral _Alcaldia Muncipal | I6: Impresión y entrega direcata por Ventas -Territorial, para revisión previa de Facturación, en cumplimiento a compromisos ante la SSPD. | K6: Paola De la Hoz BastidasMUNICIPIO DE VALLEDUPARACUEDUCTO | L6: 5359669
A7: Paola De la Hoz Bastidas | B7: 5360243 | C7: MUNICIPIO DE VALLEDUPAR | D7: ACUEDUCTO AGUAS BLANCAS_CGTO AGUAS BLANCAS | E7: ACUEDUCTO | F7: NO | G7: CR 5 No.15- 65 Secretraia Gral _Alcaldia Muncipal | I7: Impresión y entrega direcata por Ventas -Territorial, para revisión previa de Facturación, en cumplimiento a compromisos ante la SSPD. | K7: Paola De la Hoz BastidasMUNICIPIO DE VALLEDUPARACUEDUCTO | L7: 5360243
A8: Paola De la Hoz Bastidas | B8: 5360245 | C8: MUNICIPIO DE VALLEDUPAR | D8: ACUEDUCTO AGUAS BLANCAS_CGTO AGUAS BLANCAS | E8: ACUEDUCTO | F8: NO | G8: CR 5 No.15- 65 Secretraia Gral _Alcaldia Muncipal | I8: Impresión y entrega direcata por Ventas -Territorial, para revisión previa de Facturación, en cumplimiento a compromisos ante la SSPD. | K8: Paola De la Hoz BastidasMUNICIPIO DE VALLEDUPARACUEDUCTO | L8: 5360245
A9: Paola De la Hoz Bastidas | B9: 5361891 | C9: MUNICIPIO DE VALLEDUPAR | D9: ACUEDUCTO GUAYMARAL_CGTO GUAIMARAL | E9: ACUEDUCTO | F9: NO | G9: CR 5 No.15- 65 Secretraia Gral _Alcaldia Muncipal | I9: Impresión y entrega direcata por Ventas -Territorial, para revisión previa de Facturación, en cumplimiento a compromisos ante la SSPD. | K9: Paola De la Hoz BastidasMUNICIPIO DE VALLEDUPARACUEDUCTO | L9: 5361891
A10: Paola De la Hoz Bastidas | B10: 5361969 | C10: MUNICIPIO DE VALLEDUPAR | D10: ACUEDUCTO SAN MARTIN_CGTO EL PERRO | E10: ACUEDUCTO | F10: NO | G10: CR 5 No.15- 65 Secretraia Gral _Alcaldia Muncipal | I10: Impresión y entrega direcata por Ventas -Territorial, para revisión previa de Facturación, en cumplimiento a compromisos ante la SSPD. | K10: Paola De la Hoz BastidasMUNICIPIO DE VALLEDUPARACUEDUCTO | L10: 5361969
A11: Paola De la Hoz Bastidas | B11: 6238148 | C11: MUNICIPIO DE VALLEDUPAR | D11: ACDTO BOMBA LA VEGA _CGTO LA VEGA ARRIBA | E11: ACUEDUCTO | F11: NO | G11: CR 5 No.15- 65 Secretraia Gral _Alcaldia Muncipal | I11: Impresión y entrega direcata por Ventas -Territorial, para revisión previa de Facturación, en cumplimiento a compromisos ante la SSPD. | K11: Paola De la Hoz BastidasMUNICIPIO DE VALLEDUPARACUEDUCTO | L11: 6238148
A12: Paola De la Hoz Bastidas | B12: 6634302 | C12: MUNICIPIO DE VALLEDUPAR | D12: ACUEDUCTO DE ATANQUEZ_CGTO ATANQUEZ | E12: ACUEDUCTO | F12: NO | G12: CR 5 No.15- 65 Secretraia Gral _Alcaldia Muncipal | I12: Impresión y entrega direcata por Ventas -Territorial, para revisión previa de Facturación, en cumplimiento a compromisos ante la SSPD. | K12: Paola De la Hoz BastidasMUNICIPIO DE VALLEDUPARACUEDUCTO | L12: 6634302
A13: Paola De la Hoz Bastidas | B13: 6634330 | C13: MUNICIPIO DE VALLEDUPAR | D13: POZOS PROFUNDOS LAS CASITAS_VALLEDUPAR | E13: ACUEDUCTO | F13: NO | G13: CR 5 No.15- 65 Secretraia Gral _Alcaldia Muncipal | I13: Impresión y entrega direcata por Ventas -Territorial, para revisión previa de Facturación, en cumplimiento a compromisos ante la SSPD. | K13: Paola De la Hoz BastidasMUNICIPIO DE VALLEDUPARACUEDUCTO | L13: 6634330
... A330: Paola De la Hoz Bastidas | B330: 7958047 | C330: MUNICIPIO DE VALLEDUPAR | D330: PARQUE LA PROVINCIA_VALLEDUPAR | E330: MERCABASTOS | F330: NO | G330: CR 5 No.15- 65 Secretraia Gral _Alcaldia Muncipal | I330: Impresión y entrega direcata por Ventas -Territorial, para revisión previa de Facturación, en cumplimiento a compromisos ante la SSPD. | K330: Paola De la Hoz BastidasMUNICIPIO DE VALLEDUPARMERCABASTOS | L330: 7958047

Sheet PENDIENTE X RELACION
A1: NIC
A2: 1042964
A3: 7807638
A4: 1004143
A5: 6826884
A6: 7716020
A7: 7891239
A8: 5803604
A9: 1004333
A10: 5824593
A11: 5851177
A12: 5302399
A13: 1021220
... A84: 1039109

Sheet Hoja1
A1: EJECUTIVO | B1: Rosmeri Rivera Rodriguez
A2: SEGMENTO_CUENTA | B2: CENTRALIZADA | M2: Paola___SUPERCEL_EU___ | O2: Roberto_ACUEDUCTO_DESCENTRALIZADO | Q2: Rocio_ACUEDUCTO | S2: Rosmeri_ACUEDUCTO_DESCENTRALIZADO
D3: Yeisver Jimenéz Quiroz | F3: Paola De la Hoz Bastidas | I3: Anyela EDUCACION | K3: Ingrid_ACUEDUCTO | M3: SUPERCELL | O3: Acsepal | Q3: ADMON PUBLICA COOP SERVICIOS PUBLICOS DE NUEVA GRANADA | S3: EMPAZ | U3: Yeisver_ACUEDUCTO_DESCENTRALIZADO
A4: Etiquetas de fila | D4: ACUEDUCTO_DESCENTRALIZADO | F4: ___SUPERCEL_EU___ | I4: HOSPITAL DE AGUSTIN CODAZZI | K4: MUNICIPIO DE PAILITAS | O4: Empresa de servicios publicos EMCOPEY | Q4: MUNICIPIO DE ARIGUANI | S4: ESPUMA ESP | U4: EMPRESA DE SERVICIOS PUBLICOS EMPOBOSCONIA
A5: Total general | D5: ACUEDUCTO_EMPASO_DESCENTRALIZADO | F5: __SIVA_SISTEMA_INTEGRADO_DE_TRANSPORTE | I5: HOSPITAL DE BECERRIL | K5: MUNICIPIO DE CHIRIGUANA | M5: Paola_EDUCACION | O5: Empresa de servicios publicos SERVISANANGEL | Q5: MUNICIPIO DE ASTREA
D6: CASA_DE_LA_CULTURA_BOSCO_DESCENTRALIZADO_ | F6: ACUEDUCTO | I6: HOSPITAL DE CURUMANI | K6: MUNICIPIO DE LA GLORIA | M6: FAMISANAR ENTIDAD PROMOTORA DE SALUD | Q6: MUNICIPIO DE CHIMICHAGUA | S6: Rosmeri_PRIVADO | U6: Yeisver_EDUCACION
D7: EDUCACION | F7: EDUCACION | I7: HOSPITAL EL SOCORRO | K7: MUNICIPIO DE PELAYA | M7: MUNICIPIO DE VALLEDUPAR | O7: Roberto_PRIVADO | S7: BBVA COLOMBIA SA | U7: HOSPITAL DE EL PASO HERNANDO QUINTERO BLANCO
D8: NOTARIA | F8: EMDUPAR | I8: HOSPITAL JORGE ISAAC RINCON TORRES | K8: MUNICIPIO DE TAMALAMEQUE | O8: FUNDACION MEMBRANA (Pueblito Arhuaco) | Q8: Rocio_OTROS | S8: AGROPECUARIA CAMPO VERDE | U8: HOSPITAL SAN JUAN BOSCO
D9: PRIVADO | F9: FONVISOCIAL | I9: MUNICIPIO DE AGUSTIN CODAZZI | M9: Paola_HEAD | Q9: GOBERNACION DEL CESAR | S9: ALIMENTOS FRESCOS | U9: MUNCIPIO DE EL PASO
D10: PROPIOS | F10: HEAD | I10: MUNICIPIO DE BECERRIL | M10: HOSPITAL EDUARDO ARREDONDO DAZA | O10: Roberto_ACUEDUCTO_CENTRALIZADO | Q10: GOBERNACION DEL CESAR- PARQUE LUDICO LAS FLORES LOC2 | S10: APARTA HOTEL CUERPOS | U10: MUNICIPIO DE BOSCONIA
F11: IDECESAR | I11: MUNICIPIO DE CURUMANI | K11: Ingrid_PRIVADO | O11: Municipio de Pueblo Bello | Q11: GOBERNACION DEL CESAR- PARQUE LUDICO LAS FLORES LOC3 | S11: APARTA HOTEL PUNTO G
F12: INDER | I12: MUNICIPIO DE LA JAGUA DE IBIRICO | K12: AGROSAVIA | M12: Paola_INDER_SEDE_PERMANENTE_12_DE_OCTUBRE_ | Q12: GOBERNACION DEL CESAR- PARQUE LUDICO LAS FLORES LOC4 | S12: ARANGO CARNES | U12: Yeisver_PROPIOS
F13: INDER_SEDE_PERMANENTE_12_DE_OCTUBRE_ | I13: MUNICIPIO DE SAN DIEGO | K13: APRESHI LTDA -CERA COLEY STEFANY | M13: INDER | O13: Roberto_PROPIOS | Q13: GOBERNACION DEL CESAR-PARQUE LUDICO LAS FLORES LOC1 | S13: AREAS COMUNES DEL TERMINAL | U13: MUNCIPIO DE EL PASO
A14: EJECUTIVO | B14: Anyela Maria Gutierrez Ochoa | F14: INTERASEO_S.A.E.S.P | K14: ASOC PADRES DE FAMILIA | O14: Municipio de Algarrobo | S14: ARROCERA LA MALENA | U14: MUNICIPIO DE BOSCONIA
D15: Rosmeri Rivera Rodriguez | F15: MERCABASTOS | K15: AUTOCENTRO SUPERMERCADO | M15: Paola_PRIVADO | O15: Municipio de El Copey | Q15: Rocio_ACUEDUCTO_DESCENTRALIZADO | S15: ARROCERA MANO DE DIOS
A16: Etiquetas de fila | D16: ACUEDUCTO_DESCENTRALIZADO | F16: PRIVADO | K16: BBVA COLOMBIA | M16: CGIO MANUELA BELTRAN | O16: Municipio de Pueblo Bello | Q16: ACUEDUCTO DESCENTRALIZADO ACUACHIN | S16: ARROCERA VICTOR GUERRA | U16: Yeisver_ACUEDUCTO_EMPASO_DESCENTRALIZADO
A17: ACUEDUCTO | D17: CONCEJO_DESCENTRALIZADO | F17: PROPIO_SIN_PARQUE | K17: CARLOS MURGAS GUERRERO | M17: COL CALLEJA REAL | O17: Municipio de San Angel | S17: BANAPALMA | U17: EMPRESA DE SERVICIOS PUBLICOS DE EL PASO EMPASO E.S.P
A18: ACUEDUCTO_DESCENTRALIZADO | D18: EDUCACION | I18: Anyela ACUEDUCTO | K18: CENTRO CIAL ORBE PLAZA ARCO 01 | M18: MR. HARRY SPA | Q18: Rocio_PROPIOS | S18: BANCO BOGOTA
A19: BOMBEROS_DESCENTRALIZADO | D19: PRIVADO | I19: MUNICIPIO DE CURUMANI | K19: CENTRO DE ATENCION PRIORITARIA EN SALUD, CAPS | M19: ADOLFO JEREMIAS MOLINA MOLINA | O19: Roberto_EDUCACION | Q19: AGENCIA COLOMBIANA PARA LA REINCORPORACION Y LA NORMALIZACION ARN | S19: BANCO DAVIVIENDA SA | U19: Yeisver_NOTARIA
A20: EDUCACION | D20: PROPIOS | I20: MUNICIPIO DE SAN DIEGO | K20: CENTRO DE SERVICIO LTDA | M20: ALMACEN CAÑAMO | O20: DIOCESIS DE VALLEDUPAR (CURIA) | Q20: ALMACEN CALZATODO SA | S20: BANCO POPULAR SA | U20: JAIME ROMERO AMADOR
A21: PROPIOS | K21: CERA COLEY STEFANY | M21: C.D.T. DEL CESAR FUNDACION CENTRO DE INVESTIGACION | O21: Hospital Camilo Villazon Pumarejo | Q21: ALMACEN GINO PASCALLY | S21: BAVARIA
A22: PROPIOS_LUMINARIAS | F22: Ingrid Johana Giraldo Quinonez | I22: Anyela SALUD | K22: COOGANASUR | M22: CEMENTERIO JARDINES | O22: Hospital Local de Algarrobo | Q22: ALMACENES CAÑAMO | S22: BORROSO ANABEL | U22: Yeisver_CASA_DE_LA_CULTURA_BOSCO_DESCENTRALIZADO_
A23: SALUD | F23: ACUEDUCTO | I23: MUNICIPIO DE AGUSTIN CODAZZI | K23: EPS SANITAS CC ORBE PLAZA FLORES | M23: CUCINARE SAS | O23: Hospital Local Sabanas de San Angel | Q23: ALMACENES FLAMINGO | S23: CAJA DE COMPENSACION FAMILIAR DEL CESAR | U23: INSTITUTO MUNICOPAL DE CULTURA DEPORTE Y RECERACION DEL MUNICIPAL DE BOSCONIACASA GRANDE
A24: Total general | F24: ACUEDUCTO_DESCENTRALIZADO | K24: ESTACION DOÑA EXI | M24: ESESCO | O24: Hospital San Roque de El Copey | Q24: ARCE SOCARRAS LUIS F | S24: CAMARA DE COMERCIO
D25: Rocio Gutierrez Ochoa | F25: EDUCACION | I25: Anyela ACUEDUCTO DESCENTRALIZADO | K25: GIL ALEJANDRO | M25: ESPECIAL MIGRACION COLOMBIA UNIDAD ADMINISTRATIVA | O25: Municipio de Algarrobo | Q25: ARN AGENCIA PARA LA REINTEGRACION | S25: CARCO
D26: ACUEDUCTO | F26: PRIVADO | I26: ACUACUR | K26: GRUPO AGROINDUSTRIAL HACIENDA LA GLORIA | M26: GLORIA YOLANDA OLIVEROS OSORIO | O26: Municipio de El Copey | Q26: AS Y MORON S.A.S. | S26: CASA INDIGENA LOS CAMPANOS | U26: Yeisver_PRIVADO
D27: ACUEDUCTO_DESCENTRALIZADO | F27: PROPIOS | I27: EMPOSANDIEGO | K27: HOTEL RESTAURANTE TRANSPORTADOR | M27: HOTEL URAK ALFONSO DEL CASTILLO OLMEDO | O27: Municipio de Pueblo Bello | Q27: ASISTENCIA MEDICA INMEDIATA | S27: CICELED | U27: AEROCIVIL
D28: EDUCACION | F28: SALUD | I28: MUNICIPIO DE AGUSTIN CODAZZI | K28: INSTITUTO COLOMBIANO AGROPECUARIO ICA | M28: INVERSIONES MACHIQUE | O28: Municipio de San Angel | Q28: BERMUDEZ DIANA | S28: CLINICA BUENOS AIRES SAS | U28: ANA MARTINEZ DE PADILLA
D29: OTROS | I29: MUNICIPIO DE BECERRIL | K29: INSTITUTO NACIONAL DE VIAS | M29: JANNA MOTOR?S.A.S | Q29: BIBLIOTECA RAFAEL CARRILLO LUQUEZ | S29: CLINICA MEDICOS SA | U29: AREOPUERTOS DE ORIENTE
D30: PROPIOS | I30: TRIPLE AAA DE LA JAGUA DE IBIRICO | K30: MARFIL IMPRESOS | M30: MEGA COLEGIO FRANCISCO DE PAULA | O30: Roberto_CENTRALIZADA | Q30: BRITO PARODI JOSE LUIS | S30: CLUB CAMPESTRE | U30: ASMETSALUD
D31: SALUD | K31: MEDICAS DEL CESAR CENTRO DE ESPECIALISTAS | M31: MEGACOLEGIO | O31: INDUSTRIA MILITAR INDUMIL | Q31: CAFÉ DON VALLE | S31: COMPARTA EPS COPERATIVA DE SALUD | U31: AUTOCHEVROLET
I32: Anyela PROPIOS | K32: QUIMIOSALUD | M32: PINTO DAVID MORENO | O32: SEGURIDAD | Q32: CAMAGUEY SAS | S32: COOPROFESORES | U32: AUTOTROPICAL S.A.S
I33: CONCEJO MUNICIPAL LA JAGUA DE IBIRICO | K33: RAMA JUDICIAL | M33: SAS HOTEL UCLA CENTER CONS EN GESTION FINANCIERA Y DE RES | Q33: CANCHA DE FUTBOL NVA GRANADA | S33: DUSAKAWI - IPS HOSPITAL | U33: BASCULA BOSCONIA
I34: MUNICIPIO DE AGUSTIN CODAZZI | K34: UNIDAD DE TRATAMIENTO DE DOLOR CARIBE SAS | Q34: CASINO ATLANTIS CC MAYALES | S34: DUSAKAWI IPS HOSPITAL | U34: CESAR VEGA
D35: Roberto Pavajeau Hernandez | F35: Dalila Michela Bracho Acosta | I35: MUNICIPIO DE BECERRIL | M35: Paola__SIVA_SISTEMA_INTEGRADO_DE_TRANSPORTE | Q35: CC GUATAPURI COCINAS VERDES CREATIVAS LOCAL 332 | S35: EFECTIVO LTDA | U35: CLINICA REGIONAL SINAIS VITAIS S.A.S DE ESPECIALISTAS
D36: ACUEDUCTO_CENTRALIZADO | F36: EMPRESA | I36: MUNICIPIO DE CURUMANI | K36: Ingrid_ACUEDUCTO_DESCENTRALIZADO | M36: SIVA | Q36: CENTRO COMERCIAL SANITAS | S36: ETICOS SERRANO GOMEZ | U36: FENOCO SA
D37: ACUEDUCTO_DESCENTRALIZADO | I37: MUNICIPIO DE LA JAGUA DE IBIRICO | K37: ACUEDUCTO DE SIMAÑA | Q37: CENTRO ORTOPEDICO DEL CESAS S.A.S. | S37: EUPARI HOTEL | U37: GASAN BOSCONIA
D38: EDUCACION | I38: MUNICIPIO DE SAN DIEGO | K38: DE PAILITAS EMPRESAS DE SERVICIO PUBLICOS | Q38: CESAR ANAYA | S38: FEDERACION NACIONAL DE ARROCEROS FEDEARROZ | U38: HOTEL LAS OLAS RUTA DEL SOL
D39: PRIVADO | I39: POLICIA NACIONAL | K39: EMPOGLORIA EPS EMPRESA DE SERVICIOS PUBLICOS DE LA GLORIA | M39: Paola_EMDUPAR | Q39: CHURRASCADA PARRILLA | S39: FUNDACION DE LA MUJER | U39: HOTEL PALMA DE MAYORCA
D40: PROPIOS | I40: REGISTRADURIA NACIONAL DEL ESTADO CIVIL | K40: PROHIDRIK SA ESP | M40: EMDUPAR | Q40: CILEDCO | S40: FUNDACION MEDICO PREVENTIVA | U40: INVERSIONES SANTANA
D41: CENTRALIZADA | F41: Anyela Maria Gutierrez Ochoa | Q41: CLINICA DE LA FRACTURA VALLEDUPAR SAS | S41: HOTEL DAMAR | U41: IVAN MANTILLA SERRANO
F42: ACUEDUCTO | K42: Ingrid_PROPIOS | Q42: COLPENSIONES | S42: HOTEL PANORAMA | U42: JESUS VARGAS BOMBA
F43: ACUEDUCTO_DESCENTRALIZADO | K43: MUNICIPIO DE PAILITAS | M43: Paola_IDECESAR | Q43: COMERCIALIZADORA SAYARA SAS | S43: HOTEL PIBE CRIS | U43: MARTHA CECILIA ARANGO LOPEZ
F44: BOMBEROS_DESCENTRALIZADO | I44: Anyela_BOMBEROS_DESCENTRALIZADO | K44: MUNICIPIO DE CHIRIGUANA | M44: MUNICIPIO DE VALLEDUPAR | Q44: CONCEJO MUNICIPAL CHIMICHAGUA | S44: HOTEL TATIVAN | U44: ORBE LTDA CONSTRUCTORA
F45: EDUCACION | I45: BOMBEROS DE LA JAGUA DE IBIRICO | K45: MUNICIPIO DE LA GLORIA | Q45: DEFENSORIA DEL PUEBLO | S45: IGLESIA LA CONCEPCION | U45: PEAJE COPEY
F46: PROPIOS | K46: MUNICIPIO DE PELAYA | M46: Paola_INTERASEO_S.A.E.S.P | Q46: DIVERSIONES DE COLOMBIA LOCAL 4 | S46: IGLESIA LA CONCEPCION | U46: PEAJE LA LOMA
F47: PROPIOS_LUMINARIAS | K47: MUNICIPIO DE TAMALAMEQUE | M47: INTERASEO | Q47: DROGUERIA CRUZ VERDE | S47: IGLESIA SANTA MARIA | U47: PLATA RUBEN
F48: SALUD | I48: Anyela_PROPIOS_LUMINARIAS | Q48: EL ESQUIMAL HIELO S.A.S. | S48: ING CLINICAL CENTER | U48: POLLOS EL BUCANERO S.A
I49: MUNICIPIO DE BECERRIL | M49: Paola_PROPIO_SIN_PARQUE | Q49: EXPRESO BRASILIA | S49: INVERSALUD DE LAS AMERICAS | U49: PRODUCTOS LACTEOS SAS PLAE DE ALTA EFECTIVIDAD
K50: Ingrid_EDUCACION | M50: MUNICIPIO DE VALLEDUPAR | Q50: FAKARDO MEDINA ALIRIO | S50: INVERSIONES ARZUAGA | U50: RAYCO LA GRANJA
K51: MUNICIPIO DE PAILITAS | Q51: FARMACIAS CRUZ VERDE S A | S51: INVERSIONES DUPAR | U51: VALENCIA PEAJE
K52: MUNICIPIO DE CHIRIGUANA | M52: Paola_ACUEDUCTO | Q52: FENOCO | S52: INVERSIONES PLANES DE PAZ
I53: Dalila_EMPRESA | K53: MUNICIPIO DE LA GLORIA | M53: MUNICIPIO DE VALLEDUPAR | Q53: FIDUCIARIA CENTRAL | S53: IPS KAMKUAMA
I54: COMERCIALIZADORA COLANTA | K54: MUNICIPIO DE PELAYA | Q54: FORESTAL MONTERREY COLOMBIA SAS | S54: JAIME JUAN HOTEL SAN DIEGO
K55: MUNICIPIO DE TAMALAMEQUE | M55: Paola_FONVISOCIAL | Q55: GASNACER S.A. | S55: LACERA EFRAIN
M56: FONVISOCIAL | Q56: GOBERNACIO DEL CESAR BAÑOS PUBLICOS | S56: LACTEOS SAN DIEGO
Q57: GOBERNACION DEL CESAR -ALBERGUE PAILITAS | S57: LADRI SANTO ECCE HOMO
K58: Ingrid_SALUD | M58: Paola_INDER | Q58: GOBERNACION DEL CESAR -EDIFICIO PRINCIPAL | S58: LIBRERÍA DEPARTAMENTAL
K59: E.S.E. HOSPITAL TAMALAMEQUE | M59: MUNICIPIO DE VALLEDUPAR | Q59: GOBERNACION DEL CESAR- ESTADIO DE BEISBOL ERASMO C. SECRET.COLDEPORTE | S59: LTDA COLIN
K60: E.S.E. HOSPITAL SAN JOSE DE LA GLORIA CESAR | Q60: GOBERNACION DEL CESAR -LIGA DE SOFBOL DEL CESAR | S60: MONTECARMELO
K61: HOSPITAL E.S.E HELI MORENO BLANCO | Q61: GOBERNACION DEL CESAR- LOCAL 1 PARQUE GARUPAL | S61: MOTOR KIA
K62: HOSPÍTAL FRANCISCO CANOSSA ESE | M62: Paola_MERCABASTOS | Q62: GOBERNACION DEL CESAR- LOCAL 101 PARQUE GARUPAL | S62: NUEVA EPS
K63: HOSPITAL REGIONAL SAN ANDRES ESE | M63: MUNICIPIO DE VALLEDUPAR | Q63: GOBERNACION DEL CESAR- LOCAL 102 PARQUE GARUPAL | S63: OLIMPICA STEREO
Q64: GOBERNACION DEL CESAR- LOCAL 13PARQUE GARUPAL | S64: ORGANIZACIÓN MEDICA SANTA ISABEL SAS
Q65: GOBERNACION DEL CESAR- LOCAL 2PARQUE GARUPAL | S65: PANADERIA DEL NORTE
Q66: GOBERNACION DEL CESAR- MONUMENTO ECCE-HOMO | S66: PEÑUELA GALVIS
Q67: GOBERNACION DEL CESAR -PARQUE DE LA VIDA | S67: PORVENIR
Q68: GOBERNACION DEL CESAR -PUEBLITO VALLENATO | S68: PROPIEDAD HORIZONTAL ED GALERIA POPULAR
Q69: GOBERNACION DEL CESAR-Antigua Oficina modelo URPA | S69: RADIO GUATAPURI
Q70: GOBERNACION DEL CESAR-ARCHIVO DEPARTAMENTAL | S70: RESIDENCIAS SAN FRANCISCO
Q71: GOBERNACION DEL CESAR-BODEGA RENTA DEPARTAM. | S71: RICARDO ARIZA JORGE ELIECER
Q72: GOBERNACION DEL CESAR-COLISEO CUBIERTO | S72: SRES PAVIMENTOS EL DORADO
Q73: GOBERNACION DEL CESAR-KENNEDY | S73: UNIVERSIDAD DE SANTANDER UDES
Q74: GOBERNACION DEL CESAR-MALARIA
Q75: GOBERNACION DEL CESAR-PARQUE TENISTICO
Q76: GOBERNACION DEL CESAR-PLAZA MERCADO LA LUNA | S76: Rosmeri_CONCEJO_DESCENTRALIZADO
Q77: GOBERNACION DEL CESAR-PLAZOLETA GOBERNACION | S77: CONCEJO MUNICIPAL
Q78: GRANITOS Y MARMOLES ESPAÑOLES CERAMIA
Q79: HOTEL CASA CAMPO EL BOSQUE
Q80: INSTITUTO GEOGRAFICO AGUSTIN CODAZZI | S80: Rosmeri_PROPIOS
Q81: INSTITUTO NACIONAL DE MEDICINA LEGAL | S81: MUNICIPIO DE LA PAZ
Q82: INSTITUTO NACIONAL DE VIAS INVIAS | S82: MUNICIPIO DE MANAURE BALCON DEL CESAR
Q83: INVERSIONES ALTAMIRANDA OROZCO
Q84: LA GRANJA DEL VALLE | S84: Rosmeri_EDUCACION
Q85: LANAO ZABARAIN SELVIS ENRIQUE | S85: HOSPITAL JOSE ANTONIO SOCARRAS ESE
Q86: MANOSALVA QUINTERO JESUS REVELAIS | S86: HOSPITAL MARINO ZULETA RAMIREZ
Q87: MAYA Y ASOCIADOS | S87: MUNICIPIO DE LA PAZ
Q88: MEDICINA INTEGRAL IPS SA | S88: MUNICIPIO DE MANAURE BALCON DEL CESAR
Q89: MERCADERIA SAS
Q90: MUNICIPIO DE ARIGUANI
Q91: MUNICIPIO DE ASTREA
Q92: MUNICIPIO DE CHIMICHAGUA
Q93: MUNICIPIO DE NUEVA GRANADA
Q94: ODONT JOMAR S A S
Q95: OTONIEL LEAL QUINTERO
Q96: PEAJE EL DIFICIL
Q97: PEDRO GOMEZ EDIFICIO MULTICENTRO
Q98: PINEDA DUARTE AMALIA
Q99: PLASTVALL S.A.S.
Q100: POSTRES Y POSTRES DON
...

Sheet Analisis
G1: EJECUTIVO | H1: Anyela Maria Gutierrez Ochoa | N1: EJECUTIVO | O1: Anyela Maria Gutierrez Ochoa
G2: MUNICIPIO | H2: AGUSTIN CODAZZI | N2: MUNICIPIO | O2: AGUSTIN CODAZZI
G3: SEGMENTO EJECUTIVO | H3: (Todas) | N3: SEGMENTO EJECUTIVO | O3: ACUEDUCTO_DESCENTRALIZADO
G5: NIC | H5: DIRECCION DE ENTREGA REAL | I5: SIMB VAR | J5: IMPORTE | K5: SALDO VENCIDO | N5: NIC | O5: DIRECCION DE ENTREGA REAL | P5: SIMB VAR | Q5: IMPORTE | R5: SALDO VENCIDO
G6: 1034390 | H6: Alcaldia de Agustin Codazzi Calle 18 Cra. 15-93 | I6: 1034390065 | J6: 2585190 | K6: 2585190 | N6: 5803338 | O6: CLL6 CRA 4-17 | P6: 5803338336 | Q6: 4000910 | R6: 534271517
G7: 1048898 | H7: Alcaldia de Agustin Codazzi Calle 18 Cra. 15-93 | I7: 1048898063 | J7: 238180 | K7: 238180 | N7: 5827735 | O7: CLL6 CRA 4-17 | P7: 5827735325 | Q7: 5125720 | R7: 22941430
G8: 1048901 | H8: Alcaldia de Agustin Codazzi Calle 18 Cra. 15-93 | I8: 1048901065 | J8: 563200 | K8: 563200 | N8: Total general
G9: 1048906 | H9: Alcaldia de Agustin Codazzi Calle 18 Cra. 15-93 | I9: 1048906063 | J9: 2615720 | K9: 2615720
G10: 1063642 | H10: Alcaldia de Agustin Codazzi Calle 18 Cra. 15-93 | I10: 1063642060 | J10: 3112250 | K10: 3112250
G11: 1067280 | H11: Alcaldia de Agustin Codazzi Calle 18 Cra. 15-93 | I11: 1067280050 | J11: 740650 | K11: 740650
G12: 1080798 | H12: Alcaldia de Agustin Codazzi Calle 18 Cra. 15-93 | I12: 1080798055 | J12: 842170 | K12: 842170
G13: 1088785 | H13: Alcaldia de Agustin Codazzi Calle 18 Cra. 15-93 | I13: 1088785057 | J13: 247820 | K13: 247820
G14: 1088786 | H14: Alcaldia de Agustin Codazzi Calle 18 Cra. 15-93 | I14: 1088786055 | J14: 120650 | K14: 120650
G15: 1344722 | H15: Alcaldia de Agustin Codazzi Calle 18 Cra. 15-93 | I15: 1344722027 | J15: 5491580 | K15: 5491580
G16: 1379384 | H16: Alcaldia de Agustin Codazzi Calle 18 Cra. 15-93 | I16: 1379384018 | J16: 1667330 | K16: 1667330
G17: 1379392 | H17: Alcaldia de Agustin Codazzi Calle 18 Cra. 15-93 | I17: 1379392018 | J17: 1667330 | K17: 1667330
G18: 1379396 | H18: Alcaldia de Agustin Codazzi Calle 18 Cra. 15-93 | I18: 1379396018 | J18: 1570770 | K18: 1570770
G19: 1379400 | H19: Alcaldia de Agustin Codazzi Calle 18 Cra. 15-93 | I19: 1379400017 | J19: 217110 | K19: 217110
G20: 1379404 | H20: Alcaldia de Agustin Codazzi Calle 18 Cra. 15-93 | I20: 1379404017 | J20: 181280 | K20: 181280
... G87: 7925626 | H87: Alcaldia de Agustin Codazzi Calle 18 Cra. 15-93 | I87: 7925626103 | J87: 5527410 | K87: 5527410
G88: Total general

Sheet Hoja2
A3: DIRECCION DE ENTREGA REAL | B3: TITULAR DE PAGO | C3: Cuenta de DIRECCION DE ENTREGA REAL
A4: CALLE 7 No 6 - 04 Barrio Fundacion - Hospital Tamalameque | B4: HOSPITAL TAMALAMEQUE | C4: 2
A5: tesoreria@agroindustriasjmd.com | B5: AGROINDUSTRIAS JMD Y | C5: 7
A6: Alcaldia de Agustin Codazzi Calle 18 Cra. 15-93 | B6: MUNICIPIO DE AGUSTIN | C6: 82
A7: Alcaldia de Curumani CLL 7 No.16-36 | B7: ACUACUR ESP | C7: 1
A8: Alcaldia de Curumani CLL 7 No.16-36 | B8: MUNICIPIO DE CURUMAN | C8: 68
A9: AREOPUERTO ALFONSO LOPEZ/VALLEDUPAR | B9: AEROCIVIL | C9: 3
A10: CALLE 10 # 22 - 52 EL COPEY | B10: EMPRESA DE SERVICIOS | C10: 2
A11: Calle 10 No. 10 - 75 - Hospital Francisco Canossa | B11: HOSPITAL FRANCISCO C | C11: 2
A12: CALLE 13 16A-35 - CODAZZI | B12: ALIMENTOS FRESCOS DE | C12: 1
A13: Calle 2 #8-56, Barrio Aríguani, Pueblo Bello | B13: FUNDACION MEMBRANA | C13: 1
A14: CALLE 2 No 5 A -75 Barrio El Centro - Alcaldia Municipal | B14: EMPRESA DE SERVICIOS | C14: 4
A15: CALLE 2 No 5 A -75 Barrio El Centro - Alcaldia Municipal | B15: MUNICIPIO DE LA GLOR | C15: 23
... A312: Vía Troncal del Oriente KM 7 | B312: POLICIA NACIONAL | C312: 1
A313: Total general | C313: 1992

Sheet INFO
A1: NIC | B1: FECHA EMISION | C1: NOMBRE DEL CLIENTE | D1: TITULAR DE PAGO | E1: DIRECCION DE LA CUENTA | F1: NIC2 | G1: SIMB VAR | H1: NIF | I1: NIS-RAD | J1: UNIC | K1: RUTA | L1: ITIN | M1: F. LECTURA | N1: TAR | O1: DESCRIPCION TARIFA | P1: IMPORTE | Q1: CSMO.KWH | R1: IMPORTE KWH | S1: POSICION | T1: SEC. ORDEN | U1: F. PAGO OPORTUNO | V1: MUNICIPIO | W1: TIPO DE MEDIDA | X1: PROPIEDAD DEL ACTIVO | Y1: FOES | Z1: DIAS FACTURADOS | AA1: ORDENADO (SI / NO) | AB1: CONSECUTIVO PDF | AC1: CENTRO DE IMPRESION | AD1: EXCLUIR (NO / VIRTUAL / ECA) | AE1: CLIENTE DISPERSO (SI / NO / CENTRALIZADA) | AF1: NOMBRE INFO | AG1: TIPO CLIENTE | AH1: CIIU | AI1: FECHA LECTURA INICIAL | AJ1: CIRCUITO | AK1: SALDO VENCIDO | AL1: OBSERVACION FACTURA | AM1: CENTRALIZADA | AN1: FISICOS | AO1: OBSERVACIONES VENTAS | AP1: EJECUTIVO | AQ1: DIRECCION DE ENTREGA REAL | AR1: SEGMENTO EJECUTIVO | AS1: DESCRIPCIÓN DE SUMINISTRO
A2: 5312024 | B2: 46111 | C2: COOPERATIVA COLANTA | D2: COMERCIALIZADORA COLANTA | E2: CENTRAL DE ABASTOS VALLEDUPAR DG 21 54-6 P 1 LOC 3B | F2: 5312024 | G2: 5312024295 | H2: 25308882 | I2: 5324022 | J2: 3110 | K2: 50 | L2: 2003 | M2: 46099 | N2: CZ1 | O2: Com (Sencilla Niv.1 ) Caribe | P2: 12452090 | Q2: 9480 | R2: 10506001 | T2: 63110EN0022531195500200502003000160 | U2: 46121 | V2: VALLEDUPAR | W2: NIVEL I | X2: Propiedad Empresa | Y2: MEDICION | Z2: 30 | AA2: SI | AB2: 1 | AC2: VALLEDUPAR | AD2: NO | AE2: NO | AF2: INFO_CONSOL_ESPECIALES | AG2: Comercial Liberalizado | AH2: Comercio al por menor en | AI2: 46069 | AJ2: VALLEDUPAR 2 | AK2: 12452090 | AL2: #N/A | AM2: #N/A | AN2: RECIBIDO | AO2: =_xlfn.XLOOKUP(Tabla1[[#This Row],[NIC]],'R.V.'!B:B,'R.V.'!I:I) -> 0 | AP2: =_xlfn.XLOOKUP(Tabla1[[#This Row],[NIC]],'R.V.'!B:B,'R.V.'!A:A) -> Dalila Michela Bracho Acosta | AQ2: =_xlfn.XLOOKUP(Tabla1[[#This Row],[NIC]],'R.V.'!B:B,'R.V.'!G:G) -> DG 21, 54 6 P1 LOC 3B CENTRAL DE ABASTOS | AR2: =_xlfn.XLOOKUP(Tabla1[[#This Row],[NIC]],'R.V.'!B:B,'R.V.'!E:E) -> EMPRESA | AS2: =VLOOKUP(Tabla1[[#This Row],[NIC]],'R.V.'!B:D,3,0) -> PRIVADO
A3: 5808658 | B3: 46111 | C3: GOBERNACION DE DE LA | D3: CENTRO EDUCATIVO EL PLAN | E3: EL PLAN RURAL EL PLAN CR 5 CL 5-55 | F3: 5808658 | G3: 5808658335 | H3: 25843478 | I3: 5808658 | J3: 3110 | K3: 60 | L3: 1 | M3: 46082 | N3: CZ1 | O3: Com (Sencilla Niv.1 ) Caribe | P3: 0 | Q3: 351 | R3: 368978.22 | T3: 63110EN0022565187900100600001010660 | V3: LA JAGUA DEL PILAR | W3: NIVEL I | X3: Propiedad Empresa | Y3: MEDICION | Z3: 28 | AA3: SI | AB3: 2 | AC3: VALLEDUPAR | AD3: NO | AE3: NO | AF3: INFO_CONSOL_ESPECIALES | AG3: Regulado Oficial Departamental | AH3: Educación | AI3: 46054 | AJ3: BALCON DEL CESAR 1 | AK3: 9954600 | AL3: #N/A | AM3: #N/A | AN3: RECIBIDO | AO3: =_xlfn.XLOOKUP(Tabla1[[#This Row],[NIC]],'R.V.'!B:B,'R.V.'!I:I) -> #N/A | AP3: =_xlfn.XLOOKUP(Tabla1[[#This Row],[NIC]],'R.V.'!B:B,'R.V.'!A:A) -> #N/A | AQ3: =_xlfn.XLOOKUP(Tabla1[[#This Row],[NIC]],'R.V.'!B:B,'R.V.'!G:G) -> #N/A | AR3: =_xlfn.XLOOKUP(Tabla1[[#This Row],[NIC]],'R.V.'!B:B,'R.V.'!E:E) -> #N/A | AS3: =VLOOKUP(Tabla1[[#This Row],[NIC]],'R.V.'!B:D,3,0) -> #N/A
A4: 6894764 | B4: 46111 | C4: ING CLINICAL CENTER | D4: ING CLINICAL CENTER SAS | E4: SANTA ANA VALLEDUPAR CL 16 17-261 | F4: 6894764 | G4: 6894764260 | H4: 34000167 | I4: 7723098 | J4: 3110 | K4: 50 | L4: 2005 | M4: 46106 | N4: CY2 | O4: Com(Mon.dbl.Tip2Niv.2)Caribe | P4: 114182410 | Q4: 112200 | R4: 98787898 | T4: 63110EN0023637806400100502005001270 | U4: 46121 | V4: VALLEDUPAR | W4: NIVEL II | X4: Propiedad Empresa | Y4: MEDICION | Z4: 32 | AA4: SI | AB4: 3 | AC4: VALLEDUPAR | AD4: NO | AE4: NO | AF4: INFO_CONSOL_ESPECIALES | AG4: Comercial Liberalizado | AH4: Actividades de hospitales | AI4: 46074 | AJ4: GUATAPURI 1 | AK4: 3916883097 | AL4: #N/A | AM4: #N/A | AN4: RECIBIDO | AO4: =_xlfn.XLOOKUP(Tabla1[[#This Row],[NIC]],'R.V.'!B:B,'R.V.'!I:I) -> 0 | AP4: =_xlfn.XLOOKUP(Tabla1[[#This Row],[NIC]],'R.V.'!B:B,'R.V.'!A:A) -> Rosmeri Rivera Rodriguez | AQ4: =_xlfn.XLOOKUP(Tabla1[[#This Row],[NIC]],'R.V.'!B:B,'R.V.'!G:G) -> CL 16 17 261 OFI 3 - VALLEDUPAR | AR4: =_xlfn.XLOOKUP(Tabla1[[#This Row],[NIC]],'R.V.'!B:B,'R.V.'!E:E) -> PRIVADO | AS4: =VLOOKUP(Tabla1[[#This Row],[NIC]],'R.V.'!B:D,3,0) -> ING CLINICAL CENTER
A5: 6908929 | B5: 46111 | C5: ING CLINICAL CENTER | D5: ING CLINICAL CENTER SAS | E5: SANTA ANA VALLEDUPAR CL 16 17-261 | F5: 6908929 | G5: 6908929237 | H5: 25320410 | I5: 7771911 | J5: 3110 | K5: 50 | L5: 2005 | M5: 46106 | N5: CZ1 | O5: Com (Sencilla Niv.1 ) Caribe | P5: 402110 | Q5: 320 | R5: 352211.2 | T5: 63110EN0023637806400100502005001270 | U5: 46121 | V5: VALLEDUPAR | W5: NIVEL I | X5: Propiedad Empresa | Y5: MEDICION | Z5: 32 | AA5: SI | AB5: 3 | AC5: VALLEDUPAR | AD5: NO | AE5: NO | AF5: INFO_CONSOL_ESPECIALES | AG5: Comercial Liberalizado | AH5: Actividades de administra | AI5: 46074 | AJ5: GUATAPURI 1 | AK5: 1646660 | AL5: #N/A | AM5: #N/A | AN5: RECIBIDO | AO5: =_xlfn.XLOOKUP(Tabla1[[#This Row],[NIC]],'R.V.'!B:B,'R.V.'!I:I) -> 0 | AP5: =_xlfn.XLOOKUP(Tabla1[[#This Row],[NIC]],'R.V.'!B:B,'R.V.'!A:A) -> Rosmeri Rivera Rodriguez | AQ5: =_xlfn.XLOOKUP(Tabla1[[#This Row],[NIC]],'R.V.'!B:B,'R.V.'!G:G) -> CL 16 17 261 OFI 3 - VALLEDUPAR | AR5: =_xlfn.XLOOKUP(Tabla1[[#This Row],[NIC]],'R.V.'!B:B,'R.V.'!E:E) -> PRIVADO | AS5: =VLOOKUP(Tabla1[[#This Row],[NIC]],'R.V.'!B:D,3,0) -> ING CLINICAL CENTER
A6: 5818889 | B6: 46111 | C6: SRES MUNICIPIO DE LA | D6: SRES MUNICIPIO DE LA | E6: CENTRO LA PAZ CL 6 CR 8-9 | F6: 5818889 | G6: 5818889325 | H6: 25857255 | I6: 5824934 | J6: 3110 | K6: 70 | L6: 150 | M6: 46094 | N6: OW1 | O6: Ofi (Sencilla Niv.1) Caribe | P6: 123240 | Q6: 122 | R6: 111900.84 | T6: 63110EN0022586181500200700150009860 | U6: 46121 | V6: LA PAZ | W6: NIVEL I | X6: Propiedad Empresa | Y6: ESTIMADO | Z6: 30 | AA6: SI | AB6: 4 | AC6: VALLEDUPAR | AD6: NO | AE6: NO | AF6: INFO_CONSOL_ESPECIALES | AG6: Regulado Oficial Municipal | AH6: Comercio al por menor en | AI6: 46064 | AJ6: BALCON DEL CESAR 2 | AK6: 240820 | AL6: #N/A | AM6: #N/A | AN6: RECIBIDO | AO6: =_xlfn.XLOOKUP(Tabla1[[#This Row],[NIC]],'R.V.'!B:B,'R.V.'!I:I) -> 0 | AP6: =_xlfn.XLOOKUP(Tabla1[[#This Row],[NIC]],'R.V.'!B:B,'R.V.'!A:A) -> Rosmeri Rivera Rodriguez | AQ6: =_xlfn.XLOOKUP(Tabla1[[#This Row],[NIC]],'R.V.'!B:B,'R.V.'!G:G) -> CR 9 6 36 - LA PAZ | AR6: =_xlfn.XLOOKUP(Tabla1[[#This Row],[NIC]],'R.V.'!B:B,'R.V.'!E:E) -> PROPIOS | AS6: =VLOOKUP(Tabla1[[#This Row],[NIC]],'R.V.'!B:D,3,0) -> MATADERO MUNICIPAL
A7: 5819129 | B7: 46111 | C7: SRES MUNICIPIO DE LA | D7: SRES MUNICIPIO DE LA | E7: CENTRO LA PAZ CL 6 CR 8-9 | F7: 5819129 | G7: 5819129328 | H7: 25835592 | I7: 5825414 | J7: 3110 | K7: 50 | L7: 2009 | M7: 46105 | N7: OW1 | O7: Ofi (Sencilla Niv.1) Caribe | P7: 1187010 | Q7: 1120 | R7: 1027286.4 | T7: 63110EN0022586181500200502009000481 | U7: 46121 | V7: LA PAZ | W7: NIVEL I | X7: Propiedad Empresa | Y7: MEDICION | Z7: 32 | AA7: SI | AB7: 4 | AC7: VALLEDUPAR | AD7: NO | AE7: NO | AF7: INFO_CONSOL_ESPECIALES | AG7: Regulado Oficial Municipal | AH7: Administración del Estado | AI7: 46073 | AJ7: LA PAZ | AK7: 2016060 | AL7: #N/A | AM7: #N/A | AN7: RECIBIDO | AO7: =_xlfn.XLOOKUP(Tabla1[[#This Row],[NIC]],'R.V.'!B:B,'R.V.'!I:I) -> 0 | AP7: =_xlfn.XLOOKUP(Tabla1[[#This Row],[NIC]],'R.V.'!B:B,'R.V.'!A:A) -> Rosmeri Rivera Rodriguez | AQ7: =_xlfn.XLOOKUP(Tabla1[[#This Row],[NIC]],'R.V.'!B:B,'R.V.'!G:G) -> CR 9 6 36 - LA PAZ | AR7: =_xlfn.XLOOKUP(Tabla1[[#This Row],[NIC]],'R.V.'!B:B,'R.V.'!E:E) -> PROPIOS | AS7: =VLOOKUP(Tabla1[[#This Row],[NIC]],'R.V.'!B:D,3,0) -> BIBLIOTECA M. CANTILLO
A8: 5819133 | B8: 46111 | C8: SRES MUNICIPIO DE LA | D8: SRES MUNICIPIO DE LA | E8: CENTRO LA PAZ CL 6 CR 8-9 | F8: 5819133 | G8: 5819133340 | H8: 25836898 | I8: 5825422 | J8: 3110 | K8: 70 | L8: 150 | M8: 46092 | N8: OW1 | O8: Ofi (Sencilla Niv.1) Caribe | P8: 746980 | Q8: 672 | R8: 616371.84 | T8: 63110EN0022586181500200700150009860 | U8: 46121 | V8: LA PAZ | W8: NIVEL I | X8: Propiedad Empresa | Y8: ESTIMADO | Z8: 30 | AA8: SI | AB8: 4 | AC8: VALLEDUPAR | AD8: NO | AE8: NO | AF8: INFO_CONSOL_ESPECIALES | AG8: Regulado Oficial Municipal | AH8: Actividades deportivas. | AI8: 46062 | AJ8: LA PAZ | AK8: 1375650 | AL8: #N/A | AM8: #N/A | AN8: RECIBIDO | AO8: =_xlfn.XLOOKUP(Tabla1[[#This Row],[NIC]],'R.V.'!B:B,'R.V.'!I:I) -> 0 | AP8: =_xlfn.XLOOKUP(Tabla1[[#This Row],[NIC]],'R.V.'!B:B,'R.V.'!A:A) -> Rosmeri Rivera Rodriguez | AQ8: =_xlfn.XLOOKUP(Tabla1[[#This Row],[NIC]],'R.V.'!B:B,'R.V.'!G:G) -> CR 9 6 36 - LA PAZ | AR8: =_xlfn.XLOOKUP(Tabla1[[#This Row],[NIC]],'R.V.'!B:B,'R.V.'!E:E) -> PROPIOS | AS8: =VLOOKUP(Tabla1[[#This Row],[NIC]],'R.V.'!B:D,3,0) -> ESTADIO EDINSON MEJIA
A9: 5839002 | B9: 46111 | C9: SRES MUNICIPIO DE LA | D9: SRES MUNICIPIO DE LA | E9: CENTRO LA PAZ CL 6 CR 8-9 | F9: 5839002 | G9: 5839002322 | H9: 25856600 | I9: 5865160 | J9: 3110 | K9: 70 | L9: 150 | M9: 46093 | N9: OW1 | O9: Ofi (Sencilla Niv.1) Caribe | P9: 1010 | Q9: 1 | R9: 917.22 | T9: 63110EN0022586181500200700150009860 | U9: 46121 | V9: LA PAZ | W9: NIVEL I | X9: Propiedad Empresa | Y9: ESTIMADO | Z9: 30 | AA9: SI | AB9: 4 | AC9: VALLEDUPAR | AD9: NO | AE9: NO | AF9: INFO_CONSOL_ESPECIALES | AG9: Regulado Oficial Municipal | AH9: Actividades administrativ | AI9: 46063 | AJ9: MANAURE (CESAR) | AK9: 1970 | AL9: #N/A | AM9: #N/A | AN9: RECIBIDO | AO9: =_xlfn.XLOOKUP(Tabla1[[#This Row],[NIC]],'R.V.'!B:B,'R.V.'!I:I) -> 0 | AP9: =_xlfn.XLOOKUP(Tabla1[[#This Row],[NIC]],'R.V.'!B:B,'R.V.'!A:A) -> Rosmeri Rivera Rodriguez | AQ9: =_xlfn.XLOOKUP(Tabla1[[#This Row],[NIC]],'R.V.'!B:B,'R.V.'!G:G) -> CR 9 6 36 - LA PAZ | AR9: =_xlfn.XLOOKUP(Tabla1[[#This Row],[NIC]],'R.V.'!B:B,'R.V.'!E:E) -> PROPIOS | AS9: =VLOOKUP(Tabla1[[#This Row],[NIC]],'R.V.'!B:D,3,0) -> INPECCION VARAS BLANCAS
A10: 5839387 | B10: 46111 | C10: SRES MUNICIPIO DE LA | D10: SRES MUNICIPIO DE LA | E10: CENTRO LA PAZ CL 6 CR 8-9 | F10: 5839387 | G10: 5839387331 | H10: 25835583 | I10: 5865930 | J10: 3110 | K10: 70 | L10: 150 | M10: 46098 | N10: OW1 | O10: Ofi (Sencilla Niv.1) Caribe | P10: 2049780 | Q10: 1974 | R10: 1810592.3 | T10: 63110EN0022586181500200700150009860 | U10: 46121 | V10: LA PAZ | W10: NIVEL I | X10: Propiedad Empresa | Y10: MEDICION | Z10: 31 | AA10: SI | AB10: 4 | AC10: VALLEDUPAR | AD10: NO | AE10: NO | AF10: INFO_CONSOL_ESPECIALES | AG10: Regulado Oficial Municipal | AH10: Administración del Estado | AI10: 46067 | AJ10: LA PAZ | AK10: 2922970 | AL10: #N/A | AM10: #N/A | AN10: RECIBIDO | AO10: =_xlfn.XLOOKUP(Tabla1[[#This Row],[NIC]],'R.V.'!B:B,'R.V.'!I:I) -> 0 | AP10: =_xlfn.XLOOKUP(Tabla1[[#This Row],[NIC]],'R.V.'!B:B,'R.V.'!A:A) -> Rosmeri Rivera Rodriguez | AQ10: =_xlfn.XLOOKUP(Tabla1[[#This Row],[NIC]],'R.V.'!B:B,'R.V.'!G:G) -> CR 9 6 36 - LA PAZ | AR10: =_xlfn.XLOOKUP(Tabla1[[#This Row],[NIC]],'R.V.'!B:B,'R.V.'!E:E) -> PROPIOS | AS10: =VLOOKUP(Tabla1[[#This Row],[NIC]],'R.V.'!B:D,3,0) -> CASA DE LA CULTURA
A11: 5840257 | B11: 46111 | C11: SRES MUNICIPIO DE LA | D11: SRES MUNICIPIO DE LA | E11: CENTRO LA PAZ CL 6 CR 8-9 | F11: 5840257 | G11: 5840257326 | H11: 25836195 | I11: 5867670 | J11: 3110 | K11: 70 | L11: 150 | M11: 46092 | N11: OW1 | O11: Ofi (Sencilla Niv.1) Caribe | P11: 350860 | Q11: 291 | R11: 266911.02 | T11: 63110EN0022586181500200700150009860 | U11: 46121 | V11: LA PAZ | W11: NIVEL I | X11: Propiedad Empresa | Y11: ESTIMADO | Z11: 30 | AA11: SI | AB11: 4 | AC11: VALLEDUPAR | AD11: NO | AE11: NO | AF11: INFO_CONSOL_ESPECIALES | AG11: Regulado Oficial Municipal | AH11: Centros carcelarios | AI11: 46062 | AJ11: LA PAZ | AK11: 768000 | AL11: #N/A | AM11: #N/A | AN11: RECIBIDO | AO11: =_xlfn.XLOOKUP(Tabla1[[#This Row],[NIC]],'R.V.'!B:B,'R.V.'!I:I) -> 0 | AP11: =_xlfn.XLOOKUP(Tabla1[[#This Row],[NIC]],'R.V.'!B:B,'R.V.'!A:A) -> Rosmeri Rivera Rodriguez | AQ11: =_xlfn.XLOOKUP(Tabla1[[#This Row],[NIC]],'R.V.'!B:B,'R.V.'!G:G) -> CR 9 6 36 - LA PAZ | AR11: =_xlfn.XLOOKUP(Tabla1[[#This Row],[NIC]],'R.V.'!B:B,'R.V.'!E:E) -> PROPIOS | AS11: =VLOOKUP(Tabla1[[#This Row],[NIC]],'R.V.'!B:D,3,0) -> CARCEL MUNICIPAL
A12: 5840322 | B12: 46111 | C12: SRES MUNICIPIO DE LA | D12: SRES MUNICIPIO DE LA | E12: CENTRO LA PAZ CL 6 CR 8-9 | F12: 5840322 | G12: 5840322346 | H12: 25835642 | I12: 5867800 | J12: 3110 | K12: 50 | L12: 2012 | M12: 46105 | N12: OW1 | O12: Ofi (Sencilla Niv.1) Caribe | P12: 7361020 | Q12: 7520 | R12: 6640009.6 | T12: 63110EN0022586181500200502012001061 | U12: 46121 | V12: LA PAZ | W12: NIVEL I | X12: Propiedad Cliente | Y12: MEDICION | Z12: 32 | AA12: SI | AB12: 4 | AC12: VALLEDUPAR | AD12: NO | AE12: NO | AF12: INFO_CONSOL_ESPECIALES | AG12: Regulado Oficial Municipal | AH12: Administración del Estado | AI12: 46073 | AJ12: MANAURE (CESAR) | AK12: 13354920 | AL12: #N/A | AM12: #N/A | AN12: RECIBIDO | AO12: =_xlfn.XLOOKUP(Tabla1[[#This Row],[NIC]],'R.V.'!B:B,'R.V.'!I:I) -> 0 | AP12: =_xlfn.XLOOKUP(Tabla1[[#This Row],[NIC]],'R.V.'!B:B,'R.V.'!A:A) -> Rosmeri Rivera Rodriguez | AQ12: =_xlfn.XLOOKUP(Tabla1[[#This Row],[NIC]],'R.V.'!B:B,'R.V.'!G:G) -> CR 9 6 36 - LA PAZ | AR12: =_xlfn.XLOOKUP(Tabla1[[#This Row],[NIC]],'R.V.'!B:B,'R.V.'!E:E) -> PROPIOS | AS12: =VLOOKUP(Tabla1[[#This Row],[NIC]],'R.V.'!B:D,3,0) -> PALACIO MUNICIPAL DE LA PAZ
A13: 5840503 | B13: 46111 | C13: SRES MUNICIPIO DE LA | D13: SRES MUNICIPIO DE LA | E13: CENTRO LA PAZ CL 6 CR 8-9 | F13: 5840503 | G13: 5840503332 | H13: 25836675 | I13: 5868162 | J13: 3110 | K13: 70 | L13: 150 | M13: 46098 | N13: OW1 | O13: Ofi (Sencilla Niv.1) Caribe | P13: 628130 | Q13: 588 | R13: 539325.36 | T13: 63110EN0022586181500200700150009860 | U13: 46121 | V13: LA PAZ | W13: NIVEL I | X13: Propiedad Empresa | Y13: MEDICION | Z13: 31 | AA13: SI | AB13: 4 | AC13: VALLEDUPAR | AD13: NO | AE13: NO | AF13: INFO_CONSOL_ESPECIALES | AG13: Regulado Oficial Municipal | AH13: Actividades de asistencia | AI13: 46067 | AJ13: LA PAZ | AK13: 1099810 | AL13: #N/A | AM13: #N/A | AN13: RECIBIDO | AO13: =_xlfn.XLOOKUP(Tabla1[[#This Row],[NIC]],'R.V.'!B:B,'R.V.'!I:I) -> 0 | AP13: =_xlfn.XLOOKUP(Tabla1[[#This Row],[NIC]],'R.V.'!B:B,'R.V.'!A:A) -> Rosmeri Rivera Rodriguez | AQ13: =_xlfn.XLOOKUP(Tabla1[[#This Row],[NIC]],'R.V.'!B:B,'R.V.'!G:G) -> CR 9 6 36 - LA PAZ | AR13: =_xlfn.XLOOKUP(Tabla1[[#This Row],[NIC]],'R.V.'!B:B,'R.V.'!E:E) -> PROPIOS | AS13: =VLOOKUP(Tabla1[[#This Row],[NIC]],'R.V.'!B:D,3,0) -> CASA ADULTO MAYOR
A14: 6654078 | B14: 46111 | C14: SRES MUNICIPIO DE LA | D14: SRES MUNICIPIO DE LA | E14: CENTRO LA PAZ CL 6 CR 8-9 | F14: 6654078 | G14: 6654078258 | H14: 35034213 | I14: 6979907 | J14: 3110 | K14: 70 | L14: 150 | M14: 46098 | N14: OW1 | O14: Ofi (Sencilla Niv.1) Caribe | P14: 1953500 | Q14: 1878 | R14: 1722539.2 | T14: 63110EN0022586181500200700150009860 | U14: 46121 | V14: LA PAZ | W14: NIVEL I | X14: Propiedad Empresa | Y14: MEDICION | Z14: 31 | AA14: SI | AB14: 4 | AC14: VALLEDUPAR | AD14: NO | AE14: NO | AF14: INFO_CONSOL_ESPECIALES | AG14: Regulado Oficial Municipal | AH14: Actividades administrativ | AI14: 46067 | AJ14: MANAURE (CESAR) | AK14: 3545210 | AL14: #N/A | AM14: #N/A | AN14: RECIBIDO | AO14: =_xlfn.XLOOKUP(Tabla1[[#This Row],[NIC]],'R.V.'!B:B,'R.V.'!I:I) -> 0 | AP14: =_xlfn.XLOOKUP(Tabla1[[#This Row],[NIC]],'R.V.'!B:B,'R.V.'!A:A) -> Rosmeri Rivera Rodriguez | AQ14: =_xlfn.XLOOKUP(Tabla1[[#This Row],[NIC]],'R.V.'!B:B,'R.V.'!G:G) -> CR 9 6 36 - LA PAZ | AR14: =_xlfn.XLOOKUP(Tabla1[[#This Row],[NIC]],'R.V.'!B:B,'R.V.'!E:E) -> PROPIOS | AS14: =VLOOKUP(Tabla1[[#This Row],[NIC]],'R.V.'!B:D,3,0) -> TRANSITO MUNICIPAL DE LA PAZ
A15: 7530493 | B15: 46111 | C15: SRES MUNICIPIO DE LA | D15: SRES MUNICIPIO DE LA | E15: CENTRO LA PAZ CL 6 CR 8-9 | F15: 7530493 | G15: 7530493206 | H15: 35157822 | I15: 8342674 | J15: 3110 | K15: 70 | L15: 150 | M15: 46098 | N15: OW1 | O15: Ofi (Sencilla Niv.1) Caribe | P15: 373970 | Q15: 314 | R15: 288007.08 | T15: 63110EN0022586181500200700150009860 | U15: 46121 | V15: LA PAZ | W15: NIVEL I | X15: Propiedad Empresa | Y15: MEDICION | Z15: 31 | AA15: SI | AB15: 4 | AC15: VALLEDUPAR | AD15: NO | AE15: NO | AF15: INFO_CONSOL_ESPECIALES | AG15: Regulado Oficial Municipal | AH15: Suministro espacio púbico | AI15: 46067 | AJ15: EL PASO 2 | AK15: 811260 | AL15: #N/A | AM15: #N/A | AN15: RECIBIDO | AO15: =_xlfn.XLOOKUP(Tabla1[[#This Row],[NIC]],'R.V.'!B:B,'R.V.'!I:I) -> 0 | AP15: =_xlfn.XLOOKUP(Tabla1[[#This Row],[NIC]],'R.V.'!B:B,'R.V.'!A:A) -> Rosmeri Rivera Rodriguez | AQ15: =_xlfn.XLOOKUP(Tabla1[[#This Row],[NIC]],'R.V.'!B:B,'R.V.'!G:G) -> CR 9 6 36 - LA PAZ | AR15: =_xlfn.XLOOKUP(Tabla1[[#This Row],[NIC]],'R.V.'!B:B,'R.V.'!E:E) -> PROPIOS | AS15: =VLOOKUP(Tabla1[[#This Row],[NIC]],'R.V.'!B:D,3,0) -> TARIMA JORGE OÑATE -
... A48: 7586589 | B48: 46111 | C48: SRES MUNICIPIO DE LA | D48: SRES MUNICIPIO DE LA | E48: CENTRO LA PAZ CR 9 6-36 | F48: 7586589 | G48: 7586589179 | H48: 36025079 | I48: 8672796 | J48: 3110 | K48: 70 | L48: 130 | M48: 46097 | N48: CZ1 | O48: Com (Sencilla Niv.1 ) Caribe | P48: 11100 | Q48: 11 | R48: 10089.42 | T48: 63110EN0022586181500100700130008066 | U48: 46121 | V48: LA PAZ | W48: NIVEL I | X48: Propiedad Empresa | Y48: MEDICION | Z48: 31 | AA48: SI | AB48: 5 | AC48: VALLEDUPAR | AD48: NO | AE48: NO | AF48: INFO_CONSOL_ESPECIALES | AG48: Regulado Oficial Municipal | AH48: Educación | AI48: 46066 | AJ48: EL PASO 2 | AK48: 21710 | AL48: #N/A | AM48: #N/A | AN48: RECIBIDO | AO48: =_xlfn.XLOOKUP(Tabla1[[#This Row],[NIC]],'R.V.'!B:B,'R.V.'!I:I) -> 0 | AP48: =_xlfn.XLOOKUP(Tabla1[[#This Row],[NIC]],'R.V.'!B:B,'R.V.'!A:A) -> Rosmeri Rivera Rodriguez | AQ48: =_xlfn.XLOOKUP(Tabla1[[#This Row],[NIC]],'R.V.'!B:B,'R.V.'!G:G) -> CR 9 6 36 - LA PAZ | AR48: =_xlfn.XLOOKUP(Tabla1[[#This Row],[NIC]],'R.V.'!B:B,'R.V.'!E:E) -> EDUCACION | AS48: =VLOOKUP(Tabla1[[#This Row],[NIC]],'R.V.'!B:D,3,0) -> ESCUELA NUEVA BOTIJA ( VDA BOTIJA VDA MINGUILLO LA PAZ CESAR )
A49: 7586593 | B49: 46111 | C49: SRES MUNICIPIO DE LA | D49: SRES MUNICIPIO DE LA | E49: CENTRO LA PAZ CR 9 6-36 | F49: 7586593 | G49: 7586593187 | H49: 36025082 | I49: 8672812 | J49: 3110 | K49: 70 | L49: 130 | M49: 46094 | N49: CZ1 | O49: Com (Sencilla Niv.1 ) Caribe | P49: 0 | Q49: 0 | R49: 0 | T49: 63110EN0022586181500100700130008066 | V49: LA PAZ | W49: NIVEL I | X49: Propiedad Empresa | Y49: ESTIMADO | Z49: 30 | AA49: SI | AB49: 5 | AC49: VALLEDUPAR | AD49: NO | AE49: NO | AF49: INFO_CONSOL_ESPECIALES | AG49: Regulado Oficial Municipal | AH49: Educación | AI49: 46064 | AJ49: EL DESASTRE | AK49: 960 | AL49: #N/A | AM49: #N/A | AN49: RECIBIDO | AO49: =_xlfn.XLOOKUP(Tabla1[[#This Row],[NIC]],'R.V.'!B:B,'R.V.'!I:I) -> 0 | AP49: =_xlfn.XLOOKUP(Tabla1[[#This Row],[NIC]],'R.V.'!B:B,'R.V.'!A:A) -> Rosmeri Rivera Rodriguez | AQ49: =_xlfn.XLOOKUP(Tabla1[[#This Row],[NIC]],'R.V.'!B:B,'R.V.'!G:G) -> CR 9 6 36 - LA PAZ | AR49: =_xlfn.XLOOKUP(Tabla1[[#This Row],[NIC]],'R.V.'!B:B,'R.V.'!E:E) -> EDUCACION | AS49: =VLOOKUP(Tabla1[[#This Row],[NIC]],'R.V.'!B:D,3,0) -> ESCUELA NUEVA LOS ANDES ( VDA LOS ANDES LA PAZ CESAR )
A50: 7586601 | B50: 46111 | C50: SRES MUNICIPIO DE LA | D50: SRES MUNICIPIO DE LA | E50: CENTRO LA PAZ CR 9 6-36 | F50: 7586601 | G50: 7586601186 | H50: 36025096 | I50: 8672843 | J50: 3110 | K50: 70 | L50: 130 | M50: 46094 | N50: CZ1 | O50: Com (Sencilla Niv.1 ) Caribe | P50: 0 | Q50: 0 | R50: 0 | T50: 63110EN0022586181500100700130008066 | V50: LA PAZ | W50: NIVEL I | X50: Propiedad Empresa | Y50: MEDICION | Z50: 30 | AA50: SI | AB50: 5 | AC50: VALLEDUPAR | AD50: NO | AE50: NO | AF50: INFO_CONSOL_ESPECIALES | AG50: Regulado Oficial Municipal | AH50: Educación | AI50: 46064 | AJ50: EL DESASTRE | AK50: 0 | AL50: #N/A | AM50: #N/A | AN50: RECIBIDO | AO50: =_xlfn.XLOOKUP(Tabla1[[#This Row],[NIC]],'R.V.'!B:B,'R.V.'!I:I) -> 0 | AP50: =_xlfn.XLOOKUP(Tabla1[[#This Row],[NIC]],'R.V.'!B:B,'R.V.'!A:A) -> Rosmeri Rivera Rodriguez | AQ50: =_xlfn.XLOOKUP(Tabla1[[#This Row],[NIC]],'R.V.'!B:B,'R.V.'!G:G) -> CR 9 6 36 - LA PAZ | AR50: =_xlfn.XLOOKUP(Tabla1[[#This Row],[NIC]],'R.V.'!B:B,'R.V.'!E:E) -> EDUCACION | AS50: =VLOOKUP(Tabla1[[#This Row],[NIC]],'R.V.'!B:D,3,0) -> ESCUELA NUEVA 5 CAMINOS ( VDA LOS ANDES LA PAZ CESAR )
A51: 7586615 | B51: 46111 | C51: SRES MUNICIPIO DE LA | D51: SRES MUNICIPIO DE LA | E51: CENTRO LA PAZ CR 9 6-36 | F51: 7586615 | G51: 7586615186 | H51: 36025104 | I51: 8672880 | J51: 3110 | K51: 70 | L51: 130 | M51: 46088 | N51: CZ1 | O51: Com (Sencilla Niv.1 ) Caribe | P51: 46420 | Q51: 46 | R51: 42192.12 | T51: 63110EN0022586181500100700130008066 | U51: 46121 | V51: LA PAZ | W51: NIVEL I | X51: Propiedad Empresa | Y51: ESTIMADO | Z51: 30 | AA51: SI | AB51: 5 | AC51: VALLEDUPAR | AD51: NO | AE51: NO | AF51: INFO_CONSOL_ESPECIALES | AG51: Regulado Oficial Municipal | AH51: Educación | AI51: 46058 | AJ51: EL PASO 2 | AK51: 83060 | AL51: #N/A | AM51: #N/A | AN51: RECIBIDO | AO51: =_xlfn.XLOOKUP(Tabla1[[#This Row],[NIC]],'R.V.'!B:B,'R.V.'!I:I) -> 0 | AP51: =_xlfn.XLOOKUP(Tabla1[[#This Row],[NIC]],'R.V.'!B:B,'R.V.'!A:A) -> Rosmeri Rivera Rodriguez | AQ51: =_xlfn.XLOOKUP(Tabla1[[#This Row],[NIC]],'R.V.'!B:B,'R.V.'!G:G) -> CR 9 6 36 - LA PAZ | AR51: =_xlfn.XLOOKUP(Tabla1[[#This Row],[NIC]],'R.V.'!B:B,'R.V.'!E:E) -> EDUCACION | AS51: =VLOOKUP(Tabla1[[#This Row],[NIC]],'R.V.'!B:D,3,0) -> ESCUELA GOTA FRIA ABAJO ( VDA GOTA FRIA LA PAZ CESAR )
A52: 7586632 | B52: 46111 | C52: SRES MUNICIPIO DE LA | D52: SRES MUNICIPIO DE LA | E52: CENTRO LA PAZ CR 9 6-36 | F52: 7586632 | G52: 7586632185 | H52: 36025120 | I52: 8672948 | J52: 3110 | K52: 70 | L52: 130 | M52: 46088 | N52: CZ1 | O52: Com (Sencilla Niv.1 ) Caribe | P52: 1010 | Q52: 1 | R52: 917.22 | T52: 63110EN0022586181500100700130008066 | U52: 46121 | V52: LA PAZ | W52: NIVEL I | X52: Propiedad Empresa | Y52: ESTIMADO | Z52: 30 | AA52: SI | AB52: 5 | AC52: VALLEDUPAR | AD52: NO | AE52: NO | AF52: INFO_CONSOL_ESPECIALES | AG52: Regulado Oficial Municipal | AH52: Educación | AI52: 46058 | AJ52: EL PASO 2 | AK52: 1970 | AL52: #N/A | AM52: #N/A | AN52: RECIBIDO | AO52: =_xlfn.XLOOKUP(Tabla1[[#This Row],[NIC]],'R.V.'!B:B,'R.V.'!I:I) -> 0 | AP52: =_xlfn.XLOOKUP(Tabla1[[#This Row],[NIC]],'R.V.'!B:B,'R.V.'!A:A) -> Rosmeri Rivera Rodriguez | AQ52: =_xlfn.XLOOKUP(Tabla1[[#This Row],[NIC]],'R.V.'!B:B,'R.V.'!G:G) -> CR 9 6 36 - LA PAZ | AR52: =_xlfn.XLOOKUP(Tabla1[[#This Row],[NIC]],'R.V.'!B:B,'R.V.'!E:E) -> EDUCACION | AS52: =VLOOKUP(Tabla1[[#This Row],[NIC]],'R.V.'!B:D,3,0) -> ESCUELA NUEVA PIE DE CUESTA ( VDA GOTA FRIA LA PAZ CESAR )
A53: 7968679 | B53: 46111 | C53: SRES MUNICIPIO DE LA | D53: SRES MUNICIPIO DE LA | E53: CENTRO LA PAZ CR 9 6-36 | F53: 7968679 | G53: 7968679090 | H53: 36170721 | I53: 6571291 | J53: 3110 | K53: 60 | L53: 1 | M53: 46082 | N53: CY2 | O53: Com(Mon.dbl.Tip2Niv.2)Caribe | P53: 367530 | Q53: 4400 | R53: 3105273.6 | T53: 63110EN0022586181500100600001003280 | U53: 46121 | V53: LA PAZ | W53: NIVEL II | X53: Propiedad Cliente | Y53: MEDICION | Z53: 28 | AA53: SI | AB53: 5 | AC53: VALLEDUPAR | AD53: NO | AE53: NO | AF53: INFO_CONSOL_ESPECIALES | AG53: Regulado Oficial Municipal | AH53: Educación | AI53: 46054 | AJ53: MANAURE (CESAR) | AK53: -1584372 | AL53: #N/A | AM53: #N/A | AN53: RECIBIDO | AO53: =_xlfn.XLOOKUP(Tabla1[[#This Row],[NIC]],'R.V.'!B:B,'R.V.'!I:I) -> 0 | AP53: =_xlfn.XLOOKUP(Tabla1[[#This Row],[NIC]],'R.V.'!B:B,'R.V.'!A:A) -> Rosmeri Rivera Rodriguez | AQ53: =_xlfn.XLOOKUP(Tabla1[[#This Row],[NIC]],'R.V.'!B:B,'R.V.'!G:G) -> CR 9 6 36 - LA PAZ | AR53: =_xlfn.XLOOKUP(Tabla1[[#This Row],[NIC]],'R.V.'!B:B,'R.V.'!E:E) -> EDUCACION | AS53: =VLOOKUP(Tabla1[[#This Row],[NIC]],'R.V.'!B:D,3,0) -> ESCUELA EDUCATIVA SAN JOSE
A54: 7979318 | B54: 46111 | C54: SRES MUNICIPIO DE LA | D54: SRES MUNICIPIO DE LA | E54: CENTRO LA PAZ CR 9 6-36 | F54: 7979318 | G54: 7979318087 | H54: 36176785 | I54: 7146655 | J54: 3110 | K54: 70 | L54: 130 | M54: 46084 | N54: CZ1 | O54: Com (Sencilla Niv.1 ) Caribe | P54: 0 | Q54: 0 | R54: 0 | T54: 63110EN0022586181500100700130008066 | V54: LA PAZ | W54: NIVEL I | X54: Propiedad Empresa | Y54: MEDICION | Z54: 29 | AA54: SI | AB54: 5 | AC54: VALLEDUPAR | AD54: NO | AE54: NO | AF54: INFO_CONSOL_ESPECIALES | AG54: Regulado Oficial Municipal | AH54: Educación | AI54: 46055 | AJ54: BALCON DEL CESAR 2 | AK54: 20 | AL54: #N/A | AM54: #N/A | AN54: RECIBIDO | AO54: =_xlfn.XLOOKUP(Tabla1[[#This Row],[NIC]],'R.V.'!B:B,'R.V.'!I:I) -> 0 | AP54: =_xlfn.XLOOKUP(Tabla1[[#This Row],[NIC]],'R.V.'!B:B,'R.V.'!A:A) -> Rosmeri Rivera Rodriguez | AQ54: =_xlfn.XLOOKUP(Tabla1[[#This Row],[NIC]],'R.V.'!B:B,'R.V.'!G:G) -> CR 9 6 36 - LA PAZ | AR54: =_xlfn.XLOOKUP(Tabla1[[#This Row],[NIC]],'R.V.'!B:B,'R.V.'!E:E) -> EDUCACION | AS54: =VLOOKUP(Tabla1[[#This Row],[NIC]],'R.V.'!B:D,3,0) -> ESCUELA NUEVA CERRO DEL TESORO
A55: 7979333 | B55: 46111 | C55: SRES MUNICIPIO DE LA | D55: SRES MUNICIPIO DE LA | E55: CENTRO LA PAZ CR 9 6-36 | F55: 7979333 | G55: 7979333086 | H55: 36176764 | I55: 7146663 | J55: 3110 | K55: 70 | L55: 130 | M55: 46084 | N55: CZ1 | O55: Com (Sencilla Niv.1 ) Caribe | P55: 0 | Q55: 0 | R55: 0 | T55: 63110EN0022586181500100700130008066 | V55: LA PAZ | W55: NIVEL I | X55: Propiedad Empresa | Y55: MEDICION | Z55: 29 | AA55: SI | AB55: 5 | AC55: VALLEDUPAR | AD55: NO | AE55: NO | AF55: INFO_CONSOL_ESPECIALES | AG55: Regulado Oficial Municipal | AH55: Educación | AI55: 46055 | AJ55: BALCON DEL CESAR 2 | AK55: 0 | AL55: #N/A | AM55: #N/A | AN55: RECIBIDO | AO55: =_xlfn.XLOOKUP(Tabla1[[#This Row],[NIC]],'R.V.'!B:B,'R.V.'!I:I) -> 0 | AP55: =_xlfn.XLOOKUP(Tabla1[[#This Row],[NIC]],'R.V.'!B:B,'R.V.'!A:A) -> Rosmeri Rivera Rodriguez | AQ55: =_xlfn.XLOOKUP(Tabla1[[#This Row],[NIC]],'R.V.'!B:B,'R.V.'!G:G) -> CR 9 6 36 - LA PAZ | AR55: =_xlfn.XLOOKUP(Tabla1[[#This Row],[NIC]],'R.V.'!B:B,'R.V.'!E:E) -> EDUCACION | AS55: =VLOOKUP(Tabla1[[#This Row],[NIC]],'R.V.'!B:D,3,0) -> ESCUELA NUEVA LA DUDA
A56: 7979367 | B56: 46111 | C56: SRES MUNICIPIO DE LA | D56: SRES MUNICIPIO DE LA | E56: CENTRO LA PAZ CR 9 6-36 | F56: 7979367 | G56: 7979367085 | H56: 36176831 | I56: 7146536 | J56: 3110 | K56: 70 | L56: 130 | M56: 46084 | N56: CZ1 | O56: Com (Sencilla Niv.1 ) Caribe | P56: 250 | Q56: 0 | R56: 0 | T56: 63110EN0022586181500100700130008066 | U56: 46121 | V56: LA PAZ | W56: NIVEL I | X56: Propiedad Empresa | Y56: ESTIMADO | Z56: 29 | AA56: SI | AB56: 5 | AC56: VALLEDUPAR | AD56: NO | AE56: NO | AF56: INFO_CONSOL_ESPECIALES | AG56: Regulado Oficial Municipal | AH56: Educación | AI56: 46055 | AJ56: BALCON DEL CESAR 2 | AK56: 250 | AL56: #N/A | AM56: #N/A | AN56: RECIBIDO | AO56: =_xlfn.XLOOKUP(Tabla1[[#This Row],[NIC]],'R.V.'!B:B,'R.V.'!I:I) -> 0 | AP56: =_xlfn.XLOOKUP(Tabla1[[#This Row],[NIC]],'R.V.'!B:B,'R.V.'!A:A) -> Rosmeri Rivera Rodriguez | AQ56: =_xlfn.XLOOKUP(Tabla1[[#This Row],[NIC]],'R.V.'!B:B,'R.V.'!G:G) -> CR 9 6 36 - LA PAZ | AR56: =_xlfn.XLOOKUP(Tabla1[[#This Row],[NIC]],'R.V.'!B:B,'R.V.'!E:E) -> EDUCACION | AS56: =VLOOKUP(Tabla1[[#This Row],[NIC]],'R.V.'!B:D,3,0) -> COLEGIO NUEVO LAS MESAS
A57: 7979390 | B57: 46111 | C57: SRES MUNICIPIO DE LA | D57: SRES MUNICIPIO DE LA | E57: CENTRO LA PAZ CR 9 6-36 | F57: 7979390 | G57: 7979390084 | H57: 36176842 | I57: 7146555 | J57: 3110 | K57: 70 | L57: 130 | M57: 46084 | N57: CZ1 | O57: Com (Sencilla Niv.1 ) Caribe | P57: 0 | Q57: 0 | R57: 0 | T57: 63110EN0022586181500100700130008066 | V57: LA PAZ | W57: NIVEL I | X57: Propiedad Empresa | Y57: MEDICION | Z57: 29 | AA57: SI | AB57: 5 | AC57: VALLEDUPAR | AD57: NO | AE57: NO | AF57: INFO_CONSOL_ESPECIALES | AG57: Regulado Oficial Municipal | AH57: Educación | AI57: 46055 | AJ57: BALCON DEL CESAR 2 | AK57: 0 | AL57: #N/A | AM57: #N/A | AN57: RECIBIDO | AO57: =_xlfn.XLOOKUP(Tabla1[[#This Row],[NIC]],'R.V.'!B:B,'R.V.'!I:I) -> 0 | AP57: =_xlfn.XLOOKUP(Tabla1[[#This Row],[NIC]],'R.V.'!B:B,'R.V.'!A:A) -> Rosmeri Rivera Rodriguez | AQ57: =_xlfn.XLOOKUP(Tabla1[[#This Row],[NIC]],'R.V.'!B:B,'R.V.'!G:G) -> CR 9 6 36 - LA PAZ | AR57: =_xlfn.XLOOKUP(Tabla1[[#This Row],[NIC]],'R.V.'!B:B,'R.V.'!E:E) -> EDUCACION | AS57: =VLOOKUP(Tabla1[[#This Row],[NIC]],'R.V.'!B:D,3,0) -> ESCUELA NUEVA LA ESPERANZA
A58: 5824755 | B58: 46111 | C58: SRES HOSPI MARINO ZU | D58: SRES HOSPI MARINO ZU | E58: CENTRO LA PAZ CR 6 CL 6-25 | F58: 5824755 | G58: 5824755333 | H58: 25835603 | I58: 5836666 | J58: 3110 | K58: 50 | L58: 2012 | M58: 46105 | N58: OV2 | O58: Ofi(Mon.dbl.Tip2Niv.2)E.Caribe | P58: 20831470 | Q58: 24480 | R58: 17956310 | T58: 63110EN0022068243700100502012000941 | U58: 46121 | V58: LA PAZ | W58: NIVEL II | X58: Propiedad Cliente | Y58: MEDICION | Z58: 32 | AA58: SI | AB58: 6 | AC58: VALLEDUPAR | AD58: NO | AE58: NO | AF58: INFO_CONSOL_ESPECIALES | AG58: Regulado Oficial Municipal | AH58: Actividades de hospitales | AI58: 46073 | AJ58: LA PAZ | AK58: 20831470 | AL58: #N/A | AM58: #N/A | AN58: RECIBIDO | AO58: =_xlfn.XLOOKUP(Tabla1[[#This Row],[NIC]],'R.V.'!B:B,'R.V.'!I:I) -> 0 | AP58: =_xlfn.XLOOKUP(Tabla1[[#This Row],[NIC]],'R.V.'!B:B,'R.V.'!A:A) -> Rosmeri Rivera Rodriguez | AQ58: =_xlfn.XLOOKUP(Tabla1[[#This Row],[NIC]],'R.V.'!B:B,'R.V.'!G:G) -> CR 6 CL 6 25 - LA PAZ | AR58: =_xlfn.XLOOKUP(Tabla1[[#This Row],[NIC]],'R.V.'!B:B,'R.V.'!E:E) -> EDUCACION | AS58: =VLOOKUP(Tabla1[[#This Row],[NIC]],'R.V.'!B:D,3,0) -> 0
A59: 5858057 | B59: 46111 | C59: SRES HOSPI MARINO ZU | D59: SRES HOSPI MARINO ZU | E59: CENTRO LA PAZ CR 6 CL 6-25 | F59: 5858057 | G59: 5858057328 | H59: 25856884 | I59: 5903270 | J59: 3110 | K59: 71 | L59: 20 | M59: 46094 | N59: OW1 | O59: Ofi (Sencilla Niv.1) Caribe | P59: 490040 | Q59: 490 | R59: 432660.2 | T59: 63110EN0022068243700100710020039890 | U59: 46121 | V59: LA PAZ | W59: NIVEL I | X59: Propiedad Cliente | Y59: MEDICION | Z59: 30 | AA59: SI | AB59: 6 | AC59: VALLEDUPAR | AD59: NO | AE59: NO | AF59: INFO_CONSOL_ESPECIALES | AG59: Regulado Oficial Municipal | AH59: Actividades de hospitales | AI59: 46064 | AJ59: BALCON DEL CESAR 2 | AK59: 490040 | AL59: #N/A | AM59: #N/A | AN59: RECIBIDO | AO59: =_xlfn.XLOOKUP(Tabla1[[#This Row],[NIC]],'R.V.'!B:B,'R.V.'!I:I) -> 0 | AP59: =_xlfn.XLOOKUP(Tabla1[[#This Row],[NIC]],'R.V.'!B:B,'R.V.'!A:A) -> Rosmeri Rivera Rodriguez | AQ59: =_xlfn.XLOOKUP(Tabla1[[#This Row],[NIC]],'R.V.'!B:B,'R.V.'!G:G) -> CR 6 CL 6 25 - LA PAZ | AR59: =_xlfn.XLOOKUP(Tabla1[[#This Row],[NIC]],'R.V.'!B:B,'R.V.'!E:E) -> EDUCACION | AS59: =VLOOKUP(Tabla1[[#This Row],[NIC]],'R.V.'!B:D,3,0) -> 0
A60: 5858751 | B60: 46111 | C60: SRES HOSP JOSE ANTON | D60: SRES HOSP JOSE ANTON | E60: CENTRO BALCON DEL CESAR CL 2 5-45 | F60: 5858751 | G60: 5858751331 | H60: 25837510 | I60: 5904658 | J60: 3110 | K60: 71 | L60: 240 | M60: 46105 | N60: OW1 | O60: Ofi (Sencilla Niv.1) Caribe | P60: 5999310 | Q60: 5960 | R60: 5262560.8 | T60: 63110EN0023406885500100710240001063 | U60: 46121 | V60: MANAURE-CESAR | W60: NIVEL I | X60: Propiedad Cliente | Y60: MEDICION | Z60: 32 | AA60: SI | AB60: 7 | AC60: VALLEDUPAR | AD60: NO | AE60: NO | AF60: INFO_CONSOL_ESPECIALES | AG60: Regulado Oficial Municipal | AH60: Actividades de hospitales | AI60: 46073 | AJ60: BALCON DEL CESAR 1 | AK60: 15491170 | AL60: #N/A | AM60: #N/A | AN60: RECIBIDO | AO60: =_xlfn.XLOOKUP(Tabla1[[#This Row],[NIC]],'R.V.'!B:B,'R.V.'!I:I) -> 0 | AP60: =_xlfn.XLOOKUP(Tabla1[[#This Row],[NIC]],'R.V.'!B:B,'R.V.'!A:A) -> Rosmeri Rivera Rodriguez | AQ60: =_xlfn.XLOOKUP(Tabla1[[#This Row],[NIC]],'R.V.'!B:B,'R.V.'!G:G) -> CR 6 2F 12 - MANAURE CESAR | AR60: =_xlfn.XLOOKUP(Tabla1[[#This Row],[NIC]],'R.V.'!B:B,'R.V.'!E:E) -> EDUCACION | AS60: =VLOOKUP(Tabla1[[#This Row],[NIC]],'R.V.'!B:D,3,0) -> 0
A61: 5839319 | B61: 46111 | C61: EMPAZ | D61: EMPAZ | E61: 19 DE MARZO LA PAZ CR 2 3A-10 | F61: 5839319 | G61: 5839319341 | H61: 25834859 | I61: 5865794 | J61: 3110 | K61: 70 | L61: 80 | M61: 46091 | N61: CZ1 | O61: Com (Sencilla Niv.1 ) Caribe | P61: 175420 | Q61: 17 | R61: 18711.22 | T61: 63110EN0023641738700100700080004590 | U61: 46121 | V61: LA PAZ | W61: NIVEL I | X61: Propiedad Empresa | Y61: ESTIMADO | Z61: 31 | AA61: SI | AB61: 8 | AC61: VALLEDUPAR | AD61: NO | AE61: NO | AF61: INFO_CONSOL_ESPECIALES | AG61: Regulado Oficial Municipal | AH61: Actividades administrativ | AI61: 46060 | AJ61: LA PAZ | AK61: 10273410 | AL61: #N/A | AM61: #N/A | AN61: RECIBIDO | AO61: =_xlfn.XLOOKUP(Tabla1[[#This Row],[NIC]],'R.V.'!B:B,'R.V.'!I:I) -> 0 | AP61: =_xlfn.XLOOKUP(Tabla1[[#This Row],[NIC]],'R.V.'!B:B,'R.V.'!A:A) -> Rosmeri Rivera Rodriguez | AQ61: =_xlfn.XLOOKUP(Tabla1[[#This Row],[NIC]],'R.V.'!B:B,'R.V.'!G:G) -> CR 9 6 36 - LA PAZ | AR61: =_xlfn.XLOOKUP(Tabla1[[#This Row],[NIC]],'R.V.'!B:B,'R.V.'!E:E) -> ACUEDUCTO_DESCENTRALIZADO | AS61: =VLOOKUP(Tabla1[[#This Row],[NIC]],'R.V.'!B:D,3,0) -> 0
A62: 5840545 | B62: 46111 | C62: SRES MUNICIPIO DE LA | D62: SRES MUNICIPIO DE LA | E62: JORGE ELIECER GAITAN LA PAZ CR 3 6-64 LOC 01 | F62: 5840545 | G62: 5840545357 | H62: 25835698 | I62: 5868246 | J62: 3110 | K62: 70 | L62: 120 | M62: 46098 | N62: OW1 | O62: Ofi (Sencilla Niv.1) Caribe | P62: 210740 | Q62: 152 | R62: 139417.44 | T62: 63110EN0022586181500700700120010955 | U62: 46121 | V62: LA PAZ | W62: NIVEL I | X62: Propiedad Empresa | Y62: MEDICION | Z62: 31 | AA62: SI | AB62: 9 | AC62: VALLEDUPAR | AD62: NO | AE62: NO | AF62: INFO_CONSOL_ESPECIALES | AG62: Regulado Oficial Municipal | AH62: Administración del Estado | AI62: 46067 | AJ62: MANAURE (CESAR) | AK62: 210740 | AL62: #N/A | AM62: #N/A | AN62: NO RECIBIDO | AO62: =_xlfn.XLOOKUP(Tabla1[[#This Row],[NIC]],'R.V.'!B:B,'R.V.'!I:I) -> Se envía por correo electrónico | AP62: =_xlfn.XLOOKUP(Tabla1[[#This Row],[NIC]],'R.V.'!B:B,'R.V.'!A:A) -> Rosmeri Rivera Rodriguez | AQ62: =_xlfn.XLOOKUP(Tabla1[[#This Row],[NIC]],'R.V.'!B:B,'R.V.'!G:G) -> CL 8A CR 7 5 - LA PAZ | AR62: =_xlfn.XLOOKUP(Tabla1[[#This Row],[NIC]],'R.V.'!B:B,'R.V.'!E:E) -> CONCEJO_DESCENTRALIZADO | AS62: =VLOOKUP(Tabla1[[#This Row],[NIC]],'R.V.'!B:D,3,0) -> 0
A63: 5808643 | B63: 46111 | C63: EMP DE SERV PUBCO DE | D63: EMP DE SERV PUBCO DE | E63: SAN ANTONIO BALCON DEL CESAR CR 1 CL 3-90 | F63: 5808643 | G63: 5808643340 | H63: 25837442 | I63: 5808643 | J63: 3110 | K63: 71 | L63: 240 | M63: 46088 | N63: CH1 | O63: Com Acu (Sencilla N1) E.Caribe | P63: 635190 | Q63: 550 | R63: 554917 | T63: 63110EN0023637200800100710240008323 | U63: 46121 | V63: MANAURE-CESAR | W63: NIVEL I | X63: Propiedad Empresa | Y63: MEDICION | Z63: 30 | AA63: SI | AB63: 10 | AC63: VALLEDUPAR | AD63: NO | AE63: NO | AF63: INFO_CONSOL_ESPECIALES | AG63: Regulado Oficial Municipal | AH63: Captación, tratamiento y | AI63: 46058 | AJ63: BALCON DEL CESAR 1 | AK63: 635190 | AL63: #N/A | AM63: #N/A | AN63: NO RECIBIDO | AO63: =_xlfn.XLOOKUP(Tabla1[[#This Row],[NIC]],'R.V.'!B:B,'R.V.'!I:I) -> Se envía por correo electrónico | AP63: =_xlfn.XLOOKUP(Tabla1[[#This Row],[NIC]],'R.V.'!B:B,'R.V.'!A:A) -> Rosmeri Rivera Rodriguez | AQ63: =_xlfn.XLOOKUP(Tabla1[[#This Row],[NIC]],'R.V.'!B:B,'R.V.'!G:G) -> CR 1 CL 3 90 - MANAURE CESAR | AR63: =_xlfn.XLOOKUP(Tabla1[[#This Row],[NIC]],'R.V.'!B:B,'R.V.'!E:E) -> ACUEDUCTO_DESCENTRALIZADO | AS63: =VLOOKUP(Tabla1[[#This Row],[NIC]],'R.V.'!B:D,3,0) -> 0
A64: 5800118 | B64: 46111 | C64: MUNICIPIO MANAURE BA | D64: MUNICIPIO MANAURE BA | E64: CENTRO BALCON DEL CESAR CR 8 2F-60 | F64: 5800118 | G64: 5800118322 | H64: 25837584 | I64: 5800118 | J64: 3110 | K64: 71 | L64: 250 | M64: 46088 | N64: CZ1 | O64: Com (Sencilla Niv.1 ) Caribe | P64: 18820 | Q64: 15 | R64: 16509.9 | T64: 63110EN0023515273100100710250008138 | U64: 46121 | V64: MANAURE-CESAR | W64: NIVEL I | X64: Propiedad Empresa | Y64: MEDICION | Z64: 30 | AA64: SI | AB64: 11 | AC64: VALLEDUPAR | AD64: NO | AE64: NO | AF64: INFO_CONSOL_ESPECIALES | AG64: Regulado Oficial Municipal | AH64: Educación | AI64: 46058 | AJ64: BALCON DEL CESAR 1 | AK64: 18820 | AL64: #N/A | AM64: #N/A | AN64: RECIBIDO | AO64: =_xlfn.XLOOKUP(Tabla1[[#This Row],[NIC]],'R.V.'!B:B,'R.V.'!I:I) -> 0 | AP64: =_xlfn.XLOOKUP(Tabla1[[#This Row],[NIC]],'R.V.'!B:B,'R.V.'!A:A) -> Rosmeri Rivera Rodriguez | AQ64: =_xlfn.XLOOKUP(Tabla1[[#This Row],[NIC]],'R.V.'!B:B,'R.V.'!G:G) -> CL 3 6A 68 - MANAURE CESAR | AR64: =_xlfn.XLOOKUP(Tabla1[[#This Row],[NIC]],'R.V.'!B:B,'R.V.'!E:E) -> EDUCACION | AS64: =VLOOKUP(Tabla1[[#This Row],[NIC]],'R.V.'!B:D,3,0) -> ESCUELA JUAN XXII
A65: 5800119 | B65: 46111 | C65: MUNICIPIO MANAURE BA | D65: MUNICIPIO MANAURE BA | E65: CENTRO BALCON DEL CESAR CR 8 2F-60 | F65: 5800119 | G65: 5800119324 | H65: 25857696 | I65: 5800119 | J65: 3110 | K65: 71 | L65: 250 | M65: 46087 | N65: CZ1 | O65: Com (Sencilla Niv.1 ) Caribe | P65: 154330 | Q65: 123 | R65: 135381.18 | T65: 63110EN0023515273100100710250008138 | U65: 46121 | V65: MANAURE-CESAR | W65: NIVEL I | X65: Propiedad Empresa | Y65: MEDICION | Z65: 30 | AA65: SI | AB65: 11 | AC65: VALLEDUPAR | AD65: NO | AE65: NO | AF65: INFO_CONSOL_ESPECIALES | AG65: Regulado Oficial Municipal | AH65: Educación | AI65: 46057 | AJ65: BALCON DEL CESAR 2 | AK65: 4913390 | AL65: #N/A | AM65: #N/A | AN65: RECIBIDO | AO65: =_xlfn.XLOOKUP(Tabla1[[#This Row],[NIC]],'R.V.'!B:B,'R.V.'!I:I) -> 0 | AP65: =_xlfn.XLOOKUP(Tabla1[[#This Row],[NIC]],'R.V.'!B:B,'R.V.'!A:A) -> Rosmeri Rivera Rodriguez | AQ65: =_xlfn.XLOOKUP(Tabla1[[#This Row],[NIC]],'R.V.'!B:B,'R.V.'!G:G) -> CL 3 6A 68 - MANAURE CESAR | AR65: =_xlfn.XLOOKUP(Tabla1[[#This Row],[NIC]],'R.V.'!B:B,'R.V.'!E:E) -> EDUCACION | AS65: =VLOOKUP(Tabla1[[#This Row],[NIC]],'R.V.'!B:D,3,0) -> ESCUELA MARIA AUXILIADORA
A66: 5808641 | B66: 46111 | C66: MUNICIPIO MANAURE BA | D66: MUNICIPIO MANAURE BA | E66: CENTRO BALCON DEL CESAR CR 8 2F-60 | F66: 5808641 | G66: 5808641319 | H66: 25837705 | I66: 5808641 | J66: 3110 | K66: 71 | L66: 250 | M66: 46090 | N66: CZ1 | O66: Com (Sencilla Niv.1 ) Caribe | P66: 56460 | Q66: 45 | R66: 49529.7 | T66: 63110EN0023515273100100710250008138 | U66: 46121 | V66: MANAURE-CESAR | W66: NIVEL I | X66: Propiedad Empresa | Y66: ESTIMADO | Z66: 31 | AA66: SI | AB66: 11 | AC66: VALLEDUPAR | AD66: NO | AE66: NO | AF66: INFO_CONSOL_ESPECIALES | AG66: Regulado Oficial Municipal | AH66: Educación | AI66: 46059 | AJ66: BALCON DEL CESAR 2 | AK66: 56460 | AL66: #N/A | AM66: #N/A | AN66: RECIBIDO | AO66: =_xlfn.XLOOKUP(Tabla1[[#This Row],[NIC]],'R.V.'!B:B,'R.V.'!I:I) -> 0 | AP66: =_xlfn.XLOOKUP(Tabla1[[#This Row],[NIC]],'R.V.'!B:B,'R.V.'!A:A) -> Rosmeri Rivera Rodriguez | AQ66: =_xlfn.XLOOKUP(Tabla1[[#This Row],[NIC]],'R.V.'!B:B,'R.V.'!G:G) -> CL 3 6A 68 - MANAURE CESAR | AR66: =_xlfn.XLOOKUP(Tabla1[[#This Row],[NIC]],'R.V.'!B:B,'R.V.'!E:E) -> EDUCACION | AS66: =VLOOKUP(Tabla1[[#This Row],[NIC]],'R.V.'!B:D,3,0) -> ESCUELA NUEVA S DEL L
A67: 5808647 | B67: 46111 | C67: MUNICIPIO MANAURE BA | D67: MUNICIPIO MANAURE BA | E67: CENTRO BALCON DEL CESAR CR 8 2F-60 | F67: 5808647 | G67: 5808647322 | H67: 25837262 | I67: 5808647 | J67: 3110 | K67: 71 | L67: 250 | M67: 46087 | N67: CZ1 | O67: Com (Sencilla Niv.1 ) Caribe | P67: 57710 | Q67: 46 | R67: 50630.36 | T67: 63110EN0023515273100100710250008138 | U67: 46121 | V67: MANAURE-CESAR | W67: NIVEL I | X67: Propiedad Empresa | Y67: MEDICION | Z67: 30 | AA67: SI | AB67: 11 | AC67: VALLEDUPAR | AD67: NO | AE67: NO | AF67: INFO_CONSOL_ESPECIALES | AG67: Regulado Oficial Municipal | AH67: Educación | AI67: 46057 | AJ67: BALCON DEL CESAR 1 | AK67: 57710 | AL67: #N/A | AM67: #N/A | AN67: RECIBIDO | AO67: =_xlfn.XLOOKUP(Tabla1[[#This Row],[NIC]],'R.V.'!B:B,'R.V.'!I:I) -> 0 | AP67: =_xlfn.XLOOKUP(Tabla1[[#This Row],[NIC]],'R.V.'!B:B,'R.V.'!A:A) -> Rosmeri Rivera Rodriguez | AQ67: =_xlfn.XLOOKUP(Tabla1[[#This Row],[NIC]],'R.V.'!B:B,'R.V.'!G:G) -> CL 3 6A 68 - MANAURE CESAR | AR67: =_xlfn.XLOOKUP(Tabla1[[#This Row],[NIC]],'R.V.'!B:B,'R.V.'!E:E) -> EDUCACION | AS67: =VLOOKUP(Tabla1[[#This Row],[NIC]],'R.V.'!B:D,3,0) -> ESCUELA ANEXA
A68: 5808649 | B68: 46111 | C68: MUNICIPIO MANAURE BA | D68: MUNICIPIO MANAURE BA | E68: CENTRO BALCON DEL CESAR CR 8 2F-60 | F68: 5808649 | G68: 5808649320 | H68: 25837204 | I68: 5808649 | J68: 3110 | K68: 50 | L68: 2012 | M68: 46105 | N68: CZ1 | O68: Com (Sencilla Niv.1 ) Caribe | P68: 5532700 | Q68: 4400 | R68: 4842904 | T68: 63110EN0023515273100100502012000861 | U68: 46121 | V68: MANAURE-CESAR | W68: NIVEL I | X68: Propiedad Empresa | Y68: MEDICION | Z68: 32 | AA68: SI | AB68: 11 | AC68: VALLEDUPAR | AD68: NO | AE68: NO | AF68: INFO_CONSOL_ESPECIALES | AG68: Regulado Oficial Municipal | AH68: Educación | AI68: 46073 | AJ68: BALCON DEL CESAR 1 | AK68: 5532700 | AL68: #N/A | AM68: #N/A | AN68: RECIBIDO | AO68: =_xlfn.XLOOKUP(Tabla1[[#This Row],[NIC]],'R.V.'!B:B,'R.V.'!I:I) -> 0 | AP68: =_xlfn.XLOOKUP(Tabla1[[#This Row],[NIC]],'R.V.'!B:B,'R.V.'!A:A) -> Rosmeri Rivera Rodriguez | AQ68: =_xlfn.XLOOKUP(Tabla1[[#This Row],[NIC]],'R.V.'!B:B,'R.V.'!G:G) -> CL 3 6A 68 - MANAURE CESAR | AR68: =_xlfn.XLOOKUP(Tabla1[[#This Row],[NIC]],'R.V.'!B:B,'R.V.'!E:E) -> EDUCACION | AS68: =VLOOKUP(Tabla1[[#This Row],[NIC]],'R.V.'!B:D,3,0) -> NORMAL MARIA INMACULADA
A69: 5808651 | B69: 46111 | C69: MUNICIPIO MANAURE BA | D69: MUNICIPIO MANAURE BA | E69: CENTRO BALCON DEL CESAR CR 8 2F-60 | F69: 5808651 | G69: 5808651328 | H69: 25837703 | I69: 5808651 | J69: 3110 | K69: 50 | L69: 2012 | M69: 46105 | N69: CY2 | O69: Com(Mon.dbl.Tip2Niv.2)Caribe | P69: 2982480 | Q69: 2970 | R69: 2610923.7 | T69: 63110EN0023515273100100502012000541 | U69: 46121 | V69: MANAURE-CESAR | W69: NIVEL II | X69: Propiedad Cliente | Y69: MEDICION | Z69: 32 | AA69: SI | AB69: 11 | AC69: VALLEDUPAR | AD69: NO | AE69: NO | AF69: INFO_CONSOL_ESPECIALES | AG69: Regulado Oficial Municipal | AH69: Educación de la primera i | AI69: 46073 | AJ69: BALCON DEL CESAR 1 | AK69: 2982480 | AL69: #N/A | AM69: #N/A | AN69: RECIBIDO | AO69: =_xlfn.XLOOKUP(Tabla1[[#This Row],[NIC]],'R.V.'!B:B,'R.V.'!I:I) -> 0 | AP69: =_xlfn.XLOOKUP(Tabla1[[#This Row],[NIC]],'R.V.'!B:B,'R.V.'!A:A) -> Rosmeri Rivera Rodriguez | AQ69: =_xlfn.XLOOKUP(Tabla1[[#This Row],[NIC]],'R.V.'!B:B,'R.V.'!G:G) -> CL 3 6A 68 - MANAURE CESAR | AR69: =_xlfn.XLOOKUP(Tabla1[[#This Row],[NIC]],'R.V.'!B:B,'R.V.'!E:E) -> EDUCACION | AS69: =VLOOKUP(Tabla1[[#This Row],[NIC]],'R.V.'!B:D,3,0) -> CONCENTRACION DESARROLLO RURAL
... A71: 6806610 | B71: 46111 | C71: MUNICIPIO MANAURE BA | D71: MUNICIPIO MANAURE BA | E71: CENTRO BALCON DEL CESAR CR 8 2F-60 | F71: 6806610 | G71: 6806610266 | H71: 25837703 | I71: 7167507 | J71: 3110 | K71: 71 | L71: 250 | M71: 46084 | N71: CZ1 | O71: Com (Sencilla Niv.1 ) Caribe | P71: 202530 | Q71: 169 | R71: 177656.18 | T71: 63110EN0023515273100100710250008138 | U71: 46121 | V71: MANAURE-CESAR | W71: NIVEL I | X71: Propiedad Empresa | Y71: MEDICION | Z71: 29 | AA71: SI | AB71: 11 | AC71: VALLEDUPAR | AD71: NO | AE71: NO | AF71: INFO_CONSOL_ESPECIALES | AG71: Regulado Oficial Municipal | AH71: Educación | AI71: 46055 | AJ71: BALCON DEL CESAR 1 | AK71: 202530 | AL71: #N/A | AM71: #N/A | AN71: RECIBIDO | AO71: =_xlfn.XLOOKUP(Tabla1[[#This Row],[NIC]],'R.V.'!B:B,'R.V.'!I:I) -> 0 | AP71: =_xlfn.XLOOKUP(Tabla1[[#This Row],[NIC]],'R.V.'!B:B,'R.V.'!A:A) -> Rosmeri Rivera Rodriguez | AQ71: =_xlfn.XLOOKUP(Tabla1[[#This Row],[NIC]],'R.V.'!B:B,'R.V.'!G:G) -> CL 3 6A 68 - MANAURE CESAR | AR71: =_xlfn.XLOOKUP(Tabla1[[#This Row],[NIC]],'R.V.'!B:B,'R.V.'!E:E) -> EDUCACION | AS71: =VLOOKUP(Tabla1[[#This Row],[NIC]],'R.V.'!B:D,3,0) -> ESCUELA RURAL
A72: 7971775 | B72: 46111 | C72: MUNICIPIO MANAURE BA | D72: MUNICIPIO MANAURE BA | E72: CENTRO BALCON DEL CESAR CR 8 2F-60 | F72: 7971775 | G72: 7971775091 | H72: 36174681 | I72: 4297374 | J72: 3110 | K72: 71 | L72: 250 | M72: 46092 | N72: CZ1 | O72: Com (Sencilla Niv.1 ) Caribe | P72: 0 | Q72: 0 | R72: 0 | T72: 63110EN0023515273100100710250008138 | V72: MANAURE-CESAR | W72: NIVEL I | X72: Propiedad Empresa | Y72: ESTIMADO | Z72: 30 | AA72: SI | AB72: 11 | AC72: VALLEDUPAR | AD72: NO | AE72: NO | AF72: INFO_CONSOL_ESPECIALES | AG72: Regulado Oficial Municipal | AH72: Educación | AI72: 46062 | AJ72: BALCON DEL CESAR 1 | AK72: 0 | AL72: #N/A | AM72: #N/A | AN72: NO RECIBIDO | AO72: =_xlfn.XLOOKUP(Tabla1[[#This Row],[NIC]],'R.V.'!B:B,'R.V.'!I:I) -> 0 | AP72: =_xlfn.XLOOKUP(Tabla1[[#This Row],[NIC]],'R.V.'!B:B,'R.V.'!A:A) -> Rosmeri Rivera Rodriguez | AQ72: =_xlfn.XLOOKUP(Tabla1[[#This Row],[NIC]],'R.V.'!B:B,'R.V.'!G:G) -> CL 3 6A 68 - MANAURE CESAR | AR72: =_xlfn.XLOOKUP(Tabla1[[#This Row],[NIC]],'R.V.'!B:B,'R.V.'!E:E) -> EDUCACION | AS72: =VLOOKUP(Tabla1[[#This Row],[NIC]],'R.V.'!B:D,3,0) -> ESCUELA VEREDA CANADA
A73: 7971974 | B73: 46111 | C73: MUNICIPIO MANAURE BA | D73: MUNICIPIO MANAURE BA | E73: CENTRO BALCON DEL CESAR CR 8 2F-60 | F73: 7971974 | G73: 7971974089 | H73: 36174793 | I73: 4297519 | J73: 3110 | K73: 71 | L73: 250 | M73: 46092 | N73: CZ1 | O73: Com (Sencilla Niv.1 ) Caribe | P73: 94110 | Q73: 75 | R73: 82549.5 | T73: 63110EN0023515273100100710250008138 | U73: 46121 | V73: MANAURE-CESAR | W73: NIVEL I | X73: Propiedad Empresa | Y73: MEDICION | Z73: 30 | AA73: SI | AB73: 11 | AC73: VALLEDUPAR | AD73: NO | AE73: NO | AF73: INFO_CONSOL_ESPECIALES | AG73: Regulado Oficial Municipal | AH73: Educación | AI73: 46062 | AJ73: BALCON DEL CESAR 1 | AK73: 94110 | AL73: #N/A | AM73: #N/A | AN73: RECIBIDO | AO73: =_xlfn.XLOOKUP(Tabla1[[#This Row],[NIC]],'R.V.'!B:B,'R.V.'!I:I) -> 0 | AP73: =_xlfn.XLOOKUP(Tabla1[[#This Row],[NIC]],'R.V.'!B:B,'R.V.'!A:A) -> Rosmeri Rivera Rodriguez | AQ73: =_xlfn.XLOOKUP(Tabla1[[#This Row],[NIC]],'R.V.'!B:B,'R.V.'!G:G) -> CL 3 6A 68 - MANAURE CESAR | AR73: =_xlfn.XLOOKUP(Tabla1[[#This Row],[NIC]],'R.V.'!B:B,'R.V.'!E:E) -> EDUCACION | AS73: =VLOOKUP(Tabla1[[#This Row],[NIC]],'R.V.'!B:D,3,0) -> COLEGIO SAN ANTONIO
A74: 7971724 | B74: 46111 | C74: MUNICIPIO MANAURE BA | D74: MUNICIPIO MANAURE BA | E74: CENTRO BALCON DEL CESAR CR 8 2F-60 | F74: 7971724 | G74: 7971724088 | H74: 36174646 | I74: 4297330 | J74: 3110 | K74: 71 | L74: 250 | M74: 46091 | N74: CZ1 | O74: Com (Sencilla Niv.1 ) Caribe | P74: 95360 | Q74: 76 | R74: 83650.16 | T74: 63110EN0023515273100100710250008138 | U74: 46121 | V74: MANAURE-CESAR | W74: NIVEL I | X74: Propiedad Empresa | Y74: MEDICION | Z74: 31 | AA74: SI | AB74: 11 | AC74: VALLEDUPAR | AD74: NO | AE74: NO | AF74: INFO_CONSOL_ESPECIALES | AG74: Regulado Oficial Municipal | AH74: Educación | AI74: 46060 | AJ74: BALCON DEL CESAR 1 | AK74: 95360 | AL74: #N/A | AM74: #N/A | AN74: RECIBIDO | AO74: =_xlfn.XLOOKUP(Tabla1[[#This Row],[NIC]],'R.V.'!B:B,'R.V.'!I:I) -> 0 | AP74: =_xlfn.XLOOKUP(Tabla1[[#This Row],[NIC]],'R.V.'!B:B,'R.V.'!A:A) -> Rosmeri Rivera Rodriguez | AQ74: =_xlfn.XLOOKUP(Tabla1[[#This Row],[NIC]],'R.V.'!B:B,'R.V.'!G:G) -> CL 3 6A 68 - MANAURE CESAR | AR74: =_xlfn.XLOOKUP(Tabla1[[#This Row],[NIC]],'R.V.'!B:B,'R.V.'!E:E) -> EDUCACION | AS74: =VLOOKUP(Tabla1[[#This Row],[NIC]],'R.V.'!B:D,3,0) -> COLEGIO VEREDA CASA GRANDE
A75: 7972032 | B75: 46111 | C75: MUNICIPIO MANAURE BA | D75: MUNICIPIO MANAURE BA | E75: CENTRO BALCON DEL CESAR CR 8 2F-60 | F75: 7972032 | G75: 7972032086 | H75: 36174740 | I75: 4297610 | J75: 3110 | K75: 71 | L75: 250 | M75: 46091 | N75: CZ1 | O75: Com (Sencilla Niv.1 ) Caribe | P75: 7520 | Q75: 6 | R75: 6603.96 | T75: 63110EN0023515273100100710250008138 | U75: 46121 | V75: MANAURE-CESAR | W75: NIVEL I | X75: Propiedad Empresa | Y75: MEDICION | Z75: 31 | AA75: SI | AB75: 11 | AC75: VALLEDUPAR | AD75: NO | AE75: NO | AF75: INFO_CONSOL_ESPECIALES | AG75: Regulado Oficial Municipal | AH75: Educación | AI75: 46060 | AJ75: BALCON DEL CESAR 1 | AK75: 7520 | AL75: #N/A | AM75: #N/A | AN75: RECIBIDO | AO75: =_xlfn.XLOOKUP(Tabla1[[#This Row],[NIC]],'R.V.'!B:B,'R.V.'!I:I) -> 0 | AP75: =_xlfn.XLOOKUP(Tabla1[[#This Row],[NIC]],'R.V.'!B:B,'R.V.'!A:A) -> Rosmeri Rivera Rodriguez | AQ75: =_xlfn.XLOOKUP(Tabla1[[#This Row],[NIC]],'R.V.'!B:B,'R.V.'!G:G) -> CL 3 6A 68 - MANAURE CESAR | AR75: =_xlfn.XLOOKUP(Tabla1[[#This Row],[NIC]],'R.V.'!B:B,'R.V.'!E:E) -> EDUCACION | AS75: =VLOOKUP(Tabla1[[#This Row],[NIC]],'R.V.'!B:D,3,0) -> ESCUELA EL VENADO
A76: 7972015 | B76: 46111 | C76: MUNICIPIO MANAURE BA | D76: MUNICIPIO MANAURE BA | E76: CENTRO BALCON DEL CESAR CR 8 2F-60 | F76: 7972015 | G76: 7972015089 | H76: 36174727 | I76: 4297565 | J76: 3110 | K76: 71 | L76: 250 | M76: 46092 | N76: CZ1 | O76: Com (Sencilla Niv.1 ) Caribe | P76: 0 | Q76: 0 | R76: 0 | T76: 63110EN0023515273100100710250008138 | V76: MANAURE-CESAR | W76: NIVEL I | X76: Propiedad Empresa | Y76: ESTIMADO | Z76: 30 | AA76: SI | AB76: 11 | AC76: VALLEDUPAR | AD76: NO | AE76: NO | AF76: INFO_CONSOL_ESPECIALES | AG76: Regulado Oficial Municipal | AH76: Educación | AI76: 46062 | AJ76: BALCON DEL CESAR 1 | AK76: 0 | AL76: #N/A | AM76: #N/A | AN76: RECIBIDO | AO76: =_xlfn.XLOOKUP(Tabla1[[#This Row],[NIC]],'R.V.'!B:B,'R.V.'!I:I) -> 0 | AP76: =_xlfn.XLOOKUP(Tabla1[[#This Row],[NIC]],'R.V.'!B:B,'R.V.'!A:A) -> Rosmeri Rivera Rodriguez | AQ76: =_xlfn.XLOOKUP(Tabla1[[#This Row],[NIC]],'R.V.'!B:B,'R.V.'!G:G) -> CL 3 6A 68 - MANAURE CESAR | AR76: =_xlfn.XLOOKUP(Tabla1[[#This Row],[NIC]],'R.V.'!B:B,'R.V.'!E:E) -> EDUCACION | AS76: =VLOOKUP(Tabla1[[#This Row],[NIC]],'R.V.'!B:D,3,0) -> ESCUELA EL CINCO
A77: 5858485 | B77: 46111 | C77: MUNICIPIO MANAURE BA | D77: MUNICIPIO MANAURE BA | E77: LA GUAJIRA BALCON DEL CESAR CL 5 6-5 | F77: 5858485 | G77: 5858485313 | H77: 25857630 | I77: 5904126 | J77: 3110 | K77: 71 | L77: 240 | M77: 46088 | N77: OW1 | O77: Ofi (Sencilla Niv.1) Caribe | P77: 493460 | Q77: 538 | R77: 493464.36 | T77: 63110EN0023515273100200710240005903 | U77: 46121 | V77: MANAURE-CESAR | W77: NIVEL I | X77: Propiedad Empresa | Y77: MEDICION | Z77: 30 | AA77: SI | AB77: 12 | AC77: VALLEDUPAR | AD77: NO | AE77: NO | AF77: INFO_CONSOL_ESPECIALES | AG77: Regulado Oficial Municipal | AH77: Actividades administrativ | AI77: 46058 | AJ77: BALCON DEL CESAR 1 | AK77: 493460 | AL77: #N/A | AM77: #N/A | AN77: RECIBIDO | AO77: =_xlfn.XLOOKUP(Tabla1[[#This Row],[NIC]],'R.V.'!B:B,'R.V.'!I:I) -> 0 | AP77: =_xlfn.XLOOKUP(Tabla1[[#This Row],[NIC]],'R.V.'!B:B,'R.V.'!A:A) -> Rosmeri Rivera Rodriguez | AQ77: =_xlfn.XLOOKUP(Tabla1[[#This Row],[NIC]],'R.V.'!B:B,'R.V.'!G:G) -> CL 3 6A 68 - MANAURE CESAR | AR77: =_xlfn.XLOOKUP(Tabla1[[#This Row],[NIC]],'R.V.'!B:B,'R.V.'!E:E) -> PROPIOS | AS77: =VLOOKUP(Tabla1[[#This Row],[NIC]],'R.V.'!B:D,3,0) -> CASA DE LA CULTURA
A78: 5858798 | B78: 46111 | C78: MUNICIPIO MANAURE BA | D78: MUNICIPIO MANAURE BA | E78: LA GUAJIRA BALCON DEL CESAR CL 5 6-5 | F78: 5858798 | G78: 5858798330 | H78: 25837268 | I78: 5904752 | J78: 3110 | K78: 71 | L78: 240 | M78: 46084 | N78: OW1 | O78: Ofi (Sencilla Niv.1) Caribe | P78: 767980 | Q78: 769 | R78: 673659.38 | T78: 63110EN0023515273100200710240005903 | U78: 46121 | V78: MANAURE-CESAR | W78: NIVEL I | X78: Propiedad Empresa | Y78: MEDICION | Z78: 29 | AA78: SI | AB78: 12 | AC78: VALLEDUPAR | AD78: NO | AE78: NO | AF78: INFO_CONSOL_ESPECIALES | AG78: Regulado Oficial Municipal | AH78: Actividades de asistencia | AI78: 46055 | AJ78: BALCON DEL CESAR 1 | AK78: 4768640 | AL78: #N/A | AM78: #N/A | AN78: RECIBIDO | AO78: =_xlfn.XLOOKUP(Tabla1[[#This Row],[NIC]],'R.V.'!B:B,'R.V.'!I:I) -> 0 | AP78: =_xlfn.XLOOKUP(Tabla1[[#This Row],[NIC]],'R.V.'!B:B,'R.V.'!A:A) -> Rosmeri Rivera Rodriguez | AQ78: =_xlfn.XLOOKUP(Tabla1[[#This Row],[NIC]],'R.V.'!B:B,'R.V.'!G:G) -> CL 3 6A 68 - MANAURE CESAR | AR78: =_xlfn.XLOOKUP(Tabla1[[#This Row],[NIC]],'R.V.'!B:B,'R.V.'!E:E) -> PROPIOS | AS78: =VLOOKUP(Tabla1[[#This Row],[NIC]],'R.V.'!B:D,3,0) -> CENTRO ROSITA DAVILA - CASA DEL ABUELO MANAURE
A79: 6930503 | B79: 46111 | C79: MUNICIPIO MANAURE BA | D79: MUNICIPIO MANAURE BA | E79: LA GUAJIRA BALCON DEL CESAR CL 5 6-5 | F79: 6930503 | G79: 6930503205 | H79: 35018699 | I79: 8072306 | J79: 3110 | K79: 71 | L79: 240 | M79: 46084 | N79: OW1 | O79: Ofi (Sencilla Niv.1) Caribe | P79: 0 | Q79: 0 | R79: 0 | T79: 63110EN0023515273100200710240005903 | V79: MANAURE-CESAR | W79: NIVEL I | X79: Propiedad Empresa | Y79: ESTIMADO | Z79: 29 | AA79: SI | AB79: 12 | AC79: VALLEDUPAR | AD79: NO | AE79: NO | AF79: INFO_CONSOL_ESPECIALES | AG79: Regulado Oficial Municipal | AH79: Comercio al por menor en | AI79: 46055 | AJ79: BALCON DEL CESAR 1 | AK79: 468000 | AL79: #N/A | AM79: #N/A | AN79: RECIBIDO | AO79: =_xlfn.XLOOKUP(Tabla1[[#This Row],[NIC]],'R.V.'!B:B,'R.V.'!I:I) -> 0 | AP79: =_xlfn.XLOOKUP(Tabla1[[#This Row],[NIC]],'R.V.'!B:B,'R.V.'!A:A) -> Rosmeri Rivera Rodriguez | AQ79: =_xlfn.XLOOKUP(Tabla1[[#This Row],[NIC]],'R.V.'!B:B,'R.V.'!G:G) -> CL 3 6A 68 - MANAURE CESAR | AR79: =_xlfn.XLOOKUP(Tabla1[[#This Row],[NIC]],'R.V.'!B:B,'R.V.'!E:E) -> PROPIOS | AS79: =VLOOKUP(Tabla1[[#This Row],[NIC]],'R.V.'!B:D,3,0) -> MERCADO
A80: 6694182 | B80: 46111 | C80: MUNICIPIO MANAURE BA | D80: MUNICIPIO MANAURE BA | E80: LA GUAJIRA BALCON DEL CESAR CL 5 6-5 | F80: 6694182 | G80: 6694182261 | H80: 35043430 | I80: 7037465 | J80: 3110 | K80: 71 | L80: 240 | M80: 46088 | N80: OW1 | O80: Ofi (Sencilla Niv.1) Caribe | P80: 3152570 | Q80: 3015 | R80: 2765418.3 | T80: 63110EN0023515273100200710240005903 | U80: 46121 | V80: MANAURE-CESAR | W80: NIVEL I | X80: Propiedad Empresa | Y80: MEDICION | Z80: 30 | AA80: SI | AB80: 12 | AC80: VALLEDUPAR | AD80: NO | AE80: NO | AF80: INFO_CONSOL_ESPECIALES | AG80: Regulado Oficial Municipal | AH80: Actividades ejecutivas de | AI80: 46058 | AJ80: BALCON DEL CESAR 1 | AK80: 3152570 | AL80: #N/A | AM80: #N/A | AN80: RECIBIDO | AO80: =_xlfn.XLOOKUP(Tabla1[[#This Row],[NIC]],'R.V.'!B:B,'R.V.'!I:I) -> 0 | AP80: =_xlfn.XLOOKUP(Tabla1[[#This Row],[NIC]],'R.V.'!B:B,'R.V.'!A:A) -> Rosmeri Rivera Rodriguez | AQ80: =_xlfn.XLOOKUP(Tabla1[[#This Row],[NIC]],'R.V.'!B:B,'R.V.'!G:G) -> CL 3 6A 68 - MANAURE CESAR | AR80: =_xlfn.XLOOKUP(Tabla1[[#This Row],[NIC]],'R.V.'!B:B,'R.V.'!E:E) -> PROPIOS | AS80: =VLOOKUP(Tabla1[[#This Row],[NIC]],'R.V.'!B:D,3,0) -> PALACIO Y/O ALCALDIA MUNICIPAL DE MANAURE - SEDE ALCALDIA
A81: 6930504 | B81: 46111 | C81: MUNICIPIO MANAURE BA | D81: MUNICIPIO MANAURE BA | E81: LA GUAJIRA BALCON DEL CESAR CL 5 6-5 | F81: 6930504 | G81: 6930504222 | H81: 35018699 | I81: 8072311 | J81: 3110 | K81: 71 | L81: 240 | M81: 46084 | N81: OW1 | O81: Ofi (Sencilla Niv.1) Caribe | P81: 233630 | Q81: 226 | R81: 197980.52 | T81: 63110EN0023515273100200710240005903 | U81: 46121 | V81: MANAURE-CESAR | W81: NIVEL I | X81: Propiedad Empresa | Y81: MEDICION | Z81: 29 | AA81: SI | AB81: 12 | AC81: VALLEDUPAR | AD81: NO | AE81: NO | AF81: INFO_CONSOL_ESPECIALES | AG81: Regulado Oficial Municipal | AH81: Actividades administrativ | AI81: 46055 | AJ81: BALCON DEL CESAR 1 | AK81: 233630 | AL81: #N/A | AM81: #N/A | AN81: RECIBIDO | AO81: =_xlfn.XLOOKUP(Tabla1[[#This Row],[NIC]],'R.V.'!B:B,'R.V.'!I:I) -> 0 | AP81: =_xlfn.XLOOKUP(Tabla1[[#This Row],[NIC]],'R.V.'!B:B,'R.V.'!A:A) -> Rosmeri Rivera Rodriguez | AQ81: =_xlfn.XLOOKUP(Tabla1[[#This Row],[NIC]],'R.V.'!B:B,'R.V.'!G:G) -> CL 3 6A 68 - MANAURE CESAR | AR81: =_xlfn.XLOOKUP(Tabla1[[#This Row],[NIC]],'R.V.'!B:B,'R.V.'!E:E) -> PROPIOS | AS81: =VLOOKUP(Tabla1[[#This Row],[NIC]],'R.V.'!B:D,3,0) -> ALCALDIA MUNICIPAL
A82: 7600579 | B82: 46111 | C82: MUNICIPIO MANAURE BA | D82: MUNICIPIO MANAURE BA | E82: LA GUAJIRA BALCON DEL CESAR CL 5 6-5 | F82: 7600579 | G82: 7600579189 | H82: 25857630 | I82: 8763249 | J82: 3110 | K82: 71 | L82: 240 | M82: 46088 | N82: OW1 | O82: Ofi (Sencilla Niv.1) Caribe | P82: 234220 | Q82: 224 | R82: 205457.28 | T82: 63110EN0023515273100200710240005903 | U82: 46121 | V82: MANAURE-CESAR | W82: NIVEL I | X82: Propiedad Empresa | Y82: MEDICION | Z82: 30 | AA82: SI | AB82: 12 | AC82: VALLEDUPAR | AD82: NO | AE82: NO | AF82: INFO_CONSOL_ESPECIALES | AG82: Regulado Oficial Municipal | AH82: Actividades administrativ | AI82: 46058 | AJ82: BALCON DEL CESAR 1 | AK82: 234220 | AL82: #N/A | AM82: #N/A | AN82: RECIBIDO | AO82: =_xlfn.XLOOKUP(Tabla1[[#This Row],[NIC]],'R.V.'!B:B,'R.V.'!I:I) -> 0 | AP82: =_xlfn.XLOOKUP(Tabla1[[#This Row],[NIC]],'R.V.'!B:B,'R.V.'!A:A) -> Rosmeri Rivera Rodriguez | AQ82: =_xlfn.XLOOKUP(Tabla1[[#This Row],[NIC]],'R.V.'!B:B,'R.V.'!G:G) -> CL 3 6A 68 - MANAURE CESAR | AR82: =_xlfn.XLOOKUP(Tabla1[[#This Row],[NIC]],'R.V.'!B:B,'R.V.'!E:E) -> PROPIOS | AS82: =VLOOKUP(Tabla1[[#This Row],[NIC]],'R.V.'!B:D,3,0) -> CASA DE LA CULTURA
A83: 7691630 | B83: 46111 | C83: MUNICIPIO MANAURE BA | D83: MUNICIPIO MANAURE BA | E83: LA GUAJIRA BALCON DEL CESAR CL 5 6-5 | F83: 7691630 | G83: 7691630171 | H83: 36074500 | I83: 3445776 | J83: 3110 | K83: 71 | L83: 240 | M83: 46088 | N83: OW1 | O83: Ofi (Sencilla Niv.1) Caribe | P83: 248740 | Q83: 223 | R83: 204540.06 | T83: 63110EN0023515273100200710240005903 | U83: 46121 | V83: MANAURE-CESAR | W83: NIVEL I | X83: Propiedad Empresa | Y83: MEDICION | Z83: 30 | AA83: SI | AB83: 12 | AC83: VALLEDUPAR | AD83: NO | AE83: NO | AF83: INFO_CONSOL_ESPECIALES | AG83: Regulado Oficial Municipal | AH83: Actividades de biblioteca | AI83: 46058 | AJ83: BALCON DEL CESAR 1 | AK83: 248740 | AL83: #N/A | AM83: #N/A | AN83: RECIBIDO | AO83: =_xlfn.XLOOKUP(Tabla1[[#This Row],[NIC]],'R.V.'!B:B,'R.V.'!I:I) -> 0 | AP83: =_xlfn.XLOOKUP(Tabla1[[#This Row],[NIC]],'R.V.'!B:B,'R.V.'!A:A) -> Rosmeri Rivera Rodriguez | AQ83: =_xlfn.XLOOKUP(Tabla1[[#This Row],[NIC]],'R.V.'!B:B,'R.V.'!G:G) -> CL 3 6A 68 - MANAURE CESAR | AR83: =_xlfn.XLOOKUP(Tabla1[[#This Row],[NIC]],'R.V.'!B:B,'R.V.'!E:E) -> PROPIOS | AS83: =VLOOKUP(Tabla1[[#This Row],[NIC]],'R.V.'!B:D,3,0) -> BIBLIOTECA MUNICIPAL
A84: 7774563 | B84: 46111 | C84: MUNICIPIO MANAURE BA | D84: MUNICIPIO MANAURE BA | E84: LA GUAJIRA BALCON DEL CESAR CL 5 6-5 | F84: 7774563 | G84: 7774563147 | H84: 36108338 | I84: 1918642 | J84: 3110 | K84: 50 | L84: 2012 | M84: 46105 | N84: OX1 | O84: Ofi(Sencilla Niv.1) Carib | P84: 1776100 | Q84: 1760 | R84: 1554044.8 | T84: 63110EN0023515273100200502012000041 | U84: 46121 | V84: MANAURE-CESAR | W84: NIVEL I | X84: Propiedad Cliente | Y84: MEDICION | Z84: 32 | AA84: SI | AB84: 12 | AC84: VALLEDUPAR | AD84: NO | AE84: NO | AF84: INFO_CONSOL_ESPECIALES | AG84: Regulado Oficial Municipal | AH84: Suministro espacio púbico | AI84: 46073 | AJ84: BALCON DEL CESAR 1 | AK84: 1776100 | AL84: #N/A | AM84: #N/A | AN84: RECIBIDO | AO84: =_xlfn.XLOOKUP(Tabla1[[#This Row],[NIC]],'R.V.'!B:B,'R.V.'!I:I) -> 0 | AP84: =_xlfn.XLOOKUP(Tabla1[[#This Row],[NIC]],'R.V.'!B:B,'R.V.'!A:A) -> Rosmeri Rivera Rodriguez | AQ84: =_xlfn.XLOOKUP(Tabla1[[#This Row],[NIC]],'R.V.'!B:B,'R.V.'!G:G) -> CL 3 6A 68 - MANAURE CESAR | AR84: =_xlfn.XLOOKUP(Tabla1[[#This Row],[NIC]],'R.V.'!B:B,'R.V.'!E:E) -> PROPIOS | AS84: =VLOOKUP(Tabla1[[#This Row],[NIC]],'R.V.'!B:D,3,0) -> BIOPARQUE MANAURE
A85: 7715131 | B85: 46111 | C85: MUNICIPIO MANAURE BA | D85: MUNICIPIO MANAURE BA | E85: LA GUAJIRA BALCON DEL CESAR CL 5 6-5 | F85: 7715131 | G85: 7715131163 | H85: 36082354 | I85: 3509184 | J85: 3110 | K85: 50 | L85: 2012 | M85: 46105 | N85: OW1 | O85: Ofi (Sencilla Niv.1) Caribe | P85: 3229050 | Q85: 3200 | R85: 2825536 | T85: 63110EN0023515273100200502012000701 | U85: 46121 | V85: MANAURE-CESAR | W85: NIVEL I | X85: Propiedad Cliente | Y85: MEDICION | Z85: 32 | AA85: SI | AB85: 12 | AC85: VALLEDUPAR | AD85: NO | AE85: NO | AF85: INFO_CONSOL_ESPECIALES | AG85: Regulado Oficial Municipal | AH85: Alumbrado Público | AI85: 46073 | AJ85: BALCON DEL CESAR 1 | AK85: 3229050 | AL85: #N/A | AM85: #N/A | AN85: RECIBIDO | AO85: =_xlfn.XLOOKUP(Tabla1[[#This Row],[NIC]],'R.V.'!B:B,'R.V.'!I:I) -> 0 | AP85: =_xlfn.XLOOKUP(Tabla1[[#This Row],[NIC]],'R.V.'!B:B,'R.V.'!A:A) -> Rosmeri Rivera Rodriguez | AQ85: =_xlfn.XLOOKUP(Tabla1[[#This Row],[NIC]],'R.V.'!B:B,'R.V.'!G:G) -> CL 3 6A 68 - MANAURE CESAR | AR85: =_xlfn.XLOOKUP(Tabla1[[#This Row],[NIC]],'R.V.'!B:B,'R.V.'!E:E) -> PROPIOS | AS85: =VLOOKUP(Tabla1[[#This Row],[NIC]],'R.V.'!B:D,3,0) -> PLAZA CIVICA (TARIMA)
A86: 5309640 | B86: 46111 | C86: PROPIEDAD HORIZONTAL | D86: PROPIEDAD HORIZONTAL | E86: EL CARMEN VALLEDUPAR CR 7 18A-34 | F86: 5309640 | G86: 5309640328 | H86: 25313398 | I86: 5319254 | J86: 3110 | K86: 7 | L86: 1512 | M86: 46088 | N86: CZ1 | O86: Com (Sencilla Niv.1 ) Caribe | P86: 8289980 | Q86: 6853 | R86: 7261301.7 | T86: 63110EN0023634000900100071512000890 | U86: 46121 | V86: VALLEDUPAR | W86: NIVEL I | X86: Propiedad Cliente | Y86: MEDICION | Z86: 30 | AA86: SI | AB86: 13 | AC86: VALLEDUPAR | AD86: NO | AE86: NO | AF86: INFO_CONSOL_ESPECIALES | AG86: Comercial Liberalizado | AH86: Actividades de otras asoc | AI86: 46058 | AJ86: VALLEDUPAR 3 | AK86: 8289980 | AL86: #N/A | AM86: #N/A | AN86: NO RECIBIDO | AO86: =_xlfn.XLOOKUP(Tabla1[[#This Row],[NIC]],'R.V.'!B:B,'R.V.'!I:I) -> Se envía por correo electrónico | AP86: =_xlfn.XLOOKUP(Tabla1[[#This Row],[NIC]],'R.V.'!B:B,'R.V.'!A:A) -> Rosmeri Rivera Rodriguez | AQ86: =_xlfn.XLOOKUP(Tabla1[[#This Row],[NIC]],'R.V.'!B:B,'R.V.'!G:G) -> CR 7 18A 40 ADMINISTRACION - VALLEDUPAR | AR86: =_xlfn.XLOOKUP(Tabla1[[#This Row],[NIC]],'R.V.'!B:B,'R.V.'!E:E) -> PRIVADO | AS86: =VLOOKUP(Tabla1[[#This Row],[NIC]],'R.V.'!B:D,3,0)
A87: 5309641 | B87: 46111 | C87: PROPIEDAD HORIZONTAL | D87: PROPIEDAD HORIZONTAL | E87: EL CARMEN VALLEDUPAR CR 7 18A-34 | F87: 5309641 | G87: 5309641328 | H87: 25313398 | I87: 5319256 | J87: 3110 | K87: 7 | L87: 1512 | M87: 46100 | N87: CZ1 | O87: Com (Sencilla Niv.1 ) Caribe | P87: 4291970 | Q87: 3548 | R87: 3759389.8 | T87: 63110EN0023634000900100071512000890 | U87: 46121 | V87: VALLEDUPAR | W87: NIVEL I | X87: Propiedad Cliente | Y87: ESTIMADO | Z87: 30 | AA87: SI | AB87: 13 | AC87: VALLEDUPAR | AD87: NO | AE87: NO | AF87: INFO_CONSOL_ESPECIALES | AG87: Comercial Liberalizado | AH87: Almacenamiento y depósito | AI87: 46070 | AJ87: VALLEDUPAR 3 | AK87: 4291970 | AL87: #N/A | AM87: #N/A | AN87: NO RECIBIDO | AO87: =_xlfn.XLOOKUP(Tabla1[[#This Row],[NIC]],'R.V.'!B:B,'R.V.'!I:I) -> Se envía por correo electrónico | AP87: =_xlfn.XLOOKUP(Tabla1[[#This Row],[NIC]],'R.V.'!B:B,'R.V.'!A:A) -> Rosmeri Rivera Rodriguez | AQ87: =_xlfn.XLOOKUP(Tabla1[[#This Row],[NIC]],'R.V.'!B:B,'R.V.'!G:G) -> CR 7 18A 40 ADMINISTRACION - VALLEDUPAR | AR87: =_xlfn.XLOOKUP(Tabla1[[#This Row],[NIC]],'R.V.'!B:B,'R.V.'!E:E) -> PRIVADO | AS87: =VLOOKUP(Tabla1[[#This Row],[NIC]],'R.V.'!B:D,3,0)
A88: 5332064 | B88: 46111 | C88: PROPIEDAD HORIZONTAL | D88: PROPIEDAD HORIZONTAL | E88: EL CARMEN VALLEDUPAR CR 7 18A-34 | F88: 5332064 | G88: 5332064330 | H88: 25313420 | I88: 5364102 | J88: 3110 | K88: 7 | L88: 1512 | M88: 46088 | N88: CZ1 | O88: Com (Sencilla Niv.1 ) Caribe | P88: 384670 | Q88: 318 | R88: 336946.44 | T88: 63110EN0023634000900100071512000890 | U88: 46121 | V88: VALLEDUPAR | W88: NIVEL I | X88: Propiedad Cliente | Y88: MEDICION | Z88: 30 | AA88: SI | AB88: 13 | AC88: VALLEDUPAR | AD88: NO | AE88: NO | AF88: INFO_CONSOL_ESPECIALES | AG88: Comercial Liberalizado | AH88: Actividades de otras asoc | AI88: 46058 | AJ88: VALLEDUPAR 3 | AK88: 384670 | AL88: #N/A | AM88: #N/A | AN88: NO RECIBIDO | AO88: =_xlfn.XLOOKUP(Tabla1[[#This Row],[NIC]],'R.V.'!B:B,'R.V.'!I:I) -> Se envía por correo electrónico | AP88: =_xlfn.XLOOKUP(Tabla1[[#This Row],[NIC]],'R.V.'!B:B,'R.V.'!A:A) -> Rosmeri Rivera Rodriguez | AQ88: =_xlfn.XLOOKUP(Tabla1[[#This Row],[NIC]],'R.V.'!B:B,'R.V.'!G:G) -> CR 7 18A 40 ADMINISTRACION - VALLEDUPAR | AR88: =_xlfn.XLOOKUP(Tabla1[[#This Row],[NIC]],'R.V.'!B:B,'R.V.'!E:E) -> PRIVADO | AS88: =VLOOKUP(Tabla1[[#This Row],[NIC]],'R.V.'!B:D,3,0)
A89: 5332065 | B89: 46111 | C89: PROPIEDAD HORIZONTAL | D89: PROPIEDAD HORIZONTAL | E89: EL CARMEN VALLEDUPAR CR 7 18A-34 | F89: 5332065 | G89: 5332065333 | H89: 25313420 | I89: 5364104 | J89: 3110 | K89: 7 | L89: 1512 | M89: 46088 | N89: CZ1 | O89: Com (Sencilla Niv.1 ) Caribe | P89: 2818570 | Q89: 2330 | R89: 2468821.4 | T89: 63110EN0023634000900100071512000890 | U89: 46121 | V89: VALLEDUPAR | W89: NIVEL I | X89: Propiedad Cliente | Y89: MEDICION | Z89: 30 | AA89: SI | AB89: 13 | AC89: VALLEDUPAR | AD89: NO | AE89: NO | AF89: INFO_CONSOL_ESPECIALES | AG89: Comercial Liberalizado | AH89: Actividades de otras asoc | AI89: 46058 | AJ89: VALLEDUPAR 3 | AK89: 2818570 | AL89: #N/A | AM89: #N/A | AN89: NO RECIBIDO | AO89: =_xlfn.XLOOKUP(Tabla1[[#This Row],[NIC]],'R.V.'!B:B,'R.V.'!I:I) -> Se envía por correo electrónico | AP89: =_xlfn.XLOOKUP(Tabla1[[#This Row],[NIC]],'R.V.'!B:B,'R.V.'!A:A) -> Rosmeri Rivera Rodriguez | AQ89: =_xlfn.XLOOKUP(Tabla1[[#This Row],[NIC]],'R.V.'!B:B,'R.V.'!G:G) -> CR 7 18A 40 ADMINISTRACION - VALLEDUPAR | AR89: =_xlfn.XLOOKUP(Tabla1[[#This Row],[NIC]],'R.V.'!B:B,'R.V.'!E:E) -> PRIVADO | AS89: =VLOOKUP(Tabla1[[#This Row],[NIC]],'R.V.'!B:D,3,0)
A90: 5333181 | B90: 46111 | C90: PROPIEDAD HORIZONTAL | D90: PROPIEDAD HORIZONTAL | E90: EL CARMEN VALLEDUPAR CR 7 18A-34 | F90: 5333181 | G90: 5333181333 | H90: 25313398 | I90: 5366336 | J90: 3110 | K90: 7 | L90: 1512 | M90: 46088 | N90: CZ1 | O90: Com (Sencilla Niv.1 ) Caribe | P90: 2006880 | Q90: 1659 | R90: 1757843.2 | T90: 63110EN0023634000900100071512000890 | U90: 46121 | V90: VALLEDUPAR | W90: NIVEL I | X90: Propiedad Cliente | Y90: MEDICION | Z90: 30 | AA90: SI | AB90: 13 | AC90: VALLEDUPAR | AD90: NO | AE90: NO | AF90: INFO_CONSOL_ESPECIALES | AG90: Comercial Liberalizado | AH90: Actividades de otras asoc | AI90: 46058 | AJ90: VALLEDUPAR 3 | AK90: 2006880 | AL90: #N/A | AM90: #N/A | AN90: NO RECIBIDO | AO90: =_xlfn.XLOOKUP(Tabla1[[#This Row],[NIC]],'R.V.'!B:B,'R.V.'!I:I) -> Se envía por correo electrónico | AP90: =_xlfn.XLOOKUP(Tabla1[[#This Row],[NIC]],'R.V.'!B:B,'R.V.'!A:A) -> Rosmeri Rivera Rodriguez | AQ90: =_xlfn.XLOOKUP(Tabla1[[#This Row],[NIC]],'R.V.'!B:B,'R.V.'!G:G) -> CR 7 18A 40 ADMINISTRACION - VALLEDUPAR | AR90: =_xlfn.XLOOKUP(Tabla1[[#This Row],[NIC]],'R.V.'!B:B,'R.V.'!E:E) -> PRIVADO | AS90: =VLOOKUP(Tabla1[[#This Row],[NIC]],'R.V.'!B:D,3,0)
A91: 5338094 | B91: 46111 | C91: PROPIEDAD HORIZONTAL | D91: PROPIEDAD HORIZONTAL | E91: EL CARMEN VALLEDUPAR CR 7 18A-34 | F91: 5338094 | G91: 5338094331 | H91: 25313398 | I91: 5376162 | J91: 3110 | K91: 7 | L91: 1512 | M91: 46100 | N91: CZ1 | O91: Com (Sencilla Niv.1 ) Caribe | P91: 10894970 | Q91: 9000 | R91: 9536220 | T91: 63110EN0023634000900100071512000890 | U91: 46121 | V91: VALLEDUPAR | W91: NIVEL I | X91: Propiedad Cliente | Y91: MEDICION | Z91: 30 | AA91: SI | AB91: 13 | AC91: VALLEDUPAR | AD91: NO | AE91: NO | AF91: INFO_CONSOL_ESPECIALES | AG91: Comercial Liberalizado | AH91: Actividades de otras asoc | AI91: 46070 | AJ91: VALLEDUPAR 3 | AK91: 10894970 | AL91: #N/A | AM91: #N/A | AN91: RECIBIDO | AO91: =_xlfn.XLOOKUP(Tabla1[[#This Row],[NIC]],'R.V.'!B:B,'R.V.'!I:I) -> 0 | AP91: =_xlfn.XLOOKUP(Tabla1[[#This Row],[NIC]],'R.V.'!B:B,'R.V.'!A:A) -> Rosmeri Rivera Rodriguez | AQ91: =_xlfn.XLOOKUP(Tabla1[[#This Row],[NIC]],'R.V.'!B:B,'R.V.'!G:G) -> CR 7 18A 40 ADMINISTRACION - VALLEDUPAR | AR91: =_xlfn.XLOOKUP(Tabla1[[#This Row],[NIC]],'R.V.'!B:B,'R.V.'!E:E) -> PRIVADO | AS91: =VLOOKUP(Tabla1[[#This Row],[NIC]],'R.V.'!B:D,3,0)
... A99: 5335013 | B99: 46111 | C99: RADIO GUATAPURI | D99: RADIO GUATAPURI | E99: LA GRANJA VALLEDUPAR CL 17 15-67 | F99: 5335013 | G99: 5335013323 | H99: 25317959 | I99: 5370000 | J99: 3110 | K99: 37 | L99: 1719 | M99: 46088 | N99: CZ1 | O99: Com (Sencilla Niv.1 ) Caribe | P99: 4136520 | Q99: 3205 | R99: 3527615.3 | T99: 63110EN0022532888500200371719001730 | U99: 46121 | V99: VALLEDUPAR | W99: NIVEL I | X99: Propiedad Empresa | Y99: MEDICION | Z99: 30 | AA99: SI | AB99: 17 | AC99: VALLEDUPAR | AD99: NO | AE99: NO | AF99: INFO_CONSOL_ESPECIALES | AG99: Comercial Liberalizado | AH99: Actividades de programaci | AI99: 46058 | AJ99: VALLEDUPAR 3 | AK99: 4136520 | AL99: #N/A | AM99: #N/A | AN99: NO RECIBIDO | AO99: =_xlfn.XLOOKUP(Tabla1[[#This Row],[NIC]],'R.V.'!B:B,'R.V.'!I:I) -> Se envía por correo electrónico | AP99: =_xlfn.XLOOKUP(Tabla1[[#This Row],[NIC]],'R.V.'!B:B,'R.V.'!A:A) -> Rosmeri Rivera Rodriguez | AQ99: =_xlfn.XLOOKUP(Tabla1[[#This Row],[NIC]],'R.V.'!B:B,'R.V.'!G:G) -> CL 17 15 67 | AR99: =_xlfn.XLOOKUP(Tabla1[[#This Row],[NIC]],'R.V.'!B:B,'R.V.'!E:E) -> PRIVADO | AS99: =VLOOKUP(Tabla1[[#This Row],[NIC]],'R.V.'!B:D,3,0)
A100: 5828015 | B100: 46111 | C100: FUNDACION MEDICO PRE | D100: FUNDACION MEDICO PRE | E100: LOPERENA VALLEDUPAR CL 16B 9-83 P 2 APTO 02 | F100: 5828015 | G100: 5828015325 | H100: 25810250 | I100: 5843186 | J100: 3110 | K100: 1 | L100: 101 | M100: 46091 | N100: CZ1 | O100: Com (Sencilla Niv.1 ) Caribe | P100: 0 | Q100: 0 | R100: 0 | T100: 63110EN0022535930200200010101002550 | V100: VALLEDUPAR | W100: NIVEL I | X100: Propiedad Empresa | Y100: ESTIMADO | Z100: 31 | AA100: SI | AB100: 18 | AC100: VALLEDUPAR | AD100: NO | AE100: NO | AF100: INFO_CONSOL_ESPECIALES | AG100: Comercial Liberalizado | AH100: Actividades de hospitales | AI100: 46060 | AJ100: CODAZZI 3 | AK100: 0 | AL100: #N/A | AM100: #N/A | AN100: RECIBIDO | AO100: =_xlfn.XLOOKUP(Tabla1[[#This Row],[NIC]],'R.V.'!B:B,'R.V.'!I:I) -> 0 | AP100: =_xlfn.XLOOKUP(Tabla1[[#This Row],[NIC]],'R.V.'!B:B,'R.V.'!A:A) -> Rosmeri Rivera Rodriguez | AQ100: =_xlfn.XLOOKUP(Tabla1[[#This Row],[NIC]],'R.V.'!B:B,'R.V.'!G:G) -> CL 16 17 261 OFI 3 - VALLEDUPAR | AR100: =_xlfn.XLOOKUP(Tabla1[[#This Row],[NIC]],'R.V.'!B:B,'R.V.'!E:E) -> PRIVADO | AS100: =VLOOKUP(Tabla1[[#This Row],[NIC]],'R.V.'!B:D,3,0)
A101: 6557139 | B101: 46111 | C101: FUNDACION MEDICO PRE | D101: FUNDACION MEDICO PRE | E101: LOPERENA VALLEDUPAR CL 16B 9-83 P 2 APTO 02 | F101: 6557139 | G101: 6557139284 | H101: 34535878 | I101: 6658317 | J101: 3110 | K101: 1 | L101: 101 | M101: 46091 | N101: CA1 | O101: Com (Sencilla Niv.1 ) Carib | P101: 96730 | Q101: 22 | R101: 24214.52 | T101: 63110EN0022535930200200010101002550 | U101: 46121 | V101: VALLEDUPAR | W101: NIVEL I | X101: Propiedad Empresa | Y101: MEDICION | Z101: 31 | AA101: SI | AB101: 18 | AC101: VALLEDUPAR | AD101: NO | AE101: NO | AF101: INFO_CONSOL_ESPECIALES | AG101: Comercial Liberalizado | AH101: Actividades de hospitales | AI101: 46060 | AJ101: GUATAPURI 3 | AK101: 96730 | AL101: #N/A | AM101: #N/A | AN101: RECIBIDO | AO101: =_xlfn.XLOOKUP(Tabla1[[#This Row],[NIC]],'R.V.'!B:B,'R.V.'!I:I) -> 0 | AP101: =_xlfn.XLOOKUP(Tabla1[[#This Row],[NIC]],'R.V.'!B:B,'R.V.'!A:A) -> Rosmeri Rivera Rodriguez | AQ101: =_xlfn.XLOOKUP(Tabla1[[#This Row],[NIC]],'R.V.'!B:B,'R.V.'!G:G) -> CL 16 17 261 OFI 3 - VALLEDUPAR | AR101: =_xlfn.XLOOKUP(Tabla1[[#This Row],[NIC]],'R.V.'!B:B,'R.V.'!E:E) -> PRIVADO | AS101: =VLOOKUP(Tabla1[[#This Row],[NIC]],'R.V.'!B:D,3,0)
A102: 6591602 | B102: 46111 | C102: BANCO POPULAR SA | D102: BANCO POPULAR SA | E102: CENTRO VALLEDUPAR CL 16 8-20 | F102: 6591602 | G102: 6591602274 | H102: 34000160 | I102: 6803313 | J102: 3110 | K102: 50 | L102: 2008 | M102: 46084 | N102: CZ1 | O102: Com (Sencilla Niv.1 ) Caribe | P102: 528070 | Q102: 440 | R102: 462536.8 | T102: 63110EN0022532047200200502008001980 | U102: 46121 | V102: VALLEDUPAR | W102: NIVEL I | X102: Propiedad Empresa | Y102: MEDICION | Z102: 29 | AA102: SI | AB102: 19 | AC102: VALLEDUPAR | AD102: NO | AE102: NO | AF102: INFO_CONSOL_ESPECIALES | AG102: Comercial Liberalizado | AH102: Bancos comerciales. | AI102: 46055 | AJ102: SALGUERO 1 | AK102: 528070 | AL102: #N/A | AM102: #N/A | AN102: RECIBIDO | AO102: =_xlfn.XLOOKUP(Tabla1[[#This Row],[NIC]],'R.V.'!B:B,'R.V.'!I:I) -> 0 | AP102: =_xlfn.XLOOKUP(Tabla1[[#This Row],[NIC]],'R.V.'!B:B,'R.V.'!A:A) -> Rosmeri Rivera Rodriguez | AQ102: =_xlfn.XLOOKUP(Tabla1[[#This Row],[NIC]],'R.V.'!B:B,'R.V.'!G:G) -> CL 16 8 20 - VALLEDUPAR | AR102: =_xlfn.XLOOKUP(Tabla1[[#This Row],[NIC]],'R.V.'!B:B,'R.V.'!E:E) -> PRIVADO | AS102: =VLOOKUP(Tabla1[[#This Row],[NIC]],'R.V.'!B:D,3,0) -> BANCO POPULAR
A103: 6610423 | B103: 46111 | C103: BANCO POPULAR SA | D103: BANCO POPULAR SA | E103: CENTRO VALLEDUPAR CL 16 8-20 | F103: 6610423 | G103: 6610423265 | H103: 35006942 | I103: 6867798 | J103: 3110 | K103: 50 | L103: 2001 | M103: 46108 | N103: CZ1 | O103: Com (Sencilla Niv.1 ) Caribe | P103: 4246310 | Q103: 3420 | R103: 3623763.6 | T103: 63110EN0022532047200200502001000100 | U103: 46121 | V103: VALLEDUPAR | W103: NIVEL I | X103: Propiedad Cliente | Y103: MEDICION | Z103: 32 | AA103: SI | AB103: 19 | AC103: VALLEDUPAR | AD103: NO | AE103: NO | AF103: INFO_CONSOL_ESPECIALES | AG103: Comercial Liberalizado | AH103: Bancos comerciales. | AI103: 46076 | AJ103: VALLEDUPAR 3 | AK103: 4246310 | AL103: #N/A | AM103: #N/A | AN103: RECIBIDO | AO103: =_xlfn.XLOOKUP(Tabla1[[#This Row],[NIC]],'R.V.'!B:B,'R.V.'!I:I) -> 0 | AP103: =_xlfn.XLOOKUP(Tabla1[[#This Row],[NIC]],'R.V.'!B:B,'R.V.'!A:A) -> Rosmeri Rivera Rodriguez | AQ103: =_xlfn.XLOOKUP(Tabla1[[#This Row],[NIC]],'R.V.'!B:B,'R.V.'!G:G) -> CL 16 8 20 - VALLEDUPAR | AR103: =_xlfn.XLOOKUP(Tabla1[[#This Row],[NIC]],'R.V.'!B:B,'R.V.'!E:E) -> PRIVADO | AS103: =VLOOKUP(Tabla1[[#This Row],[NIC]],'R.V.'!B:D,3,0)
A104: 6866555 | B104: 46111 | C104: BANCO POPULAR SA | D104: BANCO POPULAR SA | E104: CENTRO VALLEDUPAR CL 16 8-20 | F104: 6866555 | G104: 6866555237 | H104: 35086058 | I104: 7600638 | J104: 3110 | K104: 50 | L104: 2008 | M104: 46109 | N104: CZ1 | O104: Com (Sencilla Niv.1 ) Caribe | P104: 834680 | Q104: 690 | R104: 731110.2 | T104: 63110EN0022532047200200502008001980 | U104: 46121 | V104: VALLEDUPAR | W104: NIVEL I | X104: Propiedad Cliente | Y104: MEDICION | Z104: 32 | AA104: SI | AB104: 19 | AC104: VALLEDUPAR | AD104: NO | AE104: NO | AF104: INFO_CONSOL_ESPECIALES | AG104: Comercial Liberalizado | AH104: Bancos comerciales. | AI104: 46077 | AJ104: GUATAPURI 8 | AK104: 834680 | AL104: #N/A | AM104: #N/A | AN104: RECIBIDO | AO104: =_xlfn.XLOOKUP(Tabla1[[#This Row],[NIC]],'R.V.'!B:B,'R.V.'!I:I) -> 0 | AP104: =_xlfn.XLOOKUP(Tabla1[[#This Row],[NIC]],'R.V.'!B:B,'R.V.'!A:A) -> Rosmeri Rivera Rodriguez | AQ104: =_xlfn.XLOOKUP(Tabla1[[#This Row],[NIC]],'R.V.'!B:B,'R.V.'!G:G) -> CL 16 8 20 - VALLEDUPAR | AR104: =_xlfn.XLOOKUP(Tabla1[[#This Row],[NIC]],'R.V.'!B:B,'R.V.'!E:E) -> PRIVADO | AS104: =VLOOKUP(Tabla1[[#This Row],[NIC]],'R.V.'!B:D,3,0) -> BANCO POPULAR
A105: 5320564 | B105: 46111 | C105: BANCO POPULAR SA | D105: BANCO POPULAR SA | E105: CENTRO VALLEDUPAR CL 16 8-20 | F105: 5320564 | G105: 5320564320 | H105: 25309047 | I105: 5341102 | J105: 3110 | K105: 50 | L105: 2001 | M105: 46100 | N105: CQ2 | O105: Com (Mon.dbl.Tip1Niv2)E.Caribe | P105: 7805700 | Q105: 7040 | R105: 6283904 | T105: 63110EN0022532047200200502001000100 | U105: 46121 | V105: VALLEDUPAR | W105: NIVEL II | X105: Propiedad Cliente | Y105: MEDICION | Z105: 30 | AA105: SI | AB105: 19 | AC105: VALLEDUPAR | AD105: NO | AE105: NO | AF105: INFO_CONSOL_ESPECIALES | AG105: Comercial Liberalizado | AH105: Bancos comerciales. | AI105: 46070 | AJ105: GUATAPURI 2 | AK105: 7805700 | AL105: #N/A | AM105: #N/A | AN105: RECIBIDO | AO105: =_xlfn.XLOOKUP(Tabla1[[#This Row],[NIC]],'R.V.'!B:B,'R.V.'!I:I) -> 0 | AP105: =_xlfn.XLOOKUP(Tabla1[[#This Row],[NIC]],'R.V.'!B:B,'R.V.'!A:A) -> Rosmeri Rivera Rodriguez | AQ105: =_xlfn.XLOOKUP(Tabla1[[#This Row],[NIC]],'R.V.'!B:B,'R.V.'!G:G) -> CL 16 8 20 - VALLEDUPAR | AR105: =_xlfn.XLOOKUP(Tabla1[[#This Row],[NIC]],'R.V.'!B:B,'R.V.'!E:E) -> PRIVADO | AS105: =VLOOKUP(Tabla1[[#This Row],[NIC]],'R.V.'!B:D,3,0)
A106: 7851801 | B106: 46111 | C106: BANCO POPULAR SA | D106: BANCO POPULAR SA | E106: CENTRO VALLEDUPAR CL 16 8-20 | F106: 7851801 | G106: 7851801117 | H106: 36132997 | I106: 4034620 | J106: 3110 | K106: 50 | L106: 2008 | M106: 46094 | N106: CZ1 | O106: Com (Sencilla Niv.1 ) Caribe | P106: 820390 | Q106: 566 | R106: 622973.56 | T106: 63110EN0022532047200200502008001980 | U106: 46121 | V106: VALLEDUPAR | W106: NIVEL I | X106: Propiedad Empresa | Y106: MEDICION | Z106: 30 | AA106: SI | AB106: 19 | AC106: VALLEDUPAR | AD106: NO | AE106: NO | AF106: INFO_CONSOL_ESPECIALES | AG106: Comercial Liberalizado | AH106: SIN C.I.I.U. | AI106: 46064 | AJ106: GUATAPURI 8 | AK106: 820390 | AL106: #N/A | AM106: #N/A | AN106: RECIBIDO | AO106: =_xlfn.XLOOKUP(Tabla1[[#This Row],[NIC]],'R.V.'!B:B,'R.V.'!I:I) -> 0 | AP106: =_xlfn.XLOOKUP(Tabla1[[#This Row],[NIC]],'R.V.'!B:B,'R.V.'!A:A) -> Rosmeri Rivera Rodriguez | AQ106: =_xlfn.XLOOKUP(Tabla1[[#This Row],[NIC]],'R.V.'!B:B,'R.V.'!G:G) -> CL 16 8 20 - VALLEDUPAR | AR106: =_xlfn.XLOOKUP(Tabla1[[#This Row],[NIC]],'R.V.'!B:B,'R.V.'!E:E) -> PRIVADO | AS106: =VLOOKUP(Tabla1[[#This Row],[NIC]],'R.V.'!B:D,3,0)
A107: 5331212 | B107: 46111 | C107: ORGANIZACION MEDICA | D107: ORGANIZACION MEDICA | E107: SIMON BOLIVAR VALLEDUPAR CR 18D 22-9 | F107: 5331212 | G107: 5331212369 | H107: 25342575 | I107: 5362398 | J107: 3110 | K107: 50 | L107: 2008 | M107: 46101 | N107: CZ1 | O107: Com (Sencilla Niv.1 ) Caribe | P107: 2638580 | Q107: 1360 | R107: 1441028.8 | T107: 63110EN0022533107100100502008001400 | U107: 46121 | V107: VALLEDUPAR | W107: NIVEL I | X107: Propiedad Cliente | Y107: MEDICION | Z107: 30 | AA107: SI | AB107: 20 | AC107: VALLEDUPAR | AD107: NO | AE107: NO | AF107: INFO_CONSOL_ESPECIALES | AG107: Comercial Liberalizado | AH107: Actividades de hospitales | AI107: 46071 | AJ107: GUATAPURI 5 | AK107: 383147400 | AL107: #N/A | AM107: #N/A | AN107: RECIBIDO | AO107: =_xlfn.XLOOKUP(Tabla1[[#This Row],[NIC]],'R.V.'!B:B,'R.V.'!I:I) -> 0 | AP107: =_xlfn.XLOOKUP(Tabla1[[#This Row],[NIC]],'R.V.'!B:B,'R.V.'!A:A) -> Rosmeri Rivera Rodriguez | AQ107: =_xlfn.XLOOKUP(Tabla1[[#This Row],[NIC]],'R.V.'!B:B,'R.V.'!G:G) -> CR 19 14 47 - VALLEDUPAR | AR107: =_xlfn.XLOOKUP(Tabla1[[#This Row],[NIC]],'R.V.'!B:B,'R.V.'!E:E) -> PRIVADO | AS107: =VLOOKUP(Tabla1[[#This Row],[NIC]],'R.V.'!B:D,3,0) -> CLINICA SANTA ISABEL
A108: 6587914 | B108: 46111 | C108: ORGANIZACION MEDICA | D108: ORGANIZACION MEDICA | E108: SIMON BOLIVAR VALLEDUPAR CR 18D 22-9 | F108: 6587914 | G108: 6587914303 | H108: 25342575 | I108: 6795791 | J108: 3110 | K108: 50 | L108: 2008 | P108: 11319550 | Q108: 0 | R108: 0 | T108: 63110EN0022533107100100502008001400 | U108: 46121 | V108: VALLEDUPAR | Z108: 0 | AA108: SI | AB108: 20 | AC108: VALLEDUPAR | AD108: NO | AE108: NO | AF108: INFO_CONSOL_ESPECIALES | AG108: Comercial Liberalizado | AH108: Actividades de hospitales | AI108: 46071 | AJ108: GUATAPURI 5 | AK108: 3406357840 | AL108: #N/A | AM108: #N/A | AN108: RECIBIDO | AO108: =_xlfn.XLOOKUP(Tabla1[[#This Row],[NIC]],'R.V.'!B:B,'R.V.'!I:I) -> 0 | AP108: =_xlfn.XLOOKUP(Tabla1[[#This Row],[NIC]],'R.V.'!B:B,'R.V.'!A:A) -> Rosmeri Rivera Rodriguez | AQ108: =_xlfn.XLOOKUP(Tabla1[[#This Row],[NIC]],'R.V.'!B:B,'R.V.'!G:G) -> CR 19 14 47 - VALLEDUPAR | AR108: =_xlfn.XLOOKUP(Tabla1[[#This Row],[NIC]],'R.V.'!B:B,'R.V.'!E:E) -> PRIVADO | AS108: =VLOOKUP(Tabla1[[#This Row],[NIC]],'R.V.'!B:D,3,0) -> CLINICA SANTA ISABEL
A109: 6587914 | B109: 46111 | C109: ORGANIZACION MEDICA | D109: ORGANIZACION MEDICA | E109: SIMON BOLIVAR VALLEDUPAR CR 18D 22-9 | F109: 6587914 | G109: 6587914302 | H109: 25342575 | I109: 6795790 | J109: 3110 | K109: 50 | L109: 2008 | M109: 46101 | N109: CY2 | O109: Com(Mon.dbl.Tip2Niv.2)Caribe | P109: 82330780 | Q109: 82500 | R109: 72638498 | T109: 63110EN0022533107100100502008001400 | U109: 46121 | V109: VALLEDUPAR | W109: NIVEL II | X109: Propiedad Cliente | Y109: MEDICION | Z109: 30 | AA109: SI | AB109: 20 | AC109: VALLEDUPAR | AD109: NO | AE109: NO | AF109: INFO_CONSOL_ESPECIALES | AG109: Comercial Liberalizado | AH109: Actividades de hospitales | AI109: 46071 | AJ109: GUATAPURI 5 | AK109: 3406357840 | AL109: #N/A | AM109: #N/A | AN109: RECIBIDO | AO109: =_xlfn.XLOOKUP(Tabla1[[#This Row],[NIC]],'R.V.'!B:B,'R.V.'!I:I) -> 0 | AP109: =_xlfn.XLOOKUP(Tabla1[[#This Row],[NIC]],'R.V.'!B:B,'R.V.'!A:A) -> Rosmeri Rivera Rodriguez | AQ109: =_xlfn.XLOOKUP(Tabla1[[#This Row],[NIC]],'R.V.'!B:B,'R.V.'!G:G) -> CR 19 14 47 - VALLEDUPAR | AR109: =_xlfn.XLOOKUP(Tabla1[[#This Row],[NIC]],'R.V.'!B:B,'R.V.'!E:E) -> PRIVADO | AS109: =VLOOKUP(Tabla1[[#This Row],[NIC]],'R.V.'!B:D,3,0) -> CLINICA SANTA ISABEL
A110: 6826046 | B110: 46111 | C110: ORGANIZACION MEDICA | D110: ORGANIZACION MEDICA | E110: SIMON BOLIVAR VALLEDUPAR CR 18D 22-9 | F110: 6826046 | G110: 6826046269 | H110: 25300027 | I110: 7260442 | J110: 3180 | K110: 6 | L110: 1205 | M110: 46109 | N110: CZ1 | O110: Com (Sencilla Niv.1 ) Caribe | P110: 5053330 | Q110: 3142 | R110: 3458273.7 | T110: 63180EN0022533107100100061205010466 | U110: 46121 | V110: VALLEDUPAR | W110: NIVEL I | X110: Propiedad Empresa | Y110: ESTIMADO | Z110: 32 | AA110: SI | AB110: 20 | AC110: VALLEDUPAR | AD110: NO | AE110: NO | AF110: INFO_CONSOL_ESPECIALES | AG110: Comercial Liberalizado | AH110: Actividades de hospitales | AI110: 46077 | AJ110: GUATAPURI 5 | AK110: 190992230 | AL110: #N/A | AM110: #N/A | AN110: RECIBIDO | AO110: =_xlfn.XLOOKUP(Tabla1[[#This Row],[NIC]],'R.V.'!B:B,'R.V.'!I:I) -> 0 | AP110: =_xlfn.XLOOKUP(Tabla1[[#This Row],[NIC]],'R.V.'!B:B,'R.V.'!A:A) -> Rosmeri Rivera Rodriguez | AQ110: =_xlfn.XLOOKUP(Tabla1[[#This Row],[NIC]],'R.V.'!B:B,'R.V.'!G:G) -> CR 19 14 47 - VALLEDUPAR | AR110: =_xlfn.XLOOKUP(Tabla1[[#This Row],[NIC]],'R.V.'!B:B,'R.V.'!E:E) -> PRIVADO | AS110: =VLOOKUP(Tabla1[[#This Row],[NIC]],'R.V.'!B:D,3,0) -> CLINICA SANTA ISABEL
A111: 5332777 | B111: 46111 | C111: ORGANIZACION MEDICA | D111: ORGANIZACION MEDICA | E111: SIMON BOLIVAR VALLEDUPAR CR 18D 22-9 | F111: 5332777 | G111: 5332777325 | H111: 25342578 | I111: 5365528 | J111: 3110 | K111: 50 | L111: 2008 | M111: 46101 | N111: CZ1 | O111: Com (Sencilla Niv.1 ) Caribe | P111: 192040 | Q111: 80 | R111: 89629.6 | T111: 63110EN0022533107100100502008001400 | U111: 46121 | V111: VALLEDUPAR | W111: NIVEL I | X111: Propiedad Empresa | Y111: ESTIMADO | Z111: 30 | AA111: SI | AB111: 20 | AC111: VALLEDUPAR | AD111: NO | AE111: NO | AF111: INFO_CONSOL_ESPECIALES | AG111: Comercial Liberalizado | AH111: Actividades de hospitales | AI111: 46071 | AJ111: GUATAPURI 5 | AK111: 36964740 | AL111: #N/A | AM111: #N/A | AN111: RECIBIDO | AO111: =_xlfn.XLOOKUP(Tabla1[[#This Row],[NIC]],'R.V.'!B:B,'R.V.'!I:I) -> 0 | AP111: =_xlfn.XLOOKUP(Tabla1[[#This Row],[NIC]],'R.V.'!B:B,'R.V.'!A:A) -> Rosmeri Rivera Rodriguez | AQ111: =_xlfn.XLOOKUP(Tabla1[[#This Row],[NIC]],'R.V.'!B:B,'R.V.'!G:G) -> CR 19 14 47 - VALLEDUPAR | AR111: =_xlfn.XLOOKUP(Tabla1[[#This Row],[NIC]],'R.V.'!B:B,'R.V.'!E:E) -> PRIVADO | AS111: =VLOOKUP(Tabla1[[#This Row],[NIC]],'R.V.'!B:D,3,0) -> CLINICA SANTA ISABEL
A112: 5362898 | B112: 46111 | C112: ORGANIZACION MEDICA | D112: ORGANIZACION MEDICA | E112: SIMON BOLIVAR VALLEDUPAR CR 18D 22-9 | F112: 5362898 | G112: 5362898333 | H112: 25300027 | I112: 5425770 | J112: 3110 | K112: 3 | L112: 2101 | M112: 46109 | N112: CZ1 | O112: Com (Sencilla Niv.1 ) Caribe | P112: 11142410 | Q112: 4021 | R112: 4425753.9 | T112: 63110EN0022533107100100032101000620 | U112: 46121 | V112: VALLEDUPAR | W112: NIVEL I | X112: Propiedad Empresa | Y112: MEDICION | Z112: 32 | AA112: SI | AB112: 20 | AC112: VALLEDUPAR | AD112: NO | AE112: NO | AF112: INFO_CONSOL_ESPECIALES | AG112: Comercial Liberalizado | AH112: Actividades de hospitales | AI112: 46077 | AJ112: GUATAPURI 5 | AK112: 315126600 | AL112: #N/A | AM112: #N/A | AN112: RECIBIDO | AO112: =_xlfn.XLOOKUP(Tabla1[[#This Row],[NIC]],'R.V.'!B:B,'R.V.'!I:I) -> 0 | AP112: =_xlfn.XLOOKUP(Tabla1[[#This Row],[NIC]],'R.V.'!B:B,'R.V.'!A:A) -> Rosmeri Rivera Rodriguez | AQ112: =_xlfn.XLOOKUP(Tabla1[[#This Row],[NIC]],'R.V.'!B:B,'R.V.'!G:G) -> CR 19 14 47 - VALLEDUPAR | AR112: =_xlfn.XLOOKUP(Tabla1[[#This Row],[NIC]],'R.V.'!B:B,'R.V.'!E:E) -> PRIVADO | AS112: =VLOOKUP(Tabla1[[#This Row],[NIC]],'R.V.'!B:D,3,0) -> CLINICA SANTA ISABEL
A113: 5360554 | B113: 46111 | C113: CLINICA MEDICOS SA | D113: CLINICA MEDICOS SA | E113: LOPERENA VALLEDUPAR CL 16B 11.-33 LOC 5 | F113: 5360554 | G113: 5360554354 | H113: 25329021 | I113: 5421082 | J113: 3110 | K113: 50 | L113: 2002 | M113: 46102 | N113: CY2 | O113: Com(Mon.dbl.Tip2Niv.2)Caribe | P113: 194216230 | Q113: 159500 | R113: 140429839 | T113: 63110EN0022536029900300502002002182 | U113: 46121 | V113: VALLEDUPAR | W113: NIVEL II | X113: Propiedad Cliente | Y113: MEDICION | Z113: 30 | AA113: SI | AB113: 21 | AC113: VALLEDUPAR | AD113: NO | AE113: NO | AF113: INFO_CONSOL_ESPECIALES | AG113: Comercial Liberalizado | AH113: Actividades de hospitales | AI113: 46072 | AJ113: SALGUERO 1 | AK113: 1597512314 | AL113: #N/A | AM113: #N/A | AN113: RECIBIDO | AO113: =_xlfn.XLOOKUP(Tabla1[[#This Row],[NIC]],'R.V.'!B:B,'R.V.'!I:I) -> 0 | AP113: =_xlfn.XLOOKUP(Tabla1[[#This Row],[NIC]],'R.V.'!B:B,'R.V.'!A:A) -> Rosmeri Rivera Rodriguez | AQ113: =_xlfn.XLOOKUP(Tabla1[[#This Row],[NIC]],'R.V.'!B:B,'R.V.'!G:G) -> CL 14 17 47 - VALLEDUPAR | AR113: =_xlfn.XLOOKUP(Tabla1[[#This Row],[NIC]],'R.V.'!B:B,'R.V.'!E:E) -> PRIVADO | AS113: =VLOOKUP(Tabla1[[#This Row],[NIC]],'R.V.'!B:D,3,0)
A114: 6692939 | B114: 46111 | C114: CLINICA MEDICOS SA | D114: CLINICA MEDICOS SA | E114: LOPERENA VALLEDUPAR CL 16B 11.-33 LOC 5 | F114: 6692939 | G114: 6692939278 | H114: 25329265 | I114: 7036107 | J114: 3110 | K114: 50 | L114: 2002 | M114: 46102 | N114: CZ1 | O114: Com (Sencilla Niv.1 ) Caribe | P114: 0 | Q114: 0 | R114: 0 | T114: 63110EN0022536029900300502002002242 | V114: VALLEDUPAR | W114: NIVEL I | X114: Propiedad Cliente | Y114: MEDICION | Z114: 30 | AA114: SI | AB114: 21 | AC114: VALLEDUPAR | AD114: NO | AE114: NO | AF114: INFO_CONSOL_ESPECIALES | AG114: Comercial Liberalizado | AH114: Actividades de hospitales | AI114: 46072 | AJ114: VALLEDUPAR 3 | AK114: 0 | AL114: #N/A | AM114: #N/A | AN114: RECIBIDO | AO114: =_xlfn.XLOOKUP(Tabla1[[#This Row],[NIC]],'R.V.'!B:B,'R.V.'!I:I) -> 0 | AP114: =_xlfn.XLOOKUP(Tabla1[[#This Row],[NIC]],'R.V.'!B:B,'R.V.'!A:A) -> Rosmeri Rivera Rodriguez | AQ114: =_xlfn.XLOOKUP(Tabla1[[#This Row],[NIC]],'R.V.'!B:B,'R.V.'!G:G) -> CL 14 17 47 - VALLEDUPAR | AR114: =_xlfn.XLOOKUP(Tabla1[[#This Row],[NIC]],'R.V.'!B:B,'R.V.'!E:E) -> PRIVADO | AS114: =VLOOKUP(Tabla1[[#This Row],[NIC]],'R.V.'!B:D,3,0) -> CLINICA MEDICOS S.A.
A115: 5348789 | B115: 46111 | C115: CLINICA MEDICOS SA | D115: CLINICA MEDICOS SA | E115: LOPERENA VALLEDUPAR CL 16B 11.-33 LOC 5 | F115: 5348789 | G115: 5348789348 | H115: 25329332 | I115: 5397552 | J115: 3110 | K115: 1 | L115: 101 | M115: 46088 | N115: CZ1 | O115: Com (Sencilla Niv.1 ) Caribe | P115: 73580 | Q115: 58 | R115: 63838.28 | T115: 63110EN0022536029900300010101001890 | U115: 46121 | V115: VALLEDUPAR | W115: NIVEL I | X115: Propiedad Empresa | Y115: ESTIMADO | Z115: 30 | AA115: SI | AB115: 21 | AC115: VALLEDUPAR | AD115: NO | AE115: NO | AF115: INFO_CONSOL_ESPECIALES | AG115: Comercial Liberalizado | AH115: Actividades de hospitales | AI115: 46058 | AJ115: SALGUERO 1 | AK115: 73580 | AL115: #N/A | AM115: #N/A | AN115: RECIBIDO | AO115: =_xlfn.XLOOKUP(Tabla1[[#This Row],[NIC]],'R.V.'!B:B,'R.V.'!I:I) -> 0 | AP115: =_xlfn.XLOOKUP(Tabla1[[#This Row],[NIC]],'R.V.'!B:B,'R.V.'!A:A) -> Rosmeri Rivera Rodriguez | AQ115: =_xlfn.XLOOKUP(Tabla1[[#This Row],[NIC]],'R.V.'!B:B,'R.V.'!G:G) -> CL 14 17 47 - VALLEDUPAR | AR115: =_xlfn.XLOOKUP(Tabla1[[#This Row],[NIC]],'R.V.'!B:B,'R.V.'!E:E) -> PRIVADO | AS115: =VLOOKUP(Tabla1[[#This Row],[NIC]],'R.V.'!B:D,3,0) -> CLINICA MEDICOS S.A.
A116: 7796096 | B116: 46111 | C116: CLINICA MEDICOS SA | D116: CLINICA MEDICOS SA | E116: LOPERENA VALLEDUPAR CL 16B 11.-33 LOC 5 | F116: 7796096 | G116: 7796096131 | H116: 36116433 | I116: 1983278 | J116: 3110 | K116: 32 | L116: 910 | M116: 46098 | N116: CZ1 | O116: Com (Sencilla Niv.1 ) Caribe | P116: 2371710 | Q116: 1825 | R116: 2008704.5 | T116: 63110EN0022536029900300320910003385 | U116: 46121 | V116: VALLEDUPAR | W116: NIVEL I | X116: Propiedad Empresa | Y116: MEDICION | Z116: 31 | AA116: SI | AB116: 21 | AC116: VALLEDUPAR | AD116: NO | AE116: NO | AF116: INFO_CONSOL_ESPECIALES | AG116: Comercial Liberalizado | AH116: Comercio al por mayor de | AI116: 46067 | AJ116: GUATAPURI 1 | AK116: 2371710 | AL116: #N/A | AM116: #N/A | AN116: RECIBIDO | AO116: =_xlfn.XLOOKUP(Tabla1[[#This Row],[NIC]],'R.V.'!B:B,'R.V.'!I:I) -> 0 | AP116: =_xlfn.XLOOKUP(Tabla1[[#This Row],[NIC]],'R.V.'!B:B,'R.V.'!A:A) -> Rosmeri Rivera Rodriguez | AQ116: =_xlfn.XLOOKUP(Tabla1[[#This Row],[NIC]],'R.V.'!B:B,'R.V.'!G:G) -> CL 14 17 47 - VALLEDUPAR | AR116: =_xlfn.XLOOKUP(Tabla1[[#This Row],[NIC]],'R.V.'!B:B,'R.V.'!E:E) -> PRIVADO | AS116: =VLOOKUP(Tabla1[[#This Row],[NIC]],'R.V.'!B:D,3,0)
A117: 7677294 | B117: 46111 | C117: CLINICA MEDICOS SA | D117: CLINICA MEDICOS SA | E117: LOPERENA VALLEDUPAR CL 16B 11.-33 LOC 5 | F117: 7677294 | G117: 7677294185 | H117: 36066226 | I117: 3262992 | J117: 3110 | K117: 50 | L117: 2004 | M117: 46102 | N117: CQ2 | O117: Com (Mon.dbl.Tip1Niv2)E.Caribe | P117: 554381640 | Q117: 455400 | R117: 401607360 | T117: 63110EN0022536029900300502004001940 | U117: 46121 | V117: VALLEDUPAR | W117: NIVEL II | X117: Propiedad Cliente | Y117: MEDICION | Z117: 30 | AA117: SI | AB117: 21 | AC117: VALLEDUPAR | AD117: NO | AE117: NO | AF117: INFO_CONSOL_ESPECIALES | AG117: Comercial Liberalizado | AH117: Actividades de hospitales | AI117: 46072 | AJ117: GUATAPURI 1 | AK117: 4489834160 | AL117: #N/A | AM117: #N/A | AN117: RECIBIDO | AO117: =_xlfn.XLOOKUP(Tabla1[[#This Row],[NIC]],'R.V.'!B:B,'R.V.'!I:I) -> 0 | AP117: =_xlfn.XLOOKUP(Tabla1[[#This Row],[NIC]],'R.V.'!B:B,'R.V.'!A:A) -> Rosmeri Rivera Rodriguez | AQ117: =_xlfn.XLOOKUP(Tabla1[[#This Row],[NIC]],'R.V.'!B:B,'R.V.'!G:G) -> CL 14 17 47 - VALLEDUPAR | AR117: =_xlfn.XLOOKUP(Tabla1[[#This Row],[NIC]],'R.V.'!B:B,'R.V.'!E:E) -> PRIVADO | AS117: =VLOOKUP(Tabla1[[#This Row],[NIC]],'R.V.'!B:D,3,0)
A118: 5359673 | B118: 46111 | C118: BBVA COLOMBIA SA | D118: BBVA COLOMBIA SA | E118: URB BULEVAR DE LA SIERRA VALLEDUPAR SECTOR 1 MZ A-9 | F118: 5359673 | G118: 5359673334 | H118: 25309686 | I118: 5419320 | J118: 3110 | K118: 11 | L118: 3912 | M118: 46100 | N118: CZ1 | O118: Com (Sencilla Niv.1 ) Caribe | P118: 10512460 | Q118: 8600 | R118: 9112388 | T118: 63110EN0023509431400100113912007055 | U118: 46121 | V118: VALLEDUPAR | W118: NIVEL I | X118: Propiedad Cliente | Y118: MEDICION | Z118: 30 | AA118: SI | AB118: 22 | AC118: VALLEDUPAR | AD118: NO | AE118: NO | AF118: INFO_CONSOL_ESPECIALES | AG118: Comercial Liberalizado | AH118: Bancos comerciales. | AI118: 46070 | AJ118: GUATAPURI 2 | AK118: 10512460 | AL118: #N/A | AM118: #N/A | AN118: RECIBIDO | AO118: =_xlfn.XLOOKUP(Tabla1[[#This Row],[NIC]],'R.V.'!B:B,'R.V.'!I:I) -> 0 | AP118: =_xlfn.XLOOKUP(Tabla1[[#This Row],[NIC]],'R.V.'!B:B,'R.V.'!A:A) -> Rosmeri Rivera Rodriguez | AQ118: =_xlfn.XLOOKUP(Tabla1[[#This Row],[NIC]],'R.V.'!B:B,'R.V.'!G:G) -> CR 9 15A 25 - VALLEDUPAR | AR118: =_xlfn.XLOOKUP(Tabla1[[#This Row],[NIC]],'R.V.'!B:B,'R.V.'!E:E) -> PRIVADO | AS118: =VLOOKUP(Tabla1[[#This Row],[NIC]],'R.V.'!B:D,3,0)
A119: 7618957 | B119: 46111 | C119: BBVA COLOMBIA SA | D119: BBVA COLOMBIA SA | E119: URB BULEVAR DE LA SIERRA VALLEDUPAR SECTOR 1 MZ A-9 | F119: 7618957 | G119: 7618957180 | H119: 36012838 | I119: 8815344 | J119: 3110 | K119: 11 | L119: 3912 | M119: 46099 | N119: CZ1 | O119: Com (Sencilla Niv.1 ) Caribe | P119: 920870 | Q119: 671 | R119: 710978.18 | T119: 63110EN0023509431400100113912007035 | U119: 46121 | V119: VALLEDUPAR | W119: NIVEL I | X119: Propiedad Cliente | Y119: MEDICION | Z119: 30 | AA119: SI | AB119: 22 | AC119: VALLEDUPAR | AD119: NO | AE119: NO | AF119: INFO_CONSOL_ESPECIALES | AG119: Comercial Liberalizado | AH119: Actividades administrativ | AI119: 46069 | AJ119: GUATAPURI 2 | AK119: 920870 | AL119: #N/A | AM119: #N/A | AN119: RECIBIDO | AO119: =_xlfn.XLOOKUP(Tabla1[[#This Row],[NIC]],'R.V.'!B:B,'R.V.'!I:I) -> 0 | AP119: =_xlfn.XLOOKUP(Tabla1[[#This Row],[NIC]],'R.V.'!B:B,'R.V.'!A:A) -> Rosmeri Rivera Rodriguez | AQ119: =_xlfn.XLOOKUP(Tabla1[[#This Row],[NIC]],'R.V.'!B:B,'R.V.'!G:G) -> CR 9 15A 25 - VALLEDUPAR | AR119: =_xlfn.XLOOKUP(Tabla1[[#This Row],[NIC]],'R.V.'!B:B,'R.V.'!E:E) -> PRIVADO | AS119: =VLOOKUP(Tabla1[[#This Row],[NIC]],'R.V.'!B:D,3,0)
A120: 5902101 | B120: 46111 | C120: BBVA COLOMBIA SA | D120: BBVA COLOMBIA SA | E120: URB BULEVAR DE LA SIERRA VALLEDUPAR SECTOR 1 MZ A-9 | F120: 5902101 | G120: 5902101307 | H120: 25309686 | I120: 5939096 | J120: 3110 | K120: 11 | L120: 3912 | M120: 46098 | N120: CZ1 | O120: Com (Sencilla Niv.1 ) Caribe | P120: 4615780 | Q120: 3719 | R120: 3940578 | T120: 63110EN0023509431400100113912007035 | U120: 46121 | V120: VALLEDUPAR | W120: NIVEL I | X120: Propiedad Cliente | Y120: ESTIMADO | Z120: 31 | AA120: SI | AB120: 22 | AC120: VALLEDUPAR | AD120: NO | AE120: NO | AF120: INFO_CONSOL_ESPECIALES | AG120: Comercial Liberalizado | AH120: Bancos comerciales. | AI120: 46067 | AJ120: GUATAPURI 2 | AK120: 4615780 | AL120: #N/A | AM120: #N/A | AN120: RECIBIDO | AO120: =_xlfn.XLOOKUP(Tabla1[[#This Row],[NIC]],'R.V.'!B:B,'R.V.'!I:I) -> 0 | AP120: =_xlfn.XLOOKUP(Tabla1[[#This Row],[NIC]],'R.V.'!B:B,'R.V.'!A:A) -> Rosmeri Rivera Rodriguez | AQ120: =_xlfn.XLOOKUP(Tabla1[[#This Row],[NIC]],'R.V.'!B:B,'R.V.'!G:G) -> CR 9 15A 25 - VALLEDUPAR | AR120: =_xlfn.XLOOKUP(Tabla1[[#This Row],[NIC]],'R.V.'!B:B,'R.V.'!E:E) -> PRIVADO | AS120: =VLOOKUP(Tabla1[[#This Row],[NIC]],'R.V.'!B:D,3,0)
A121: 7671885 | B121: 46111 | C121: BBVA COLOMBIA SA | D121: BBVA COLOMBIA SA | E121: URB BULEVAR DE LA SIERRA VALLEDUPAR SECTOR 1 MZ A-9 | F121: 7671885 | G121: 7671885157 | H121: 36025678 | I121: 3187055 | J121: 3110 | K121: 11 | L121: 3912 | M121: 46105 | N121: CZ1 | O121: Com (Sencilla Niv.1 ) Caribe | P121: 1480660 | Q121: 1224 | R121: 1296925.9 | T121: 63110EN0023509431400100113912007035 | U121: 46121 | V121: VALLEDUPAR | W121: NIVEL I | X121: Propiedad Cliente | Y121: MEDICION | Z121: 32 | AA121: SI | AB121: 22 | AC121: VALLEDUPAR | AD121: NO | AE121: NO | AF121: INFO_CONSOL_ESPECIALES | AG121: Comercial Liberalizado | AH121: Bancos comerciales. | AI121: 46073 | AJ121: SALGUERO 3 | AK121: 1480660 | AL121: #N/A | AM121: #N/A | AN121: RECIBIDO | AO121: =_xlfn.XLOOKUP(Tabla1[[#This Row],[NIC]],'R.V.'!B:B,'R.V.'!I:I) -> 0 | AP121: =_xlfn.XLOOKUP(Tabla1[[#This Row],[NIC]],'R.V.'!B:B,'R.V.'!A:A) -> Rosmeri Rivera Rodriguez | AQ121: =_xlfn.XLOOKUP(Tabla1[[#This Row],[NIC]],'R.V.'!B:B,'R.V.'!G:G) -> CR 9 15A 25 - VALLEDUPAR | AR121: =_xlfn.XLOOKUP(Tabla1[[#This Row],[NIC]],'R.V.'!B:B,'R.V.'!E:E) -> PRIVADO | AS121: =VLOOKUP(Tabla1[[#This Row],[NIC]],'R.V.'!B:D,3,0)
A122: 5337776 | B122: 46111 | C122: BBVA COLOMBIA SA | D122: BBVA COLOMBIA SA | E122: URB BULEVAR DE LA SIERRA VALLEDUPAR SECTOR 1 MZ A-9 | F122: 5337776 | G122: 5337776322 | H122: 25329180 | I122: 5375526 | J122: 3110 | K122: 11 | L122: 3912 | M122: 46100 | N122: CZ1 | O122: Com (Sencilla Niv.1 ) Caribe | P122: 410740 | Q122: 240 | R122: 264158.4 | T122: 63110EN0023509431400100113912007055 | U122: 46121 | V122: VALLEDUPAR | W122: NIVEL I | X122: Propiedad Empresa | Y122: MEDICION | Z122: 30 | AA122: SI | AB122: 22 | AC122: VALLEDUPAR | AD122: NO | AE122: NO | AF122: INFO_CONSOL_ESPECIALES | AG122: Comercial Liberalizado | AH122: Bancos comerciales. | AI122: 46070 | AJ122: GUATAPURI 2 | AK122: 5839370 | AL122: #N/A | AM122: #N/A | AN122: RECIBIDO | AO122: =_xlfn.XLOOKUP(Tabla1[[#This Row],[NIC]],'R.V.'!B:B,'R.V.'!I:I) -> 0 | AP122: =_xlfn.XLOOKUP(Tabla1[[#This Row],[NIC]],'R.V.'!B:B,'R.V.'!A:A) -> Rosmeri Rivera Rodriguez | AQ122: =_xlfn.XLOOKUP(Tabla1[[#This Row],[NIC]],'R.V.'!B:B,'R.V.'!G:G) -> CR 9 15A 25 - VALLEDUPAR | AR122: =_xlfn.XLOOKUP(Tabla1[[#This Row],[NIC]],'R.V.'!B:B,'R.V.'!E:E) -> PRIVADO | AS122: =VLOOKUP(Tabla1[[#This Row],[NIC]],'R.V.'!B:D,3,0) -> BBVA
A123: 5332976 | B123: 46111 | C123: BBVA COLOMBIA SA | D123: BBVA COLOMBIA SA | E123: URB BULEVAR DE LA SIERRA VALLEDUPAR SECTOR 1 MZ A-9 | F123: 5332976 | G123: 5332976322 | H123: 25322065 | I123: 5365926 | J123: 3110 | K123: 11 | L123: 3912 | M123: 46102 | N123: CZ1 | O123: Com (Sencilla Niv.1 ) Caribe | P123: 109170 | Q123: 0 | R123: 0 | T123: 63110EN0023509431400100113912007055 | U123: 46121 | V123: VALLEDUPAR | W123: NIVEL I | X123: Propiedad Cliente | Y123: MEDICION | Z123: 30 | AA123: SI | AB123: 22 | AC123: VALLEDUPAR | AD123: NO | AE123: NO | AF123: INFO_CONSOL_ESPECIALES | AG123: Comercial Liberalizado | AH123: Bancos comerciales. | AI123: 46072 | AJ123: SALGUERO 1 | AK123: 1631700 | AL123: #N/A | AM123: #N/A | AN123: RECIBIDO | AO123: =_xlfn.XLOOKUP(Tabla1[[#This Row],[NIC]],'R.V.'!B:B,'R.V.'!I:I) -> 0 | AP123: =_xlfn.XLOOKUP(Tabla1[[#This Row],[NIC]],'R.V.'!B:B,'R.V.'!A:A) -> Rosmeri Rivera Rodriguez | AQ123: =_xlfn.XLOOKUP(Tabla1[[#This Row],[NIC]],'R.V.'!B:B,'R.V.'!G:G) -> CR 9 15A 25 - VALLEDUPAR | AR123: =_xlfn.XLOOKUP(Tabla1[[#This Row],[NIC]],'R.V.'!B:B,'R.V.'!E:E) -> PRIVADO | AS123: =VLOOKUP(Tabla1[[#This Row],[NIC]],'R.V.'!B:D,3,0)
A124: 5349703 | B124: 46111 | C124: DUSAKAWI IPS HOSPITA | D124: DUSAKAWI IPS HOSPITA | E124: ROSALIA VALLEDUPAR CR 9 4N-105 | F124: 5349703 | G124: 5349703359 | H124: 25305782 | I124: 5399380 | J124: 3110 | K124: 32 | L124: 918 | M124: 46102 | N124: CZ1 | O124: Com (Sencilla Niv.1 ) Caribe | P124: 9872850 | Q124: 8160 | R124: 8646172.8 | T124: 63110EN0022532167900200320918002090 | U124: 46121 | V124: VALLEDUPAR | W124: NIVEL I | X124: Propiedad Cliente | Y124: MEDICION | Z124: 30 | AA124: SI | AB124: 23 | AC124: VALLEDUPAR | AD124: NO | AE124: NO | AF124: INFO_CONSOL_ESPECIALES | AG124: Comercial Liberalizado | AH124: Actividades de hospitales | AI124: 46072 | AJ124: GUATAPURI 1 | AK124: 9872850 | AL124: #N/A | AM124: #N/A | AN124: RECIBIDO | AO124: =_xlfn.XLOOKUP(Tabla1[[#This Row],[NIC]],'R.V.'!B:B,'R.V.'!I:I) -> 0 | AP124: =_xlfn.XLOOKUP(Tabla1[[#This Row],[NIC]],'R.V.'!B:B,'R.V.'!A:A) -> Rosmeri Rivera Rodriguez | AQ124: =_xlfn.XLOOKUP(Tabla1[[#This Row],[NIC]],'R.V.'!B:B,'R.V.'!G:G) -> CL 14 15 78 - VALLEDUPAR | AR124: =_xlfn.XLOOKUP(Tabla1[[#This Row],[NIC]],'R.V.'!B:B,'R.V.'!E:E) -> PRIVADO | AS124: =VLOOKUP(Tabla1[[#This Row],[NIC]],'R.V.'!B:D,3,0)
A125: 5303305 | B125: 46111 | C125: COMFACESAR | D125: COMFACESAR | E125: MAYALES 1 ETAPA VALLEDUPAR CL 31 4B-69 | F125: 5303305 | G125: 5303305312 | H125: 25357303 | I125: 5306584 | J125: 3110 | K125: 7 | L125: 1303 | M125: 46093 | N125: CZ1 | O125: Com (Sencilla Niv.1 ) Caribe | P125: 764020 | Q125: 608 | R125: 669201.28 | T125: 63110EN0022534952400100071303000100 | U125: 46121 | V125: VALLEDUPAR | W125: NIVEL I | X125: Propiedad Empresa | Y125: MEDICION | Z125: 30 | AA125: SI | AB125: 24 | AC125: VALLEDUPAR | AD125: NO | AE125: NO | AF125: INFO_CONSOL_ESPECIALES | AG125: Comercial Liberalizado | AH125: Actividades de planes de | AI125: 46063 | AJ125: GUATAPURI 4 | AK125: 764020 | AL125: #N/A | AM125: #N/A | AN125: RECIBIDO | AO125: =_xlfn.XLOOKUP(Tabla1[[#This Row],[NIC]],'R.V.'!B:B,'R.V.'!I:I) -> 0 | AP125: =_xlfn.XLOOKUP(Tabla1[[#This Row],[NIC]],'R.V.'!B:B,'R.V.'!A:A) -> Rosmeri Rivera Rodriguez | AQ125: =_xlfn.XLOOKUP(Tabla1[[#This Row],[NIC]],'R.V.'!B:B,'R.V.'!G:G) -> CR 9 16A 48 - VALLEDUPAR | AR125: =_xlfn.XLOOKUP(Tabla1[[#This Row],[NIC]],'R.V.'!B:B,'R.V.'!E:E) -> PRIVADO | AS125: =VLOOKUP(Tabla1[[#This Row],[NIC]],'R.V.'!B:D,3,0)
A126: 5303306 | B126: 46111 | C126: COMFACESAR | D126: COMFACESAR | E126: MAYALES 1 ETAPA VALLEDUPAR CL 31 4B-69 | F126: 5303306 | G126: 5303306313 | H126: 25357304 | I126: 5306586 | J126: 3110 | K126: 7 | L126: 1303 | M126: 46093 | N126: CZ1 | O126: Com (Sencilla Niv.1 ) Caribe | P126: 912640 | Q126: 117 | R126: 128777.22 | T126: 63110EN0022534952400100071303000100 | U126: 46121 | V126: VALLEDUPAR | W126: NIVEL I | X126: Propiedad Empresa | Y126: ESTIMADO | Z126: 30 | AA126: SI | AB126: 24 | AC126: VALLEDUPAR | AD126: NO | AE126: NO | AF126: INFO_CONSOL_ESPECIALES | AG126: Comercial Liberalizado | AH126: Actividades de planes de | AI126: 46063 | AJ126: GUATAPURI 6 | AK126: 912640 | AL126: #N/A | AM126: #N/A | AN126: RECIBIDO | AO126: =_xlfn.XLOOKUP(Tabla1[[#This Row],[NIC]],'R.V.'!B:B,'R.V.'!I:I) -> 0 | AP126: =_xlfn.XLOOKUP(Tabla1[[#This Row],[NIC]],'R.V.'!B:B,'R.V.'!A:A) -> Rosmeri Rivera Rodriguez | AQ126: =_xlfn.XLOOKUP(Tabla1[[#This Row],[NIC]],'R.V.'!B:B,'R.V.'!G:G) -> CR 9 16A 48 - VALLEDUPAR | AR126: =_xlfn.XLOOKUP(Tabla1[[#This Row],[NIC]],'R.V.'!B:B,'R.V.'!E:E) -> PRIVADO | AS126: =VLOOKUP(Tabla1[[#This Row],[NIC]],'R.V.'!B:D,3,0)
... A155: 7537844 | B155: 46111 | C155: SRS. AGROPECUARIA CA | D155: SRS. AGROPECUARIA CA | E155: NOVALITO VALLEDUPAR CR 7 10-44 APTO 702 | F155: 7537844 | G155: 7537844232 | H155: 35159714 | I155: 8476060 | J155: 3110 | K155: 72 | L155: 1210 | M155: 46101 | N155: IY3 | O155: Ind(Mon.dbl.Tip2Niv.3)E.Caribe | P155: 13259840 | Q155: 15600 | R155: 11874480 | T155: 63110EN0023524324200100721210003330 | U155: 46121 | V155: VALLEDUPAR | W155: NIVEL III | X155: Propiedad Cliente | Y155: MEDICION | Z155: 30 | AA155: SI | AB155: 31 | AC155: VALLEDUPAR | AD155: NO | AE155: NO | AF155: INFO_CONSOL_ESPECIALES | AG155: Industrial Liberalizado | AH155: Cultivo de palma para ace | AI155: 46071 | AJ155: LINEA 559 | AK155: 13259840 | AL155: #N/A | AM155: #N/A | AN155: RECIBIDO | AO155: =_xlfn.XLOOKUP(Tabla1[[#This Row],[NIC]],'R.V.'!B:B,'R.V.'!I:I) -> 0 | AP155: =_xlfn.XLOOKUP(Tabla1[[#This Row],[NIC]],'R.V.'!B:B,'R.V.'!A:A) -> Rosmeri Rivera Rodriguez | AQ155: =_xlfn.XLOOKUP(Tabla1[[#This Row],[NIC]],'R.V.'!B:B,'R.V.'!G:G) -> CR 7 # 10- 44 APTO 702 - VALLEDUPAR | AR155: =_xlfn.XLOOKUP(Tabla1[[#This Row],[NIC]],'R.V.'!B:B,'R.V.'!E:E) -> PRIVADO | AS155: =VLOOKUP(Tabla1[[#This Row],[NIC]],'R.V.'!B:D,3,0) -> AGROPECUARIA CAMPO VERDE LTDA
A156: 5303311 | B156: 46111 | C156: INVERSIONES TATIVAN | D156: INVERSIONES TATIVAN | E156: LOPERENA VALLEDUPAR CL 16A 9-50 | F156: 5303311 | G156: 5303311332 | H156: 25328964 | I156: 7747617 | J156: 3110 | K156: 50 | L156: 2002 | P156: 4688930 | Q156: 0 | R156: 0 | T156: 63110EN0022530325700100502002001882 | U156: 46121 | V156: VALLEDUPAR | Z156: 0 | AA156: SI | AB156: 32 | AC156: VALLEDUPAR | AD156: NO | AE156: NO | AF156: INFO_CONSOL_ESPECIALES | AG156: Comercial Liberalizado | AK156: 30648120 | AL156: #N/A | AM156: #N/A | AN156: RECIBIDO | AO156: =_xlfn.XLOOKUP(Tabla1[[#This Row],[NIC]],'R.V.'!B:B,'R.V.'!I:I) -> 0 | AP156: =_xlfn.XLOOKUP(Tabla1[[#This Row],[NIC]],'R.V.'!B:B,'R.V.'!A:A) -> Rosmeri Rivera Rodriguez | AQ156: =_xlfn.XLOOKUP(Tabla1[[#This Row],[NIC]],'R.V.'!B:B,'R.V.'!G:G) -> CL 16A, 9 50 - VALLEDUPAR | AR156: =_xlfn.XLOOKUP(Tabla1[[#This Row],[NIC]],'R.V.'!B:B,'R.V.'!E:E) -> PRIVADO | AS156: =VLOOKUP(Tabla1[[#This Row],[NIC]],'R.V.'!B:D,3,0)
A157: 5304070 | B157: 46111 | C157: JUAN CARLOS JAIME HO | D157: JUAN CARLOS JAIME HO | E157: LAS CASITAS VALLEDUPAR CARRT VIA A LA PAZ KM 0-545 | F157: 5304070 | G157: 5304070327 | H157: 25357920 | I157: 5308114 | J157: 3110 | K157: 50 | L157: 2006 | M157: 46108 | N157: CZ1 | O157: Com (Sencilla Niv.1 ) Caribe | P157: 5614510 | Q157: 4400 | R157: 4842904 | T157: 63110EN0022530401400100502006001880 | U157: 46121 | V157: VALLEDUPAR | W157: NIVEL I | X157: Propiedad Empresa | Y157: MEDICION | Z157: 32 | AA157: SI | AB157: 33 | AC157: VALLEDUPAR | AD157: NO | AE157: NO | AF157: INFO_CONSOL_ESPECIALES | AG157: Comercial Liberalizado | AH157: Alojamiento en hoteles. | AI157: 46076 | AJ157: SALGUERO 2 | AK157: 5614510 | AL157: #N/A | AM157: #N/A | AN157: RECIBIDO | AO157: =_xlfn.XLOOKUP(Tabla1[[#This Row],[NIC]],'R.V.'!B:B,'R.V.'!I:I) -> 0 | AP157: =_xlfn.XLOOKUP(Tabla1[[#This Row],[NIC]],'R.V.'!B:B,'R.V.'!A:A) -> Rosmeri Rivera Rodriguez | AQ157: =_xlfn.XLOOKUP(Tabla1[[#This Row],[NIC]],'R.V.'!B:B,'R.V.'!G:G) -> CARRT VIA A LA PAZ, KM 0 - VALLEDUPAR | AR157: =_xlfn.XLOOKUP(Tabla1[[#This Row],[NIC]],'R.V.'!B:B,'R.V.'!E:E) -> PRIVADO | AS157: =VLOOKUP(Tabla1[[#This Row],[NIC]],'R.V.'!B:D,3,0) -> FUNERARIA SENDEROS
A158: 5305313 | B158: 46111 | C158: SRES CLUB DE LEONES | D158: SRES CLUB DE LEONES | E158: 1 DE MAYO VALLEDUPAR CR 19 22A-25 | F158: 5305313 | G158: 5305313326 | H158: 25300294 | I158: 5310600 | J158: 3110 | K158: 50 | L158: 2008 | M158: 46101 | N158: CZ1 | O158: Com (Sencilla Niv.1 ) Caribe | P158: 10464090 | Q158: 8560 | R158: 9070004.8 | T158: 63110EN0022530525400100502008001360 | U158: 46121 | V158: VALLEDUPAR | W158: NIVEL I | X158: Propiedad Cliente | Y158: MEDICION | Z158: 30 | AA158: SI | AB158: 34 | AC158: VALLEDUPAR | AD158: NO | AE158: NO | AF158: INFO_CONSOL_ESPECIALES | AG158: Comercial Liberalizado | AH158: Actividades de atención | AI158: 46071 | AJ158: SALGUERO 3 | AK158: 10464090 | AL158: #N/A | AM158: #N/A | AN158: RECIBIDO | AO158: =_xlfn.XLOOKUP(Tabla1[[#This Row],[NIC]],'R.V.'!B:B,'R.V.'!I:I) -> 0 | AP158: =_xlfn.XLOOKUP(Tabla1[[#This Row],[NIC]],'R.V.'!B:B,'R.V.'!A:A) -> Rosmeri Rivera Rodriguez | AQ158: =_xlfn.XLOOKUP(Tabla1[[#This Row],[NIC]],'R.V.'!B:B,'R.V.'!G:G) -> CR 19, 22A 25 IPS KANKUAMA - VALLEDUPAR | AR158: =_xlfn.XLOOKUP(Tabla1[[#This Row],[NIC]],'R.V.'!B:B,'R.V.'!E:E) -> PRIVADO | AS158: =VLOOKUP(Tabla1[[#This Row],[NIC]],'R.V.'!B:D,3,0)
A159: 5308749 | B159: 46111 | C159: HOTEL EUPARI PROTUR | D159: HOTEL EUPARI PROTUR | E159: CAÑAGUATE VALLEDUPAR CR 6 13B-31 | F159: 5308749 | G159: 5308749324 | H159: 25308507 | I159: 5317472 | J159: 3110 | K159: 50 | L159: 2004 | M159: 46102 | N159: CZ1 | O159: Com (Sencilla Niv.1 ) Caribe | P159: 3024450 | Q159: 2320 | R159: 2553531.2 | T159: 63110EN0022530868600100502004001300 | U159: 46121 | V159: VALLEDUPAR | W159: NIVEL I | X159: Propiedad Empresa | Y159: MEDICION | Z159: 30 | AA159: SI | AB159: 35 | AC159: VALLEDUPAR | AD159: NO | AE159: NO | AF159: INFO_CONSOL_ESPECIALES | AG159: Comercial Liberalizado | AH159: Alojamiento en hoteles. | AI159: 46072 | AJ159: GUATAPURI 2 | AK159: 3024450 | AL159: #N/A | AM159: #N/A | AN159: RECIBIDO | AO159: =_xlfn.XLOOKUP(Tabla1[[#This Row],[NIC]],'R.V.'!B:B,'R.V.'!I:I) -> 0 | AP159: =_xlfn.XLOOKUP(Tabla1[[#This Row],[NIC]],'R.V.'!B:B,'R.V.'!A:A) -> Rosmeri Rivera Rodriguez | AQ159: =_xlfn.XLOOKUP(Tabla1[[#This Row],[NIC]],'R.V.'!B:B,'R.V.'!G:G) -> CR 6, 13B 31 112 - VALLEDUPAR | AR159: =_xlfn.XLOOKUP(Tabla1[[#This Row],[NIC]],'R.V.'!B:B,'R.V.'!E:E) -> PRIVADO | AS159: =VLOOKUP(Tabla1[[#This Row],[NIC]],'R.V.'!B:D,3,0)
A160: 5310091 | B160: 46111 | C160: SRES. BENAVIDES GIRA ANATOLIO SEGUNDO | D160: SRES. BENAVIDES GIRA ANATOLIO SEGUNDO | E160: LOS ANGELES VALLEDUPAR CL 6C CR 13A-50 | F160: 5310091 | G160: 5310091351 | H160: 25341425 | I160: 7640522 | J160: 3110 | K160: 50 | L160: 2004 | P160: 1509520 | Q160: 0 | R160: 0 | T160: 63110EN0023400737700100502004000680 | U160: 46121 | V160: VALLEDUPAR | Z160: 0 | AA160: SI | AB160: 36 | AC160: VALLEDUPAR | AD160: NO | AE160: NO | AF160: INFO_CONSOL_ESPECIALES | AG160: Industrial Liberalizado | AK160: 10860950 | AL160: #N/A | AM160: #N/A | AN160: RECIBIDO | AO160: =_xlfn.XLOOKUP(Tabla1[[#This Row],[NIC]],'R.V.'!B:B,'R.V.'!I:I) -> 0 | AP160: =_xlfn.XLOOKUP(Tabla1[[#This Row],[NIC]],'R.V.'!B:B,'R.V.'!A:A) -> Rosmeri Rivera Rodriguez | AQ160: =_xlfn.XLOOKUP(Tabla1[[#This Row],[NIC]],'R.V.'!B:B,'R.V.'!G:G) -> CL 6C, 13A 44 - VALLEDUPAR | AR160: =_xlfn.XLOOKUP(Tabla1[[#This Row],[NIC]],'R.V.'!B:B,'R.V.'!E:E) -> PRIVADO | AS160: =VLOOKUP(Tabla1[[#This Row],[NIC]],'R.V.'!B:D,3,0)
A161: 5324315 | B161: 46111 | C161: AREAS COMUNES TERMIN | D161: AREAS COMUNES TERMIN | E161: 25 DE DICIEMBRE VALLEDUPAR CR 7A 44-156 | F161: 5324315 | G161: 5324315342 | H161: 25303331 | I161: 5348604 | J161: 3110 | K161: 6 | L161: 1205 | M161: 46109 | N161: CY2 | O161: Com(Mon.dbl.Tip2Niv.2)Caribe | P161: 22958790 | Q161: 22194 | R161: 16282855 | T161: 63110EN0022532421200100061205000240 | U161: 46121 | V161: VALLEDUPAR | W161: NIVEL II | X161: Propiedad Empresa | Y161: MEDICION | Z161: 32 | AA161: SI | AB161: 37 | AC161: VALLEDUPAR | AD161: NO | AE161: NO | AF161: INFO_CONSOL_ESPECIALES | AG161: Comercial Liberalizado | AH161: Areas Comunes | AI161: 46077 | AJ161: SALGUERO 2 | AK161: 730596251 | AL161: #N/A | AM161: #N/A | AN161: RECIBIDO | AO161: =_xlfn.XLOOKUP(Tabla1[[#This Row],[NIC]],'R.V.'!B:B,'R.V.'!I:I) -> 0 | AP161: =_xlfn.XLOOKUP(Tabla1[[#This Row],[NIC]],'R.V.'!B:B,'R.V.'!A:A) -> Rosmeri Rivera Rodriguez | AQ161: =_xlfn.XLOOKUP(Tabla1[[#This Row],[NIC]],'R.V.'!B:B,'R.V.'!G:G) -> TERMINAL DE TRANSPORTE - VALLEDUPAR | AR161: =_xlfn.XLOOKUP(Tabla1[[#This Row],[NIC]],'R.V.'!B:B,'R.V.'!E:E) -> PRIVADO | AS161: =VLOOKUP(Tabla1[[#This Row],[NIC]],'R.V.'!B:D,3,0) -> AREAS COMUNES TERMINAL
A162: 5324634 | B162: 46111 | C162: CENTRO DIAGNOSTICO A VALLEDUPAR SAS | D162: CENTRO DIAGNOSTICO A VALLEDUPAR SAS | E162: SAN FERNANDO VALLEDUPAR CR 18D CL 47-17 | F162: 5324634 | G162: 5324634349 | H162: 25357882 | I162: 5349242 | J162: 3110 | K162: 60 | L162: 1 | M162: 46082 | N162: CZ1 | O162: Com (Sencilla Niv.1 ) Caribe | P162: 2695600 | Q162: 1983 | R162: 2003147.3 | T162: 63110EN0023458664600100600001009280 | U162: 46121 | V162: VALLEDUPAR | W162: NIVEL I | X162: Propiedad Cliente | Y162: MEDICION | Z162: 28 | AA162: SI | AB162: 38 | AC162: VALLEDUPAR | AD162: NO | AE162: NO | AF162: INFO_CONSOL_ESPECIALES | AG162: Comercial Liberalizado | AH162: Ensayos y análisis técnic | AI162: 46054 | AJ162: SALGUERO 2 | AK162: 3134760 | AL162: #N/A | AM162: #N/A | AN162: RECIBIDO | AO162: =_xlfn.XLOOKUP(Tabla1[[#This Row],[NIC]],'R.V.'!B:B,'R.V.'!I:I) -> 0 | AP162: =_xlfn.XLOOKUP(Tabla1[[#This Row],[NIC]],'R.V.'!B:B,'R.V.'!A:A) -> Rosmeri Rivera Rodriguez | AQ162: =_xlfn.XLOOKUP(Tabla1[[#This Row],[NIC]],'R.V.'!B:B,'R.V.'!G:G) -> CR 7A, 46 12 142 CE - VALLEDUPAR | AR162: =_xlfn.XLOOKUP(Tabla1[[#This Row],[NIC]],'R.V.'!B:B,'R.V.'!E:E) -> PRIVADO | AS162: =VLOOKUP(Tabla1[[#This Row],[NIC]],'R.V.'!B:D,3,0) -> CDA DEL CESAR
A163: 5328364 | B163: 46111 | C163: AUTOESTE SAS | D163: AUTOESTE SAS | E163: SAN JORGE VALLEDUPAR CR 7A 20D-15 | F163: 5328364 | G163: 5328364338 | H163: 25339422 | I163: 5356702 | J163: 3110 | K163: 7 | L163: 1304 | M163: 46084 | N163: CZ1 | O163: Com (Sencilla Niv.1 ) Caribe | P163: 6528240 | Q163: 5566 | R163: 5622550.6 | T163: 63110EN0023613974300100071304000997 | U163: 46121 | V163: VALLEDUPAR | W163: NIVEL I | X163: Propiedad Cliente | Y163: MEDICION | Z163: 29 | AA163: SI | AB163: 39 | AC163: VALLEDUPAR | AD163: NO | AE163: NO | AF163: INFO_CONSOL_ESPECIALES | AG163: Comercial Liberalizado | AH163: Comercio de vehículos aut | AI163: 46055 | AJ163: SALGUERO 1 | AK163: 6528240 | AL163: #N/A | AM163: #N/A | AN163: RECIBIDO | AO163: =_xlfn.XLOOKUP(Tabla1[[#This Row],[NIC]],'R.V.'!B:B,'R.V.'!I:I) -> 0 | AP163: =_xlfn.XLOOKUP(Tabla1[[#This Row],[NIC]],'R.V.'!B:B,'R.V.'!A:A) -> Rosmeri Rivera Rodriguez | AQ163: =_xlfn.XLOOKUP(Tabla1[[#This Row],[NIC]],'R.V.'!B:B,'R.V.'!G:G) -> CR 7A 20D 15 - VALLEDUPAR | AR163: =_xlfn.XLOOKUP(Tabla1[[#This Row],[NIC]],'R.V.'!B:B,'R.V.'!E:E) -> PRIVADO | AS163: =VLOOKUP(Tabla1[[#This Row],[NIC]],'R.V.'!B:D,3,0)
A164: 5328685 | B164: 46111 | C164: OCHOA DAZA VICTOR JOAQUIN | D164: OCHOA DAZA VICTOR JOAQUIN | E164: LOS CACIQUES VALLEDUPAR DG 20B CR 19-78 | F164: 5328685 | G164: 5328685328 | H164: 25330076 | I164: 5357344 | J164: 3110 | K164: 50 | L164: 2005 | M164: 46106 | N164: CZ1 | O164: Com (Sencilla Niv.1 ) Caribe | P164: 3744750 | Q164: 2320 | R164: 2553531.2 | T164: 63110EN0022532855900100502005001770 | U164: 46121 | V164: VALLEDUPAR | W164: NIVEL I | X164: Propiedad Empresa | Y164: MEDICION | Z164: 32 | AA164: SI | AB164: 40 | AC164: VALLEDUPAR | AD164: NO | AE164: NO | AF164: INFO_CONSOL_ESPECIALES | AG164: Comercial Liberalizado | AH164: Explotación mixta (agríco | AI164: 46074 | AJ164: GUATAPURI 5 | AK164: 5252470 | AL164: #N/A | AM164: #N/A | AN164: RECIBIDO | AO164: =_xlfn.XLOOKUP(Tabla1[[#This Row],[NIC]],'R.V.'!B:B,'R.V.'!I:I) -> 0 | AP164: =_xlfn.XLOOKUP(Tabla1[[#This Row],[NIC]],'R.V.'!B:B,'R.V.'!A:A) -> Rosmeri Rivera Rodriguez | AQ164: =_xlfn.XLOOKUP(Tabla1[[#This Row],[NIC]],'R.V.'!B:B,'R.V.'!G:G) -> DG 20B, 19 36 181 - VALLEDUPAR | AR164: =_xlfn.XLOOKUP(Tabla1[[#This Row],[NIC]],'R.V.'!B:B,'R.V.'!E:E) -> PRIVADO | AS164: =VLOOKUP(Tabla1[[#This Row],[NIC]],'R.V.'!B:D,3,0)
A165: 5329183 | B165: 46111 | C165: HOTEL DAMAR | D165: HOTEL DAMAR | E165: CENTRO VALLEDUPAR CR 9 19-94 | F165: 5329183 | G165: 5329183335 | H165: 25357910 | I165: 5358340 | J165: 3110 | K165: 50 | L165: 2002 | M165: 46102 | N165: CZ1 | O165: Com (Sencilla Niv.1 ) Caribe | P165: 8540350 | Q165: 6960 | R165: 7374676.8 | T165: 63110EN0022532905700100502002001682 | U165: 46121 | V165: VALLEDUPAR | W165: NIVEL I | X165: Propiedad Cliente | Y165: MEDICION | Z165: 30 | AA165: SI | AB165: 41 | AC165: VALLEDUPAR | AD165: NO | AE165: NO | AF165: INFO_CONSOL_ESPECIALES | AG165: Comercial Liberalizado | AH165: Alojamiento en hoteles. | AI165: 46072 | AJ165: SALGUERO 1 | AK165: 8540350 | AL165: #N/A | AM165: #N/A | AN165: RECIBIDO | AO165: =_xlfn.XLOOKUP(Tabla1[[#This Row],[NIC]],'R.V.'!B:B,'R.V.'!I:I) -> 0 | AP165: =_xlfn.XLOOKUP(Tabla1[[#This Row],[NIC]],'R.V.'!B:B,'R.V.'!A:A) -> Rosmeri Rivera Rodriguez | AQ165: =_xlfn.XLOOKUP(Tabla1[[#This Row],[NIC]],'R.V.'!B:B,'R.V.'!G:G) -> CR 9, 19 94 - VALLEDUPAR | AR165: =_xlfn.XLOOKUP(Tabla1[[#This Row],[NIC]],'R.V.'!B:B,'R.V.'!E:E) -> PRIVADO | AS165: =VLOOKUP(Tabla1[[#This Row],[NIC]],'R.V.'!B:D,3,0)
A166: 5329253 | B166: 46111 | C166: SR FUNERARIA SENDERO | D166: INVERSIONES PLANES DEL PAZ | E166: 5 DE NOVIEMBRE VALLEDUPAR CR 7A 22-39 | F166: 5329253 | G166: 5329253313 | H166: 25304129 | I166: 5358480 | J166: 3110 | K166: 7 | L166: 1305 | M166: 46108 | N166: CZ1 | O166: Com (Sencilla Niv.1 ) Caribe | P166: 5938230 | Q166: 4320 | R166: 4577385.6 | T166: 63110EN0023458012000100071305000030 | U166: 46121 | V166: VALLEDUPAR | W166: NIVEL I | X166: Propiedad Cliente | Y166: MEDICION | Z166: 32 | AA166: SI | AB166: 42 | AC166: VALLEDUPAR | AD166: NO | AE166: NO | AF166: INFO_CONSOL_ESPECIALES | AG166: Comercial Liberalizado | AH166: Pompas fúnebres y activid | AI166: 46076 | AJ166: SALGUERO 1 | AK166: 10540880 | AL166: #N/A | AM166: #N/A | AN166: RECIBIDO | AO166: =_xlfn.XLOOKUP(Tabla1[[#This Row],[NIC]],'R.V.'!B:B,'R.V.'!I:I) -> 0 | AP166: =_xlfn.XLOOKUP(Tabla1[[#This Row],[NIC]],'R.V.'!B:B,'R.V.'!A:A) -> Rosmeri Rivera Rodriguez | AQ166: =_xlfn.XLOOKUP(Tabla1[[#This Row],[NIC]],'R.V.'!B:B,'R.V.'!G:G) -> CR 7A, 22 51 - VALLEDUPAR | AR166: =_xlfn.XLOOKUP(Tabla1[[#This Row],[NIC]],'R.V.'!B:B,'R.V.'!E:E) -> PRIVADO | AS166: =VLOOKUP(Tabla1[[#This Row],[NIC]],'R.V.'!B:D,3,0)
A167: 6853013 | B167: 46111 | C167: SR FUNERARIA SENDERO | D167: INVERSIONES PLANES DEL PAZ | E167: 5 DE NOVIEMBRE VALLEDUPAR CR 7A 22-39 | F167: 6853013 | G167: 6853013242 | H167: 34552150 | I167: 7331041 | J167: 3110 | K167: 7 | L167: 1305 | M167: 46084 | N167: CZ1 | O167: Com (Sencilla Niv.1 ) Caribe | P167: 886300 | Q167: 650 | R167: 656604 | T167: 63110EN0023458012000100071305000030 | U167: 46121 | V167: VALLEDUPAR | W167: NIVEL I | X167: Propiedad Cliente | Y167: MEDICION | Z167: 29 | AA167: SI | AB167: 42 | AC167: VALLEDUPAR | AD167: NO | AE167: NO | AF167: INFO_CONSOL_ESPECIALES | AG167: Comercial Liberalizado | AH167: Pompas fúnebres y activid | AI167: 46055 | AJ167: SALGUERO 1 | AK167: 1805910 | AL167: #N/A | AM167: #N/A | AN167: RECIBIDO | AO167: =_xlfn.XLOOKUP(Tabla1[[#This Row],[NIC]],'R.V.'!B:B,'R.V.'!I:I) -> 0 | AP167: =_xlfn.XLOOKUP(Tabla1[[#This Row],[NIC]],'R.V.'!B:B,'R.V.'!A:A) -> Rosmeri Rivera Rodriguez | AQ167: =_xlfn.XLOOKUP(Tabla1[[#This Row],[NIC]],'R.V.'!B:B,'R.V.'!G:G) -> CR 7A, 22 52 - VALLEDUPAR | AR167: =_xlfn.XLOOKUP(Tabla1[[#This Row],[NIC]],'R.V.'!B:B,'R.V.'!E:E) -> PRIVADO | AS167: =VLOOKUP(Tabla1[[#This Row],[NIC]],'R.V.'!B:D,3,0)
A168: 5329315 | B168: 46111 | C168: SR LADRI ECCEHOMO AM | D168: SR LADRI ECCEHOMO AM | E168: LAS CASITAS VALLEDUPAR CARRT VIA A LA PAZ KM 4-105 | F168: 5329315 | G168: 5329315339 | H168: 25357898 | I168: 5358604 | J168: 3110 | K168: 50 | L168: 2012 | M168: 46105 | N168: IZ1 | O168: Ind (Sencilla Niv.1) E.Caribe | P168: 18030910 | Q168: 16800 | R168: 15409296 | T168: 63110EN0022532918900100502012001201 | U168: 46121 | V168: VALLEDUPAR | W168: NIVEL I | X168: Propiedad Empresa | Y168: MEDICION | Z168: 32 | AA168: SI | AB168: 43 | AC168: VALLEDUPAR | AD168: NO | AE168: NO | AF168: INFO_CONSOL_ESPECIALES | AG168: Industrial Liberalizado | AH168: Fabricación de materiales | AI168: 46073 | AJ168: SALGUERO 2 | AK168: 28406350 | AL168: #N/A | AM168: #N/A | AN168: RECIBIDO | AO168: =_xlfn.XLOOKUP(Tabla1[[#This Row],[NIC]],'R.V.'!B:B,'R.V.'!I:I) -> 0 | AP168: =_xlfn.XLOOKUP(Tabla1[[#This Row],[NIC]],'R.V.'!B:B,'R.V.'!A:A) -> Rosmeri Rivera Rodriguez | AQ168: =_xlfn.XLOOKUP(Tabla1[[#This Row],[NIC]],'R.V.'!B:B,'R.V.'!G:G) -> LADRILLERA ECCE HOMMO - VALLEDUPAR | AR168: =_xlfn.XLOOKUP(Tabla1[[#This Row],[NIC]],'R.V.'!B:B,'R.V.'!E:E) -> PRIVADO | AS168: =VLOOKUP(Tabla1[[#This Row],[NIC]],'R.V.'!B:D,3,0)
...

Sheet FISICOS
A1: SIM | B1: OBSERVACIONES | C1: Columna1
A2: 590001300 | B2: RECIBIDO | C2: =Tabla3[[#This Row],[SIM]]=A3 -> FALSE
A3: 1000367077 | B3: RECIBIDO | C3: =Tabla3[[#This Row],[SIM]]=A4 -> FALSE
A4: 1000614077 | B4: RECIBIDO | C4: =Tabla3[[#This Row],[SIM]]=A5 -> FALSE
A5: 1005534076 | B5: RECIBIDO | C5: =Tabla3[[#This Row],[SIM]]=A6 -> FALSE
A6: 1005831078 | B6: RECIBIDO | C6: =Tabla3[[#This Row],[SIM]]=A7 -> FALSE
A7: 1005832071 | B7: RECIBIDO | C7: =Tabla3[[#This Row],[SIM]]=A8 -> FALSE
A8: 1006054074 | B8: RECIBIDO | C8: =Tabla3[[#This Row],[SIM]]=A9 -> FALSE
A9: 1008001079 | B9: RECIBIDO | C9: =Tabla3[[#This Row],[SIM]]=A10 -> FALSE
A10: 1008609073 | B10: RECIBIDO | C10: =Tabla3[[#This Row],[SIM]]=A11 -> FALSE
A11: 1013144070 | B11: RECIBIDO | C11: =Tabla3[[#This Row],[SIM]]=A12 -> FALSE
A12: 1013145070 | B12: RECIBIDO | C12: =Tabla3[[#This Row],[SIM]]=A13 -> FALSE
A13: 1013146070 | B13: RECIBIDO | C13: =Tabla3[[#This Row],[SIM]]=A14 -> FALSE
... A1713: 7990133101 | B1713: RECIBIDO | C1713: =Tabla3[[#This Row],[SIM]]=A1714 -> FALSE

Sheet CENTRALIZADAS
A1: NIC | B1: TITULAR DE PAGO | C1: SEGMENTO | D1: SIGLAS EJECUTIVO | E1: EJECUTIVO DE CUENTA | F1: CENTRO DE IMPRESIÓN
A2: 1188609 | B2: ACONDESA SA | C2: SSGMTO | D2: egomezar | E2: Edmy De Jesus Gomez Ariza | F2: CARTAGENA
A3: 7885572 | B3: ACONDESA SA | C3: SSGMTO | D3: egomezar | E3: Edmy De Jesus Gomez Ariza | F3: CARTAGENA
A4: 7950277 | B4: ACONDESA SA | C4: SSGMTO | D4: egomezar | E4: Edmy De Jesus Gomez Ariza | F4: CARTAGENA
A5: 1197607 | B5: ALMACENES CORONA SAS | C5: SSGMTO | D5: egomezar | E5: Edmy De Jesus Gomez Ariza | F5: CARTAGENA
A6: 1197608 | B6: ALMACENES CORONA SAS | C6: SSGMTO | D6: egomezar | E6: Edmy De Jesus Gomez Ariza | F6: CARTAGENA
A7: 5331583 | B7: ALMACENES CORONA SAS | C7: SSGMTO | D7: egomezar | E7: Edmy De Jesus Gomez Ariza | F7: CARTAGENA
A8: 6558309 | B8: ALMACENES EXITO S A | C8: SSGMTO | D8: egomezar | E8: Edmy De Jesus Gomez Ariza | F8: CARTAGENA
A9: 6615693 | B9: ALMACENES EXITO S A | C9: SSGMTO | D9: egomezar | E9: Edmy De Jesus Gomez Ariza | F9: CARTAGENA
A10: 7871320 | B10: ALMACENES EXITO S A | C10: SSGMTO | D10: egomezar | E10: Edmy De Jesus Gomez Ariza | F10: CARTAGENA
A11: 7881802 | B11: ALMACENES EXITO S A | C11: SSGMTO | D11: egomezar | E11: Edmy De Jesus Gomez Ariza | F11: CARTAGENA
A12: 1263950 | B12: AMERICANO AVIANCA S.A. AEROVIAS DEL CONTINE | C12: SSGMTO | D12: egomezar | E12: Edmy De Jesus Gomez Ariza | F12: CARTAGENA
A13: 7768176 | B13: AMERICANO AVIANCA S.A. AEROVIAS DEL CONTINE | C13: SSGMTO | D13: egomezar | E13: Edmy De Jesus Gomez Ariza | F13: CARTAGENA
... A3992: 7555397 | B3992: VP GLOBAL LTDA | C3992: SSGMTO | D3992: egomezar | E3992: Edmy De Jesus Gomez Ariza | F3992: CARTAGENA

Sheet GESTION EJECUTIVOS
A1: NIC
A2: 1413166
A3: 5357495
A4: 5358999
A5: 5359176
A6: 5359669
A7: 5360243
A8: 5360245
A9: 5361891
A10: 5361969
A11: 6238148
A12: 6634302
A13: 6634330
... A330: 7958047
